Workbook

Sheet Living Wage Executive Summary
B1: Living Wage Executive Summary
B2: USD | C2: Canada | D2: GBP | E2: AUD | F2: Costa Rica | G2: Mexico
A3: Currency Conversion Rates (3/22) | B3: 1 | C3: 1.2511466 | D3: 0.75707513 | E3: 1.3299554 | F3: 0.0015 | G3: 0.0494685
A4: Local Currency to USD | B4: na | C4: 0.799184 | D4: 1.32105 | E4: 0.752089
A5: Local Living Wage | B5: 70000 | C5: 60000 | D5: 40000 | E5: 65000 | F5: 18141336 | G5: 600000
A6: $USD | B6: =B5 -> 70000 | C6: =C5*C4 -> 47951.04 | D6: =D5*D4 -> 52842 | E6: =E5*E4 -> 48885.785 | F6: 26574.74 | G6: =G3*G5 -> 29681.1
C7: =($B$5-C6)/$B$5 -> 0.31498514 | D7: =($B$5-D6)/$B$5 -> 0.24511429 | E7: =($B$5-E6)/$B$5 -> 0.30163164 | F7: =($B$5-F6)/$B$5 -> 0.62036086 | G7: =($B$5-G6)/$B$5 -> 0.57598429
A8: Standard of Measurement: | B8: 2 working parents, 2 kids (4 y/o, 12 y/o)
A10: Source | B10: Living Wage - MIT | C10: Ontario Policy Study | D10: Minimum Wage Income - UK | E10: UofMelbourn - iving Wage | F10: Wage Indicator | G10: Wage Indicator
D11: Living Wage Calc | F11: Trading Economics | G11: Trading Economics
F12: https://www.expatistan.com/cost-of-living/country/costa-rica | G12: https://www.expatistan.com/cost-of-living/country/mexico

Sheet Payroll Benefit Costs
B1: Total Benefit & Tax Burden Per Country | K1: Currency Calculator | L1: CAD | M1: GBP | N1: AUD
B2: Canada | D2: UK | F2: Australia | K2: $1 USD | L2: 1.26 | M2: 0.77 | N2: 1.36
B3: Amount | C3: Percent | D3: Amount | E3: Percent | F3: Amount | G3: Percent
A4: Annual Salary (Local Currency) | B4: ='Living Wage Executive Summary'!C5 -> 60000 | D4: ='Living Wage Executive Summary'!D5 -> 40000 | F4: ='Living Wage Executive Summary'!E5 -> 65000 | L4: USD
A5: Monthly Base | B5: ='Living Wage Executive Summary'!C5/12 -> 5000 | D5: ='Living Wage Executive Summary'!D5/12 -> 3333.3333 | F5: ='Living Wage Executive Summary'!E5/12 -> 5416.6667 | K5: CAD | L5: 0.79
A6: National Insurance | D6: =E6*$D$5 -> 460 | E6: 0.138 | F6: =G6*$F$5 -> 54.166667 | G6: 0.01 | K6: GBP | L6: 1.3
A7: Pension | B7: 210.53 | C7: =B7/$B$5 -> 0.042106 | D7: =E7*$D$5 -> 100 | E7: 0.03 | F7: =G7*$F$5 -> 541.66667 | G7: 0.1 | K7: AUD | L7: 0.73
A8: Private Pension | B8: 100 | C8: =B8/$B$5 -> 0.02 | D8: =E8*$D$5 -> 133.33333 | E8: 0.04
A9: Superannuation | F9: =G9*$F$5 -> 162.5 | G9: 0.03
A10: Private Health Insurance | B10: 269.64 | C10: =B10/$B$5 -> 0.053928 | D10: =E10*$D$5 -> 223.33333 | E10: 0.067
A11: Employment Ins. | B11: 79 | C11: =B11/$B$5 -> 0.0158 | D11: =E11*$D$5 -> 0
A12: Payroll Tax | F12: =G12*$F$5 -> 295.20833 | G12: 0.0545
A13: Provincial Tax | B13: 97.5 | C13: =B13/$B$5 -> 0.0195 | D13: =E13*$D$5 -> 0
A14: PEO Currency Fee | B14: 115.03 | C14: =B14/$B$5 -> 0.023006 | D14: =E14*$D$5 -> 86.666667 | E14: 0.026 | F14: =G14*$F$5 -> 130 | G14: 0.024
A16: Total Benefits | B16: =SUM(B6:B15) -> 871.7 | C16: =SUM(C7:C14) -> 0.17434 | D16: =SUM(D6:D15) -> 1003.3333 | E16: =SUM(E6:E14) -> 0.301 | F16: =SUM(F6:F15) -> 1183.5417 | G16: =SUM(G6:G14) -> 0.2185
A17: Total Cost | B17: =SUM(B5:B15) -> 5871.7 | D17: =SUM(D5:D15) -> 4336.6667 | F17: =SUM(F5:F15) -> 6600.2083
A18: Annualized Total Cost - Local Currency | B18: =B17*12 -> 70460.4 | D18: =D17*12 -> 52040 | F18: =F17*12 -> 79202.5
A19: Annualized Total Cost USD | B19: =B18*L5 -> 55663.716 | D19: =D18*L6 -> 67652 | F19: =F18*L7 -> 57817.825
A21: Pay Frequency | B21: Every other Friday | D21: Last Working Day of Month | F21: Monthly

Sheet Global Analysis
B1: Total Population | C1: Digtial Marketer Population | D1: High level LinkedIn Search (Country + Marketing/Advertising)
A2: United States | B2: 332.4M | C2: 256171 | D2: 2.3M
A3: Canada | B3: 38.2M | C3: 29951 | D3: 230k
A4: United Kingdom | B4: 67.8M | C4: 22000 | D4: 370k
A5: Australia | B5: 26.1M | C5: 36000 | D5: 150k
A6: Costa Rica | B6: 5.2M | D6: 16k

Sheet Platforms
A1: General HR Platforms
B2: US | C2: Canada | D2: UK | E2: Australia
A3: Payroll | B3: Zenefits | C3: Omnipresent | D3: Omnipresent | E3: Omnipresent
A4: Reimbursements | B4: Liquid | C4: Omnipresent | D4: Omnipresent | E4: Omnipresent
A5: Travel Scheduling | B5: TripActions | C5: TripActions | D5: TripActions | E5: TripActions
A6: PTO | B6: Zenefits | C6: Zenefits | D6: Zenefits | E6: Zenefits
A7: Holidays | B7: Zenefits | C7: Zenefits | D7: Zenefits | E7: Zenefits
A8: Org Chart | B8: Zenefits | C8: Zenefits | D8: Zenefits | E8: Zenefits
A9: Benefits | B9: Sequoia | C9: Omnipresent | D9: Omnipresent | E9: Omnipresent
A10: Retirement | B10: ForUsAll | C10: Omnipresent | D10: Omnipresent | E10: Omnipresent
