Workbook

Sheet Qx Example
C1: This Quarter Actuals | J1: Cell Color Legend
A2: Current Details | B2: Model | C2: Google | D2: LinkedIn | E2: Microsoft | F2: Facebook | G2: Directories | H2: Total | J2: Input Raw Data
A3: Total Spend | B3: 60000 | C3: 30000 | D3: 30000 | E3: 30000 | F3: 40000 | G3: 60000 | H3: =SUM(C3:G3) -> 190000 | J3: Totals
A4: Leads | B4: 18000 | C4: 160 | D4: 160 | E4: 160 | F4: 160 | G4: 160 | H4: =SUM(C4:G4) -> 800 | J4: Formulas
A5: MQLs | B5: 8000 | C5: 100 | D5: 100 | E5: 100 | F5: 100 | G5: 100 | H5: =SUM(C5:G5) -> 500
A6: SALs | B6: 2700 | C6: 80 | D6: 80 | E6: 80 | F6: 80 | G6: 80 | H6: =SUM(C6:G6) -> 400
A7: SQLs | B7: 1300 | C7: 60 | D7: 60 | E7: 60 | F7: 60 | G7: 60 | H7: =SUM(C7:G7) -> 300
A8: Opps | B8: 600 | C8: 20 | D8: 20 | E8: 20 | F8: 20 | G8: 20 | H8: =SUM(C8:G8) -> 100
A9: Customers | B9: 60 | C9: 10 | D9: 10 | E9: 10 | F9: 10 | G9: 10 | H9: =SUM(C9:G9) -> 50
A10: Est. Bookings (Annual) | B10: =iferror((B9*B29)*12,"") -> 360000 | C10: =iferror((C9*C29)*12,"") -> 60000 | D10: =iferror((D9*D29)*12,"") -> 60000 | E10: =iferror((E9*E29)*12,"") -> 60000 | F10: =iferror((F9*F29)*12,"") -> 60000 | G10: =iferror((G9*G29)*12,"") -> 60000 | H10: =sum(B10:G10) -> 660000
A11: Cost-Per-Lead | B11: =iferror(B3/B4,"") -> 3.3333333 | C11: =iferror(C3/C4,"") -> 187.5 | D11: =iferror(D3/D4,"") -> 187.5 | E11: =iferror(E3/E4,"") -> 187.5 | F11: =iferror(F3/F4,"") -> 250 | G11: =iferror(G3/G4,"") -> 375 | H11: =iferror(H3/H4,"") -> 237.5
A12: Cost-Per-MQL | B12: =iferror(B3/B5,"") -> 7.5 | C12: =iferror(C3/C5,"") -> 300 | D12: =iferror(D3/D5,"") -> 300 | E12: =iferror(E3/E5,"") -> 300 | F12: =iferror(F3/F5,"") -> 400 | G12: =iferror(G3/G5,"") -> 600 | H12: =iferror(H3/H5,"") -> 380
A13: Cost-Per-SAL | B13: =iferror(B3/B6,"") -> 22.222222 | C13: =iferror(C3/C6,"") -> 375 | D13: =iferror(D3/D6,"") -> 375 | E13: =iferror(E3/E6,"") -> 375 | F13: =iferror(F3/F6,"") -> 500 | G13: =iferror(G3/G6,"") -> 750 | H13: =iferror(H3/H6,"") -> 475
A14: Cost-Per-SQL | B14: =iferror(B3/B7,"") -> 46.153846 | C14: =iferror(C3/C7,"") -> 500 | D14: =iferror(D3/D7,"") -> 500 | E14: =iferror(E3/E7,"") -> 500 | F14: =iferror(F3/F7,"") -> 666.66667 | G14: =iferror(G3/G7,"") -> 1000 | H14: =iferror(H3/H7,"") -> 633.33333
A15: Cost-Per-Opp | B15: =iferror(B3/B8,"") -> 100 | C15: =iferror(C3/C8,"") -> 1500 | D15: =iferror(D3/D8,"") -> 1500 | E15: =iferror(E3/E8,"") -> 1500 | F15: =iferror(F3/F8,"") -> 2000 | G15: =iferror(G3/G8,"") -> 3000 | H15: =iferror(H3/H8,"") -> 1900
A16: Cost-Per-Customer | B16: =iferror(B3/B9,"") -> 1000 | C16: =iferror(C3/C9,"") -> 3000 | D16: =iferror(D3/D9,"") -> 3000 | E16: =iferror(E3/E9,"") -> 3000 | F16: =iferror(F3/F9,"") -> 4000 | G16: =iferror(G3/G9,"") -> 6000 | H16: =iferror(H3/H9,"") -> 3800
A18: Current Details | B18: =B2 -> Model | C18: =C2 -> Google | D18: =D2 -> LinkedIn | E18: =E2 -> Microsoft | F18: =F2 -> Facebook | G18: =G2 -> Directories | H18: =H2 -> Total
A19: Avg. Contract Value (Annual) | B19: =iferror(B10/B9,"") -> 6000 | C19: =iferror(C10/C9,"") -> 6000 | D19: =iferror(D10/D9,"") -> 6000 | E19: =iferror(E10/E9,"") -> 6000 | F19: =iferror(F10/F9,"") -> 6000 | G19: =iferror(G10/G9,"") -> 6000 | H19: =iferror(H10/H9,"") -> 13200
A20: Opp > Customer (Close Rate) | B20: =iferror(B9/B8,"") -> 0.1 | C20: =iferror(C9/C8,"") -> 0.5 | D20: =iferror(D9/D8,"") -> 0.5 | E20: =iferror(E9/E8,"") -> 0.5 | F20: =iferror(F9/F8,"") -> 0.5 | G20: =iferror(G9/G8,"") -> 0.5 | H20: =iferror(H9/H8,"") -> 0.5
A21: Lead > MQL | B21: =iferror(B5/B4,"") -> 0.44444444 | C21: =iferror(C5/C4,"") -> 0.625 | D21: =iferror(D5/D4,"") -> 0.625 | E21: =iferror(E5/E4,"") -> 0.625 | F21: =iferror(F5/F4,"") -> 0.625 | G21: =iferror(G5/G4,"") -> 0.625 | H21: =iferror(H5/H4,"") -> 0.625
A22: MQL > SAL | B22: =iferror(B6/B5,"") -> 0.3375 | C22: =iferror(C6/C5,"") -> 0.8 | D22: =iferror(D6/D5,"") -> 0.8 | E22: =iferror(E6/E5,"") -> 0.8 | F22: =iferror(F6/F5,"") -> 0.8 | G22: =iferror(G6/G5,"") -> 0.8 | H22: =iferror(H6/H5,"") -> 0.8
A23: SAL > SQL | B23: =iferror(B7/B6,"") -> 0.48148148 | C23: =iferror(C7/C6,"") -> 0.75 | D23: =iferror(D7/D6,"") -> 0.75 | E23: =iferror(E7/E6,"") -> 0.75 | F23: =iferror(F7/F6,"") -> 0.75 | G23: =iferror(G7/G6,"") -> 0.75 | H23: =iferror(H7/H6,"") -> 0.75
A24: SQL > Opp | B24: =iferror(B8/B7,"") -> 0.46153846 | C24: =iferror(C8/C7,"") -> 0.33333333 | D24: =iferror(D8/D7,"") -> 0.33333333 | E24: =iferror(E8/E7,"") -> 0.33333333 | F24: =iferror(F8/F7,"") -> 0.33333333 | G24: =iferror(G8/G7,"") -> 0.33333333 | H24: =iferror(H8/H7,"") -> 0.33333333
A26: Lifetime Value (LTV): | B26: Model | C26: =C2 -> Google | D26: =D2 -> LinkedIn | E26: =E2 -> Microsoft | F26: =F2 -> Facebook | G26: =G2 -> Directories | H26: =H18 -> Total | J26: Lifetime Value (LTV) | K26: Actuals (from client)
A27: Gross Margin (GM%): | B27: =if(ISBLANK($K$27),"enter actuals",$K$27) -> 0.55 | C27: =$B27 -> 0.55 | D27: =$B27 -> 0.55 | E27: =$B27 -> 0.55 | F27: =$B27 -> 0.55 | G27: =$B27 -> 0.55 | H27: =iferror(average(C27:G27),"") -> 0.55 | J27: Gross Margin (GM%): | K27: 0.55
A28: Lifespan of a customer (months): | B28: =if(ISBLANK($K$28),"enter actuals",$K$28) -> 12 | C28: =$B28 -> 12 | D28: =$B28 -> 12 | E28: =$B28 -> 12 | F28: =$B28 -> 12 | G28: =$B28 -> 12 | H28: =iferror(average(C28:G28),"") -> 12 | J28: Lifespan of a customer (months): | K28: 12
A29: Monthly Avg. Order Value | B29: =if(isblank($K$29),"enter actuals",$K$29) -> 500 | C29: =$B29 -> 500 | D29: =$B29 -> 500 | E29: =$B29 -> 500 | F29: =$B29 -> 500 | G29: =$B29 -> 500 | H29: =iferror(H19/12,"") -> 1100 | J29: Monthly Avg. Order Value | K29: 500
A30: Lifetime Value (LTV) | B30: =iferror(B27*B28*B29,"enter actuals") -> 3300 | C30: =$B30 -> 3300 | D30: =$B30 -> 3300 | E30: =$B30 -> 3300 | F30: =$B30 -> 3300 | G30: =$B30 -> 3300 | H30: =iferror(H27*H28*H29,"") -> 7260
A31: ROI | B31: =iferror((B30*B9)-B3,"") -> 138000 | C31: =iferror((C30*C9)-C3,"") -> 3000 | D31: =iferror((D30*D9)-D3,"") -> 3000 | E31: =iferror((E30*E9)-E3,"") -> 3000 | F31: =iferror((F30*F9)-F3,"") -> -7000 | G31: =iferror((G30*G9)-G3,"") -> -27000 | H31: =(H30*H9)-H3 -> 173000
A32: LTV:CAC Ratio | B32: =IFERROR(B30/B16,"") -> 3.3 | C32: =IFERROR(C30/C16,"") -> 1.1 | D32: =IFERROR((D9*D30)/D3,"") -> 1.1 | E32: =IFERROR((E9*E30)/E3,"") -> 1.1 | F32: =IFERROR((F9*F30)/F3,"") -> 0.825 | G32: =IFERROR((G9*G30)/G3,"") -> 0.55 | H32: =IFERROR((H9*H30)/H3,"") -> 1.9105263
J34: Quarterly Goal Type: | K34: SQL
C35: Next Quarter Projections
A36: Projections Details | B36: Model | C36: =C2 -> Google | D36: =D2 -> LinkedIn | E36: =E2 -> Microsoft | F36: =F2 -> Facebook | G36: =G2 -> Directories | H36: =H2 -> Total | J36: Channel | K36: ="Quarterly "&K34&" Goal" -> Quarterly SQL Goal | L36: =K34&" % Increase" -> SQL % Increase | M36: Spend Required | N36: Increase in Spend | O36: Incremental ROI
A37: Total Cost | C37: =if($K$34="Lead",VLOOKUP(C36,$J$36:$K$41,2,false)*if($K$44="Actuals",C11,if(L53="--",$K53,L53)),if($K$34="MQL",VLOOKUP(C36,$J$36:$K$41,2,false)*if($K$44="Actuals",C12,if(L54="--",$K54,L54)),if($K$34="SAL",VLOOKUP(C36,$J$36:$K$41,2,false)*if($K$44="Actuals",C13,if(L55="--",$K55,L55)), if($K$34="SQL",VLOOKUP(C36,$J$36:$K$41,2,false)*if($K$44="Actuals",C14,if(L56="--",$K56,L56)),if($K$34="Opp",VLOOKUP(C36,$J$36:$K$41,2,false)*if($K$44="Actuals",C15,if(L57="--",$K57,L57)),""))))) -> 222300 | D37: =if($K$34="Lead",VLOOKUP(D36,$J$36:$K$41,2,false)*if($K$44="Actuals",D11,if(M53="--",$K53,M53)),if($K$34="MQL",VLOOKUP(D36,$J$36:$K$41,2,false)*if($K$44="Actuals",D12,if(M54="--",$K54,M54)),if($K$34="SAL",VLOOKUP(D36,$J$36:$K$41,2,false)*if($K$44="Actuals",D13,if(M55="--",$K55,M55)), if($K$34="SQL",VLOOKUP(D36,$J$36:$K$41,2,false)*if($K$44="Actuals",D14,if(M56="--",$K56,M56)),if($K$34="Opp",VLOOKUP(D36,$J$36:$K$41,2,false)*if($K$44="Actuals",D15,if(M57="--",$K57,M57)),""))))) -> 741250 | E37: =if($K$34="Lead",VLOOKUP(E36,$J$36:$K$41,2,false)*if($K$44="Actuals",E11,if(N53="--",$K53,N53)),if($K$34="MQL",VLOOKUP(E36,$J$36:$K$41,2,false)*if($K$44="Actuals",E12,if(N54="--",$K54,N54)),if($K$34="SAL",VLOOKUP(E36,$J$36:$K$41,2,false)*if($K$44="Actuals",E13,if(N55="--",$K55,N55)), if($K$34="SQL",VLOOKUP(E36,$J$36:$K$41,2,false)*if($K$44="Actuals",E14,if(N56="--",$K56,N56)),if($K$34="Opp",VLOOKUP(E36,$J$36:$K$41,2,false)*if($K$44="Actuals",E15,if(N57="--",$K57,N57)),""))))) -> 86700 | F37: =if($K$34="Lead",VLOOKUP(F36,$J$36:$K$41,2,false)*if($K$44="Actuals",F11,if(O53="--",$K53,O53)),if($K$34="MQL",VLOOKUP(F36,$J$36:$K$41,2,false)*if($K$44="Actuals",F12,if(O54="--",$K54,O54)),if($K$34="SAL",VLOOKUP(F36,$J$36:$K$41,2,false)*if($K$44="Actuals",F13,if(O55="--",$K55,O55)), if($K$34="SQL",VLOOKUP(F36,$J$36:$K$41,2,false)*if($K$44="Actuals",F14,if(O56="--",$K56,O56)),if($K$34="Opp",VLOOKUP(F36,$J$36:$K$41,2,false)*if($K$44="Actuals",F15,if(O57="--",$K57,O57)),""))))) -> 531800 | G37: =if($K$34="Lead",VLOOKUP(G36,$J$36:$K$41,2,false)*if($K$44="Actuals",G11,if(P53="--",$K53,P53)),if($K$34="MQL",VLOOKUP(G36,$J$36:$K$41,2,false)*if($K$44="Actuals",G12,if(P54="--",$K54,P54)),if($K$34="SAL",VLOOKUP(G36,$J$36:$K$41,2,false)*if($K$44="Actuals",G13,if(P55="--",$K55,P55)), if($K$34="SQL",VLOOKUP(G36,$J$36:$K$41,2,false)*if($K$44="Actuals",G14,if(P56="--",$K56,P56)),if($K$34="Opp",VLOOKUP(G36,$J$36:$K$41,2,false)*if($K$44="Actuals",G15,if(P57="--",$K57,P57)),""))))) -> 581600 | H37: =SUM(C37:G37) -> 2163650 | J37: =C2 -> Google | K37: 50 | L37: =iferror((K37-(INDEX($A$1:$H$9,(INDEX(MATCH(($K$34&"s"),$A:$A,0),0)),(INDEX(MATCH(J37,$2:$2,0),0)))))/((INDEX($A$1:$H$9,(INDEX(MATCH(($K$34&"s"),$A:$A,0),0)),(INDEX(MATCH(J37,$2:$2,0),0))))),"") -> -0.16666667 | M37: =C37 -> 222300 | N37: =iferror(M37-C3,0) -> 192300 | O37: =iferror((((K37*C55)*C30)-M37)-C31,0) -> -164250
A38: Leads | C38: =if(($K$34&"s")=$A38,VLOOKUP(C36,$J$36:$K$41,2,false),if($K$44="Actuals",C37/C11,C37/if(L53="--",K53,L53))) -> 377.41935 | D38: =if(($K$34&"s")=$A38,VLOOKUP(D36,$J$36:$K$41,2,false),if($K$44="Actuals",D37/D11,D37/if(M53="--",K53,M53))) -> 1041.0815 | E38: =if(($K$34&"s")=$A38,VLOOKUP(E36,$J$36:$K$41,2,false),if($K$44="Actuals",E37/E11,E37/if(N53="--",K53,N53))) -> 274.36709 | F38: =if(($K$34&"s")=$A38,VLOOKUP(F36,$J$36:$K$41,2,false),if($K$44="Actuals",F37/F11,F37/if(O53="--",K53,O53))) -> 666.41604 | G38: =if(($K$34&"s")=$A38,VLOOKUP(G36,$J$36:$K$41,2,false),if($K$44="Actuals",G37/G11,G37/if(P53="--",K53,P53))) -> 499.22747 | H38: =SUM(C38:G38) -> 2858.5114 | J38: =D2 -> LinkedIn | K38: 50 | L38: =iferror((K38-(INDEX($A$1:$H$9,(INDEX(MATCH(($K$34&"s"),$A:$A,0),0)),(INDEX(MATCH(J38,$2:$2,0),0)))))/((INDEX($A$1:$H$9,(INDEX(MATCH(($K$34&"s"),$A:$A,0),0)),(INDEX(MATCH(J38,$2:$2,0),0))))),"") -> -0.16666667 | M38: =D37 -> 741250 | N38: =iferror(M38-D3,0) -> 711250 | O38: =iferror((((K38*D55)*D30)-M38)-D31,"") -> -719500
A39: MQLs | C39: =if(($K$34&"s")=$A39,VLOOKUP(C36,$J$36:$K$41,2,false),C38*C56) -> 181.16129 | D39: =if(($K$34&"s")=$A39,VLOOKUP(D36,$J$36:$K$41,2,false),D38*D56) -> 301.91362 | E39: =if(($K$34&"s")=$A39,VLOOKUP(E36,$J$36:$K$41,2,false),E38*E56) -> 200.28797 | F39: =if(($K$34&"s")=$A39,VLOOKUP(F36,$J$36:$K$41,2,false),F38*F56) -> 39.984962 | G39: =if(($K$34&"s")=$A39,VLOOKUP(G36,$J$36:$K$41,2,false),G38*G56) -> 399.38197 | H39: =SUM(C39:G39) -> 1122.7298 | J39: =E2 -> Microsoft | K39: 50 | L39: =iferror((K39-(INDEX($A$1:$H$9,(INDEX(MATCH(($K$34&"s"),$A:$A,0),0)),(INDEX(MATCH(J39,$2:$2,0),0)))))/((INDEX($A$1:$H$9,(INDEX(MATCH(($K$34&"s"),$A:$A,0),0)),(INDEX(MATCH(J39,$2:$2,0),0))))),"") -> -0.16666667 | M39: =E37 -> 86700 | N39: =iferror(M39-E3,0) -> 56700 | O39: =iferror((((K39*E55)*E30)-M39)-E31,"") -> 42300
A40: SALs | C40: =if(($K$34&"s")=$A40,VLOOKUP(C36,$J$36:$K$41,2,false),C39*C57) -> 54.348387 | D40: =if(($K$34&"s")=$A40,VLOOKUP(D36,$J$36:$K$41,2,false),D39*D57) -> 24.15309 | E40: =if(($K$34&"s")=$A40,VLOOKUP(E36,$J$36:$K$41,2,false),E39*E57) -> 104.14975 | F40: =if(($K$34&"s")=$A40,VLOOKUP(F36,$J$36:$K$41,2,false),F39*F57) -> 4.7981955 | G40: =if(($K$34&"s")=$A40,VLOOKUP(G36,$J$36:$K$41,2,false),G39*G57) -> 47.925837 | H40: =SUM(C40:G40) -> 235.37526 | J40: =F2 -> Facebook | K40: 50 | L40: =iferror((K40-(INDEX($A$1:$H$9,(INDEX(MATCH(($K$34&"s"),$A:$A,0),0)),(INDEX(MATCH(J40,$2:$2,0),0)))))/((INDEX($A$1:$H$9,(INDEX(MATCH(($K$34&"s"),$A:$A,0),0)),(INDEX(MATCH(J40,$2:$2,0),0))))),"") -> -0.16666667 | M40: =F37 -> 531800 | N40: =iferror(M40-F3,0) -> 491800 | O40: =iferror((((K40*F55)*F30)-M40)-F31,"") -> -463750
A41: SQLs | C41: =if(($K$34&"s")=$A41,VLOOKUP(C36,$J$36:$K$41,2,false),C40*C58) -> 50 | D41: =if(($K$34&"s")=$A41,VLOOKUP(D36,$J$36:$K$41,2,false),D40*D58) -> 50 | E41: =if(($K$34&"s")=$A41,VLOOKUP(E36,$J$36:$K$41,2,false),E40*E58) -> 50 | F41: =if(($K$34&"s")=$A41,VLOOKUP(F36,$J$36:$K$41,2,false),F40*F58) -> 50 | G41: =if(($K$34&"s")=$A41,VLOOKUP(G36,$J$36:$K$41,2,false),G40*G58) -> 50 | H41: =SUM(C41:G41) -> 250 | J41: =G2 -> Directories | K41: 50 | L41: =iferror((K41-(INDEX($A$1:$H$9,(INDEX(MATCH(($K$34&"s"),$A:$A,0),0)),(INDEX(MATCH(J41,$2:$2,0),0)))))/((INDEX($A$1:$H$9,(INDEX(MATCH(($K$34&"s"),$A:$A,0),0)),(INDEX(MATCH(J41,$2:$2,0),0))))),"") -> -0.16666667 | M41: =G37 -> 581600 | N41: =iferror(M41-G3,0) -> 521600 | O41: =iferror((((K41*G55)*G30)-M41)-G31,0) -> -513350
A42: Opps | C42: =if(($K$34&"s")=$A42,VLOOKUP(C36,$J$36:$K$41,2,false),C41*C59) -> 26 | D42: =if(($K$34&"s")=$A42,VLOOKUP(D36,$J$36:$K$41,2,false),D41*D59) -> 5 | E42: =if(($K$34&"s")=$A42,VLOOKUP(E36,$J$36:$K$41,2,false),E41*E59) -> 43 | F42: =if(($K$34&"s")=$A42,VLOOKUP(F36,$J$36:$K$41,2,false),F41*F59) -> 5 | G42: =if(($K$34&"s")=$A42,VLOOKUP(G36,$J$36:$K$41,2,false),G41*G59) -> 27.5 | H42: =SUM(C42:G42) -> 106.5 | J42: Total | K42: =SUM(K37:K41) -> 250 | L42: =iferror((K42-(INDEX($A$1:$H$9,(INDEX(MATCH(($K$34&"s"),$A:$A,0),0)),(INDEX(MATCH(J42,$2:$2,0),0)))))/((INDEX($A$1:$H$9,(INDEX(MATCH(($K$34&"s"),$A:$A,0),0)),(INDEX(MATCH(J42,$2:$2,0),0))))),"") -> -0.16666667 | M42: =SUM(M37:M41) -> 2163650 | N42: =SUM(N37:N41) -> 1973650 | O42: =SUM(O37:O41) -> -1818550
A43: Customers | C43: =C42*C55 -> 9.62 | D43: =D42*D55 -> 0.75 | E43: =E42*E55 -> 34.4 | F43: =F42*F55 -> 1.85 | G43: =G42*G55 -> 6.875 | H43: =SUM(C43:G43) -> 53.495
A44: Bookings (Annual) | C44: =C43*C54 -> 57720 | D44: =D43*D54 -> 4500 | E44: =E43*E54 -> 206400 | F44: =F43*F54 -> 11100 | G44: =G43*G54 -> 41250 | H44: =SUM(C44:G44) -> 320970 | J44: Base Projections On: | K44: Benchmarks
A45: Cost-Per-Lead | C45: =iferror(C37/C38,"") -> 589 | D45: =iferror(D37/D38,"") -> 712 | E45: =iferror(E37/E38,"") -> 316 | F45: =iferror(F37/F38,"") -> 798 | G45: =iferror(G37/G38,"") -> 1165 | H45: =H37/H38 -> 756.91494
A46: Cost-Per-MQL | C46: =iferror(C37/C39,"") -> 1227.0833 | D46: =iferror(D37/D39,"") -> 2455.1724 | E46: =iferror(E37/E39,"") -> 432.87671 | F46: =iferror(F37/F39,"") -> 13300 | G46: =iferror(G37/G39,"") -> 1456.25 | H46: =H37/H39 -> 1927.1333 | J46: NOTE: Double-check Benchmark Library for latest benchmark data
A47: Cost-Per-SAL | C47: =iferror(C37/C40,"") -> 4090.2778 | D47: =iferror(D37/D40,"") -> 30689.655 | E47: =iferror(E37/E40,"") -> 832.45522 | F47: =iferror(F37/F40,"") -> 110833.33 | G47: =iferror(G37/G40,"") -> 12135.417 | H47: =H37/H40 -> 9192.3426 | J47: Benchmarks | K47: Total | L47: Google | M47: LinkedIn | N47: Microsoft | O47: Facebook | P47: Directories
A48: Cost-Per-SQL | C48: =iferror(C37/C41,"") -> 4446 | D48: =iferror(D37/D41,"") -> 14825 | E48: =iferror(E37/E41,"") -> 1734 | F48: =iferror(F37/F41,"") -> 10636 | G48: =iferror(G37/G41,"") -> 11632 | H48: =H37/H41 -> 8654.6 | J48: Lead > MQL | K48: 0.46 | L48: 0.48 | M48: 0.29 | N48: 0.73 | O48: 0.06 | P48: 0.8
A49: Cost-Per-Opp | C49: =iferror(C37/C42,"") -> 8550 | D49: =iferror(D37/D42,"") -> 148250 | E49: =iferror(E37/E42,"") -> 2016.2791 | F49: =iferror(F37/F42,"") -> 106360 | G49: =iferror(G37/G42,"") -> 21149.091 | H49: =H37/H42 -> 20315.962 | J49: MQL > SAL | K49: 0.12 | L49: 0.3 | M49: 0.08 | N49: 0.52 | O49: -- | P49: --
A50: Cost-Per-Customer | C50: =iferror(C37/C43,"") -> 23108.108 | D50: =iferror(D37/D43,"") -> 988333.33 | E50: =iferror(E37/E43,"") -> 2520.3488 | F50: =iferror(F37/F43,"") -> 287459.46 | G50: =iferror(G37/G43,"") -> 84596.364 | H50: =H37/H43 -> 40445.836 | J50: SAL > SQL | K50: 0.36 | L50: 0.42 | M50: 0.19 | N50: -- | O50: -- | P50: --
J51: SQL > Opp | K51: 0.55 | L51: 0.52 | M51: 0.1 | N51: 0.86 | O51: 0.1 | P51: --
J52: Opp > Customer | K52: 0.34 | L52: 0.37 | M52: 0.15 | N52: 0.8 | O52: 0.37 | P52: 0.25
A53: Assumptions | B53: Model | C53: =C36 -> Google | D53: =D36 -> LinkedIn | E53: =E36 -> Microsoft | F53: =F36 -> Facebook | G53: =G36 -> Directories | H53: =H36 -> Total | J53: Cost-Per-Lead | K53: 575 | L53: 589 | M53: 712 | N53: 316 | O53: 798 | P53: 1165
A54: Avg. Contract Value (Annual) | C54: =C19 -> 6000 | D54: =D19 -> 6000 | E54: =E19 -> 6000 | F54: =F19 -> 6000 | G54: =G19 -> 6000 | H54: =H44/H43 -> 6000 | J54: Cost-Per-MQL | K54: 1026 | L54: 1163 | M54: 1141 | N54: 450 | O54: 1195 | P54: 1106
A55: Opp > Customer (Close Rate) | C55: =if($K$44="Actuals",C20,if(L52="--",K52,L52)) -> 0.37 | D55: =if($K$44="Actuals",D20,if(M52="--",K52,M52)) -> 0.15 | E55: =if($K$44="Actuals",E20,if(N52="--",K52,N52)) -> 0.8 | F55: =if($K$44="Actuals",F20,if(O52="--",K52,O52)) -> 0.37 | G55: =if($K$44="Actuals",G20,if(P52="--",K52,P52)) -> 0.25 | H55: =H43/H42 -> 0.50230047 | J55: Cost-Per-SAL | K55: 3923 | L55: 3887 | M55: 8509 | N55: 1243 | O55: -- | P55: --
A56: Lead > MQL | C56: =if($K$44="Actuals",C21,if(L48="--",K48,L48)) -> 0.48 | D56: =if($K$44="Actuals",D21,if(M48="--",K48,M48)) -> 0.29 | E56: =if($K$44="Actuals",E21,if(N48="--",K48,N48)) -> 0.73 | F56: =if($K$44="Actuals",F21,if(O48="--",K48,O48)) -> 0.06 | G56: =if($K$44="Actuals",G21,if(P48="--",K48,P48)) -> 0.8 | H56: =H39/H38 -> 0.39276731 | J56: Cost-Per-SQL | K56: 4395 | L56: 4446 | M56: 14825 | N56: 1734 | O56: 10636 | P56: 11632
A57: MQL > SAL | C57: =if($K$44="Actuals",C22,if(L49="--",K49,L49)) -> 0.3 | D57: =if($K$44="Actuals",D22,if(M49="--",K49,M49)) -> 0.08 | E57: =if($K$44="Actuals",E22,if(N49="--",K49,N49)) -> 0.52 | F57: =if($K$44="Actuals",F22,if(O49="--",K49,O49)) -> 0.12 | G57: =if($K$44="Actuals",G22,if(P49="--",K49,P49)) -> 0.12 | H57: =H40/H39 -> 0.2096455 | J57: Cost-Per-Opp | K57: 5427 | L57: 6168 | M57: 6314 | N57: 2506 | O57: 4276 | P57: 1727
A58: SAL > SQL | C58: =if($K$44="Actuals",C23,if(L50="--",K50,L50)) -> 0.42 | D58: =if($K$44="Actuals",D23,if(M50="--",K50,M50)) -> 0.19 | E58: =if($K$44="Actuals",E23,if(N50="--",K50,N50)) -> 0.36 | F58: =if($K$44="Actuals",F23,if(O50="--",K50,O50)) -> 0.36 | G58: =if($K$44="Actuals",G23,if(P50="--",K50,P50)) -> 0.36 | H58: =H41/H39 -> 0.22267156 | J58: Cost-Per-Customer | K58: 16794 | L58: 17001 | M58: 10088 | N58: 2288 | O58: 8596 | P58: 6713
A59: SQL > Opp | C59: =if($K$44="Actuals",C24,if(L51="--",K51,L51)) -> 0.52 | D59: =if($K$44="Actuals",D24,if(M51="--",K51,M51)) -> 0.1 | E59: =if($K$44="Actuals",E24,if(N51="--",K51,N51)) -> 0.86 | F59: =if($K$44="Actuals",F24,if(O51="--",K51,O51)) -> 0.1 | G59: =if($K$44="Actuals",G24,if(P51="--",K51,P51)) -> 0.55 | H59: =H42/H41 -> 0.426
A61: Lifetime Value (LTV): | B61: Model | C61: =C36 -> Google | D61: =D36 -> LinkedIn | E61: =E36 -> Microsoft | F61: =F36 -> Facebook | G61: =G36 -> Directories | H61: =H53 -> Total
A62: Gross Margin (GM%): | C62: =C27 -> 0.55 | D62: =D27 -> 0.55 | E62: =E27 -> 0.55 | F62: =F27 -> 0.55 | G62: =G27 -> 0.55 | H62: =average(C62:G62) -> 0.55
A63: Lifespan of a customer (months): | C63: =C28 -> 12 | D63: =D28 -> 12 | E63: =E28 -> 12 | F63: =F28 -> 12 | G63: =G28 -> 12 | H63: =average(C63:G63) -> 12
A64: Monthly Avg. Order Value | C64: =C54/12 -> 500 | D64: =D54/12 -> 500 | E64: =E54/12 -> 500 | F64: =F54/12 -> 500 | G64: =G54/12 -> 500 | H64: =H54/12 -> 500
A65: Lifetime Value (LTV) | C65: =C64*C62*C63 -> 3300 | D65: =D64*D62*D63 -> 3300 | E65: =E64*E62*E63 -> 3300 | F65: =F64*F62*F63 -> 3300 | G65: =G64*G62*G63 -> 3300 | H65: =H64*H62*H63 -> 3300
A66: ROI | C66: =(C65*C43)-C37 -> -190554 | D66: =(D65*D43)-D37 -> -738775 | E66: =(E65*E43)-E37 -> 26820 | F66: =(F65*F43)-F37 -> -525695 | G66: =(G65*G43)-G37 -> -558912.5 | H66: =(H65*H43)-H37 -> -1987116.5
A67: LTV:CAC Ratio | C67: =IFERROR((C43*C65)/C37,"") -> 0.14280702 | D67: =IFERROR((D43*D65)/D37,"") -> 0.0033389545 | E67: =IFERROR((E43*E65)/E37,"") -> 1.3093426 | F67: =IFERROR((F43*F65)/F37,"") -> 0.01147988 | G67: =IFERROR((G43*G65)/G37,"") -> 0.039008769 | H67: =IFERROR((H43*H65)/H37,"") -> 0.081590599

Sheet LTVCAC Analysis
B2: GET STARTED | BF2: NOTE
B3: Enter the values needed for calculating LTV in cells T14:T17, then customize your channels and funnel stages in the 'Current Quarter Actuals' table below. | BF3: Only edit highlighted cells.
BF4: Try not to alter cells that contain a formula.
B5: As you enter data in the 'Current Quarter Actuals' tab, this sheet will automatically update to show a summary of the quarter.
B10: Sept-Oct Summary
T12: Lifetime Value (LTV) | AC12: Lifetime Value (LTV)
T13: Gross Margin (%) | X13: 0.6 | AC13: Company Gross Margin (%) | AG13: 0.52
D14: =IFERROR(__xludf.DUMMYFUNCTION("iferror(SPARKLINE(C22,{""charttype"",""column"";""ymin"", 0; ""ymax"",MAX(C22:H22);""firstcolor"",""#304458""}),"""")"),"") | F14: =IFERROR(__xludf.DUMMYFUNCTION("iferror(SPARKLINE(F22,{""charttype"",""column"";""ymin"", 0; ""ymax"",MAX(C22:H22);""firstcolor"",""#f46524""}),"""")"),"") | T14: Lifespan of Customer (months) | X14: 12 | AC14: Retention % | AG14: 0.424
T15: Monthly Avg. Order Value | X15: 15293 | Z15: =X15*12 -> 183516
T16: Channel-level AOV's? | X16: Yes
T17: Lifetime Value (LTV) | X17: =if(X16="No",if(isblank(X13),"Enter GM%",if(isblank(X14),"Enter Lifespan",if(ISBLANK(X15),"Enter AOV",X13*X14*X15))),"See Below") -> See Below
M20: =F65 -> Form Fills | N20: =H65 -> 689 | S20: =IFERROR(__xludf.DUMMYFUNCTION("iferror(SPARKLINE(G65:H65,{""charttype"",""bar"";""max"",MAX($H$65:$H$70);""color1"",""#ebedef"";""color2"",""#073763""}),"""")"),"")
C21: Total Spend | F21: Total Est. Bookings | M21: =F66 -> Intro Held | N21: =H66 -> 373 | S21: =IFERROR(__xludf.DUMMYFUNCTION("iferror(SPARKLINE(G66:H66,{""charttype"",""bar"";""max"",MAX($H$65:$H$70);""color1"",""#ebedef"";""color2"",""#0b5394""}),"""")"),"") | W21: =iferror(if(J65="","","🔽 "&(ROUND(J65,2)*100)&"%"),"--") -> 🔽 54% | X21: =if(I65="","",I65) -> Form Fill > Intro Held
C22: =E36 -> 951168.5 | F22: =E47 -> 1317030 | M22: =F67 -> Strat Call Held | N22: =H67 -> 156 | S22: =IFERROR(__xludf.DUMMYFUNCTION("iferror(SPARKLINE(G67:H67,{""charttype"",""bar"";""max"",MAX(H65:H70);""color1"",""#ebedef"";""color2"",""#3d85c6""}),"""")"),"") | W22: =iferror(if(J66="","","🔽 "&(ROUND(J66,2)*100)&"%"),"--") -> 🔽 42% | X22: =if(I66="","",I66) -> Intro Held > Strat Call Held
M23: =F68 -> Proposals | N23: =H68 -> 104 | S23: =IFERROR(__xludf.DUMMYFUNCTION("iferror(SPARKLINE(G68:H68,{""charttype"",""bar"";""max"",MAX($H$65:$H$70);""color1"",""#ebedef"";""color2"",""#6fa8dc""}),"""")"),"") | W23: =iferror(if(J67="","","🔽 "&(ROUND(J67,2)*100)&"%"),"--") -> 🔽 67% | X23: =if(I67="","",I67) -> Strat Call Held > Proposal
M24: =F69 -> Customers | N24: =H69 -> 23 | S24: =IFERROR(__xludf.DUMMYFUNCTION("iferror(SPARKLINE(G69:H69,{""charttype"",""bar"";""max"",MAX($H$65:$H$70);""color1"",""#ebedef"";""color2"",""#9fc5e8""}),"""")"),"") | W24: =iferror(if(J68="","","🔽 "&(ROUND(J68,2)*100)&"%"),"--") -> 🔽 22% | X24: =if(I68="","",I68) -> Proposal > Customer
C25: LTV:CAC Ratio | F25: =E31 -> 1.13 | M25: =F70 | N25: =H70 | S25: {=iferror(SPARKLINE(G70:H70,{"charttype","bar";"max",MAX($H$65:$H$70);"color1","#ebedef";"color2","#cfe2f3"}),"")} | W25: =iferror(if(J69="","","🔽 "&(ROUND(J69,2)*100)&"%"),"--") | X25: =if(I69="","",I69)
C26: Net Return | F26: =E48 -> 1012798.2
B28: Sept-Oct Actuals
I29: 25000 | AM29: 35000 | AO29: 5000 | AQ29: 30000 | AS29: 60000 | AW29: 40000
E30: Total | G30: Google - Brand | I30: Google - Non-Brand: Demand Gen | K30: Google - Non-Brand: Marketing | M30: Google - Non-Brand: MOPs | O30: Google - Non-Brand: Paid Media | Q30: Google - Non-Brand: Social | S30: Google - Non-Brand: Creative | U30: Google - Non-Brand: Performance Marketing | W30: Google - Non-Brand: SEO | Y30: Google - Non-Brand: Strategy | AA30: Google - Non-Brand: Video | AC30: Google - YouTube | AE30: Google - Display | AG30: Google - Non-Brand: Events Support | AI30: Google - Non-Brand: RLSA | AK30: LinkedIn - Brand Ads | AM30: LinkedIn - Convo Ads GC | AO30: LinkedIn - Line Specific GC | AQ30: LinkedIn - Strategy GC | AS30: LinkedIn - SPC GC | AU30: Facebook/IG - Brand Ads | AW30: Facebook - SPC GC | AY30: Instagram - SPC GC | BA30: StackAdapt | BC30: Clutch.io | BE30: Manifest | BG30: Twitter - Brand | BI30: TikTok | BK30: Events | BM30: Organic | BO30: Non-Paid Media | BQ30: Total
B31: LTV:CAC Ratio | E31: =if(E36="--","--",if(istext(E46),"No LTV",if(or(isblank(E42),E42=0),0,Round(E46/E54,2)))) -> 1.13 | G31: =if(isblank(G36),"--",if(istext(G46),"No LTV",if(or(isblank(G42),G42=0),0,Round(G46/G54,2)))) -> No LTV | I31: =if(isblank(I36),"--",if(istext(I46),"No LTV",if(or(isblank(I42),I42=0),0,Round(I46/I54,2)))) -> No LTV | K31: =if(isblank(K36),"--",if(istext(K46),"No LTV",if(or(isblank(K42),K42=0),0,Round(K46/K54,2)))) -> No LTV | M31: =if(isblank(M36),"--",if(istext(M46),"No LTV",if(or(isblank(M42),M42=0),0,Round(M46/M54,2)))) -> No LTV | O31: =if(isblank(O36),"--",if(istext(O46),"No LTV",if(or(isblank(O42),O42=0),0,Round(O46/O54,2)))) -> No LTV | Q31: =if(isblank(Q36),"--",if(istext(Q46),"No LTV",if(or(isblank(Q42),Q42=0),0,Round(Q46/Q54,2)))) -> No LTV | S31: =if(isblank(S36),"--",if(istext(S46),"No LTV",if(or(isblank(S42),S42=0),0,Round(S46/S54,2)))) -> No LTV | U31: =if(isblank(U36),"--",if(istext(U46),"No LTV",if(or(isblank(U42),U42=0),0,Round(U46/U54,2)))) -> No LTV | W31: =if(isblank(W36),"--",if(istext(W46),"No LTV",if(or(isblank(W42),W42=0),0,Round(W46/W54,2)))) -> No LTV | Y31: =if(isblank(Y36),"--",if(istext(Y46),"No LTV",if(or(isblank(Y42),Y42=0),0,Round(Y46/Y54,2)))) -> No LTV | AA31: =if(isblank(AA36),"--",if(istext(AA46),"No LTV",if(or(isblank(AA42),AA42=0),0,Round(AA46/AA54,2)))) -> 0.83 | AC31: =if(isblank(AC36),"--",if(istext(AC46),"No LTV",if(or(isblank(AC42),AC42=0),0,Round(AC46/AC54,2)))) -> No LTV | AE31: =if(isblank(AE36),"--",if(istext(AE46),"No LTV",if(or(isblank(AE42),AE42=0),0,Round(AE46/AE54,2)))) -> No LTV | AG31: =if(isblank(AG36),"--",if(istext(AG46),"No LTV",if(or(isblank(AG42),AG42=0),0,Round(AG46/AG54,2)))) -> No LTV | AI31: =if(isblank(AI36),"--",if(istext(AI46),"No LTV",if(or(isblank(AI42),AI42=0),0,Round(AI46/AI54,2)))) -> No LTV | AK31: =if(isblank(AK36),"--",if(istext(AK46),"No LTV",if(or(isblank(AK42),AK42=0),0,Round(AK46/AK54,2)))) -> No LTV | AM31: =if(isblank(AM36),"--",if(istext(AM46),"No LTV",if(or(isblank(AM42),AM42=0),0,Round(AM46/AM54,2)))) -> 1.33 | AO31: =if(isblank(AO36),"--",if(istext(AO46),"No LTV",if(or(isblank(AO42),AO42=0),0,Round(AO46/AO54,2)))) -> No LTV | AQ31: =if(isblank(AQ36),"--",if(istext(AQ46),"No LTV",if(or(isblank(AQ42),AQ42=0),0,Round(AQ46/AQ54,2)))) -> No LTV | AS31: =if(isblank(AS36),"--",if(istext(AS46),"No LTV",if(or(isblank(AS42),AS42=0),0,Round(AS46/AS54,2)))) -> 2.74 | AU31: =if(isblank(AU36),"--",if(istext(AU46),"No LTV",if(or(isblank(AU42),AU42=0),0,Round(AU46/AU54,2)))) -> No LTV | AW31: =if(isblank(AW36),"--",if(istext(AW46),"No LTV",if(or(isblank(AW42),AW42=0),0,Round(AW46/AW54,2)))) -> No LTV | BA31: =if(isblank(BA36),"--",if(istext(BA46),"No LTV",if(or(isblank(BA42),BA42=0),0,Round(BA46/BA54,2)))) -> No LTV | BC31: =if(isblank(BC36),"--",if(istext(BC46),"No LTV",if(or(isblank(BC42),BC42=0),0,Round(BC46/BC54,2)))) -> No LTV | BE31: =if(isblank(BE36),"--",if(istext(BE46),"No LTV",if(or(isblank(BE42),BE42=0),0,Round(BE46/BE54,2)))) -> No LTV | BG31: =if(isblank(BG36),"--",if(istext(BG46),"No LTV",if(or(isblank(BG42),BG42=0),0,Round(BG46/BG54,2)))) -> No LTV | BI31: =if(isblank(BI36),"--",if(istext(BI46),"No LTV",if(or(isblank(BI42),BI42=0),0,Round(BI46/BI54,2)))) -> No LTV | BK31: =if(isblank(BK36),"--",if(istext(BK46),"No LTV",if(or(isblank(BK42),BK42=0),0,Round(BK46/BK54,2)))) -> No LTV | BM31: =if(isblank(BM36),"--",if(istext(BM46),"No LTV",if(or(isblank(BM42),BM42=0),0,Round(BM46/BM54,2)))) -> No LTV | BO31: =if(isblank(BO36),"--",if(istext(BO46),"No LTV",if(or(isblank(BO42),BO42=0),0,Round(BO46/BO54,2)))) -> 32.67
B32: Total Ad Spend | E32: =if(sum(G32:BS32)=0,"--",sum(G32:BS32)) -> 340478.51 | G32: 1566.34 | I32: 790.57 | K32: 10320.12 | M32: 9662.2 | O32: 182.38 | Q32: 2426.92 | S32: 8162.96 | U32: 18167.75 | W32: 6440.66 | Y32: 12024.18 | AA32: 6191.84 | AC32: 3039.35 | AE32: 0 | AG32: 795.72 | AI32: 1852.71 | AK32: 11823.74 | AM32: 65931.99 | AO32: 11401.43 | AQ32: 43631.78 | AS32: 26875.87 | AU32: 12100.79 | AW32: 21266.237 | AY32: 13327.613 | BA32: 4775.86 | BC32: =2650+2650 -> 5300 | BE32: =650+650 -> 1300 | BG32: 3901.5 | BI32: 4218 | BK32: 33000 | BM32: 0 | BO32: 0
B33: Resource Cost | E33: 567941 | G33: =(G32/$E$32)*$E$33 -> 2612.7602 | I33: =(I32/$E$32)*$E$33 -> 1318.7238 | K33: =(K32/$E$32)*$E$33 -> 17214.653 | M33: =(M32/$E$32)*$E$33 -> 16117.198 | O33: =(O32/$E$32)*$E$33 -> 304.22208 | Q33: =(Q32/$E$32)*$E$33 -> 4048.2654 | S33: =(S32/$E$32)*$E$33 -> 13616.365 | U33: =(U32/$E$32)*$E$33 -> 30305.026 | W33: =(W32/$E$32)*$E$33 -> 10743.453 | Y33: =(Y32/$E$32)*$E$33 -> 20057.139 | AA33: =(AA32/$E$32)*$E$33 -> 10328.405 | AC33: =(AC32/$E$32)*$E$33 -> 5069.8397 | AE33: =(AE32/$E$32)*$E$33 -> 0 | AG33: =(AG32/$E$32)*$E$33 -> 1327.3144 | AI33: =(AI32/$E$32)*$E$33 -> 3090.4446 | AK33: =(AK32/$E$32)*$E$33 -> 19722.792 | AM33: =(AM32/$E$32)*$E$33 -> 109978.98 | AO33: =(AO32/$E$32)*$E$33 -> 19018.35 | AQ33: =(AQ32/$E$32)*$E$33 -> 72780.737 | AS33: =(AS32/$E$32)*$E$33 -> 44830.754 | AU33: =(AU32/$E$32)*$E$33 -> 20184.93 | AW33: =(AW32/$E$32)*$E$33 -> 35473.51 | AY33: =(AY32/$E$32)*$E$33 -> 22231.353 | BA33: =(BA32/$E$32)*$E$33 -> 7966.4549 | BC33: =(BC32/$E$32)*$E$33 -> 8840.7556 | BE33: =(BE32/$E$32)*$E$33 -> 2168.4872 | BG33: =(BG32/$E$32)*$E$33 -> 6507.9638 | BI33: =(BI32/$E$32)*$E$33 -> 7035.907 | BK33: =(BK32/$E$32)*$E$33 -> 55046.214 | BM33: =(BM32/$E$32)*$E$33 -> 0 | BO33: =(BO32/$E$32)*$E$33 -> 0 | BQ33: =SUM(G33:BP33) -> 567941
G34: =G36/$E$36 -> 0.0043936487 | I34: =I36/$E$36 -> 0.0022175816 | K34: =K36/$E$36 -> 0.028948365 | M34: =M36/$E$36 -> 0.027102872 | O34: =O36/$E$36 -> 0.00051158347 | Q34: =Q36/$E$36 -> 0.0068076113 | S34: =S36/$E$36 -> 0.022897441 | U34: =U36/$E$36 -> 0.050961292 | W34: =W36/$E$36 -> 0.018066318 | Y34: =Y36/$E$36 -> 0.033728324 | AA34: =AA36/$E$36 -> 0.017368368 | AC34: =AC36/$E$36 -> 0.0085255028 | AE34: =AE36/$E$36 -> 0 | AG34: =AG36/$E$36 -> 0.0022320276 | AI34: =AI36/$E$36 -> 0.0051969284 | AK34: =AK36/$E$36 -> 0.033166081 | AM34: =AM36/$E$36 -> 0.19959237 | AO34: =AO36/$E$36 -> 0.031981484 | AQ34: =AQ36/$E$36 -> 0.12238895 | AS34: =AS36/$E$36 -> 0.07538793 | AU34: =AU36/$E$36 -> 0.033943218 | AW34: =AW36/$E$36 -> 0.062443981 | AY34: =AY36/$E$36 -> 0.037384507 | BA34: =BA36/$E$36 -> 0.013396485 | BC34: =BC36/$E$36 -> 0.01486672 | BE34: =BE36/$E$36 -> 0.0036465539 | BG34: =BG36/$E$36 -> 0.010943869 | BI34: =BI36/$E$36 -> 0.011831665 | BK34: =BK36/$E$36 -> 0.092566369 | BM34: =BM36/$E$36 -> 0 | BO34: =BO36/$E$36 -> 0.027501952
B35: Incentive Cost | E35: =if(sum(G35:BS35)=0,"--",sum(G35:BS35)) -> 42748.99 | AM35: 13935 | AW35: 2655 | BO35: 26158.99
B36: Total Spend | E36: =sum(E32:F33,E35) -> 951168.5 | G36: =sum(G32:H33,G35) -> 4179.1002 | I36: =sum(I32:J33,I35) -> 2109.2938 | K36: =sum(K32:L33,K35) -> 27534.773 | M36: =sum(M32:N33,M35) -> 25779.398 | O36: =sum(O32:P33,O35) -> 486.60208 | Q36: =sum(Q32:R33,Q35) -> 6475.1854 | S36: =sum(S32:T33,S35) -> 21779.325 | U36: =sum(U32:V33,U35) -> 48472.776 | W36: =sum(W32:X33,W35) -> 17184.113 | Y36: =sum(Y32:Z33,Y35) -> 32081.319 | AA36: =sum(AA32:AB33,AA35) -> 16520.245 | AC36: =sum(AC32:AD33,AC35) -> 8109.1897 | AE36: =sum(AE32:AF33,AE35) -> 0 | AG36: =sum(AG32:AH33,AG35) -> 2123.0344 | AI36: =sum(AI32:AJ33,AI35) -> 4943.1546 | AK36: =sum(AK32:AL33,AK35) -> 31546.532 | AM36: =sum(AM32:AN33,AM35) -> 189845.97 | AO36: =sum(AO32:AP33,AO35) -> 30419.78 | AQ36: =sum(AQ32:AR33,AQ35) -> 116412.52 | AS36: =sum(AS32:AT33,AS35) -> 71706.624 | AU36: =sum(AU32:AV33,AU35) -> 32285.72 | AW36: =sum(AW32:AX33,AW35) -> 59394.748 | AY36: =sum(AY32:AZ33,AY35) -> 35558.965 | BA36: =sum(BA32:BB33,BA35) -> 12742.315 | BC36: =sum(BC32:BD33,BC35) -> 14140.756 | BE36: =sum(BE32:BF33,BE35) -> 3468.4872 | BG36: =sum(BG32:BH33,BG35) -> 10409.464 | BI36: =sum(BI32:BJ33,BI35) -> 11253.907 | BK36: =sum(BK32:BL33,BK35) -> 88046.214 | BM36: =sum(BM32:BN33,BM35) -> 0 | BO36: =sum(BO32:BP33,BO35) -> 26158.99
B37: Form Fills | E37: =if(isblank(B37),,if($E$36="--","--",sum(G37:BS37))) -> 689 | G37: 9 | I37: 1 | K37: 3 | M37: 4 | O37: 0 | Q37: 3 | S37: 3 | U37: 7 | W37: 8 | Y37: 0 | AA37: 9 | AC37: 0 | AE37: 0 | AG37: 0 | AI37: 1 | AK37: 0 | AM37: 164 | AO37: 54 | AQ37: 111 | AS37: 41 | AU37: 0 | AW37: 84 | BA37: 1 | BC37: 12 | BE37: 0 | BG37: 0 | BI37: 0 | BK37: 0 | BM37: 48 | BO37: 126
B38: Intro Held | E38: =if(isblank(B38),,if($E$36="--","--",sum(G38:BS38))) -> 373 | G38: 6 | I38: 0 | K38: 4 | M38: 0 | O38: 0 | Q38: 0 | S38: 2 | U38: 3 | W38: 8 | Y38: 0 | AA38: 4 | AC38: 0 | AE38: 0 | AG38: 0 | AI38: 0 | AK38: 0 | AM38: 86 | AO38: 18 | AQ38: 73 | AS38: 12 | AU38: 0 | AW38: 44 | BA38: 0 | BC38: 3 | BE38: 0 | BG38: 0 | BI38: 0 | BK38: 0 | BM38: 22 | BO38: 88
B39: Strat Call Held | E39: =if(isblank(B39),,if($E$36="--","--",sum(G39:BS39))) -> 156 | G39: 2 | I39: 0 | K39: 0 | M39: 0 | O39: 0 | Q39: 0 | S39: 0 | U39: 3 | W39: 0 | Y39: 0 | AA39: 1 | AC39: 0 | AE39: 0 | AG39: 0 | AI39: 0 | AK39: 0 | AM39: 25 | AO39: 7 | AQ39: 13 | AS39: 9 | AU39: 0 | AW39: 10 | BA39: 0 | BC39: 2 | BE39: 0 | BG39: 0 | BI39: 0 | BK39: 0 | BM39: 15 | BO39: 69
B40: Proposals | E40: =if(isblank(B40),,if($E$36="--","--",sum(G40:BS40))) -> 104 | G40: 4 | I40: 0 | K40: 0 | M40: 0 | O40: 0 | Q40: 0 | S40: 0 | U40: 1 | W40: 0 | Y40: 0 | AA40: 2 | AC40: 0 | AE40: 0 | AG40: 0 | AI40: 0 | AK40: 0 | AM40: 9 | AO40: 1 | AQ40: 13 | AS40: 3 | AU40: 0 | AW40: 9 | BA40: 0 | BC40: 0 | BE40: 0 | BG40: 0 | BI40: 0 | BK40: 0 | BM40: 0 | BO40: 62
E41: =if(isblank(B41),,if($E$36="--","--",sum(G41:BS41)))
B42: Customers | E42: =if(isblank(B42),,if($E$36="--","--",sum(G42:BS42))) -> 23 | G42: 0 | I42: 0 | K42: 0 | M42: 0 | O42: 0 | Q42: 0 | S42: 0 | U42: 0 | W42: 0 | Y42: 0 | AA42: 1 | AC42: 0 | AE42: 0 | AG42: 0 | AI42: 0 | AK42: 0 | AM42: 6 | AO42: 0 | AQ42: 0 | AS42: 3 | AU42: 0 | AW42: 0 | BA42: 0 | BC42: 0 | BE42: 0 | BG42: 0 | BI42: 0 | BK42: 0 | BM42: 0 | BO42: 13
B43: AAAa | E43: =if(X16="Yes",iferror(average(G43:BS43),""),X15) -> 6490.398 | AA43: 1895.8333 | AM43: 5836.8056 | AS43: 9097.2222 | BO43: 9131.7308
B44: Total AOV | AA44: 22750 | AM44: 420250 | AS44: 327500
G45: =(G44*$AG$13)/(1-$AG$14) -> 0 | I45: =(I44*$AG$13)/(1-$AG$14) -> 0 | K45: =(K44*$AG$13)/(1-$AG$14) -> 0 | M45: =(M44*$AG$13)/(1-$AG$14) -> 0 | O45: =(O44*$AG$13)/(1-$AG$14) -> 0 | Q45: =(Q44*$AG$13)/(1-$AG$14) -> 0 | S45: =(S44*$AG$13)/(1-$AG$14) -> 0 | U45: =(U44*$AG$13)/(1-$AG$14) -> 0 | W45: =(W44*$AG$13)/(1-$AG$14) -> 0 | Y45: =(Y44*$AG$13)/(1-$AG$14) -> 0 | AA45: =(AA44*$AG$13)/(1-$AG$14) -> 20538.194 | AC45: =(AC44*$AG$13)/(1-$AG$14) -> 0 | AE45: =(AE44*$AG$13)/(1-$AG$14) -> 0 | AG45: =(AG44*$AG$13)/(1-$AG$14) -> 0 | AI45: =(AI44*$AG$13)/(1-$AG$14) -> 0 | AK45: =(AK44*$AG$13)/(1-$AG$14) -> 0 | AM45: =(AM44*$AG$13)/(1-$AG$14) -> 379392.36 | AO45: =(AO44*$AG$13)/(1-$AG$14) -> 0 | AQ45: =(AQ44*$AG$13)/(1-$AG$14) -> 0 | AS45: =(AS44*$AG$13)/(1-$AG$14) -> 295659.72 | AU45: =(AU44*$AG$13)/(1-$AG$14) -> 0 | AW45: =(AW44*$AG$13)/(1-$AG$14) -> 0 | AY45: =(AY44*$AG$13)/(1-$AG$14) -> 0 | BA45: =(BA44*$AG$13)/(1-$AG$14) -> 0 | BC45: =(BC44*$AG$13)/(1-$AG$14) -> 0 | BE45: =(BE44*$AG$13)/(1-$AG$14) -> 0 | BG45: =(BG44*$AG$13)/(1-$AG$14) -> 0 | BI45: =(BI44*$AG$13)/(1-$AG$14) -> 0 | BK45: =(BK44*$AG$13)/(1-$AG$14) -> 0 | BM45: =(BM44*$AG$13)/(1-$AG$14) -> 0 | BO45: =(BO44*$AG$13)/(1-$AG$14) -> 0
B46: Lifetime Value (LTV) | E46: =if(E36="--","--", if(X16="No",$X$17,iferror(average(G46:BS46),""))) -> 46730.865 | G46: =if($X$16="Yes",if(isblank(G36),"--",if(isblank($X$13),"Enter GM%",if(isblank($X$14),"Enter Lifespan",if(ISBLANK(G43),"Enter AOV",$X$13*$X$14*G43)))),if(isblank(G36),"--",$X$17)) -> Enter AOV | I46: =if($X$16="Yes",if(isblank(I36),"--",if(isblank($X$13),"Enter GM%",if(isblank($X$14),"Enter Lifespan",if(ISBLANK(I43),"Enter AOV",$X$13*$X$14*I43)))),if(isblank(I36),"--",$X$17)) -> Enter AOV | K46: =if($X$16="Yes",if(isblank(K36),"--",if(isblank($X$13),"Enter GM%",if(isblank($X$14),"Enter Lifespan",if(ISBLANK(K43),"Enter AOV",$X$13*$X$14*K43)))),if(isblank(K36),"--",$X$17)) -> Enter AOV | M46: =if($X$16="Yes",if(isblank(M36),"--",if(isblank($X$13),"Enter GM%",if(isblank($X$14),"Enter Lifespan",if(ISBLANK(M43),"Enter AOV",$X$13*$X$14*M43)))),if(isblank(M36),"--",$X$17)) -> Enter AOV | O46: =if($X$16="Yes",if(isblank(O36),"--",if(isblank($X$13),"Enter GM%",if(isblank($X$14),"Enter Lifespan",if(ISBLANK(O43),"Enter AOV",$X$13*$X$14*O43)))),if(isblank(O36),"--",$X$17)) -> Enter AOV | Q46: =if($X$16="Yes",if(isblank(Q36),"--",if(isblank($X$13),"Enter GM%",if(isblank($X$14),"Enter Lifespan",if(ISBLANK(Q43),"Enter AOV",$X$13*$X$14*Q43)))),if(isblank(Q36),"--",$X$17)) -> Enter AOV | S46: =if($X$16="Yes",if(isblank(S36),"--",if(isblank($X$13),"Enter GM%",if(isblank($X$14),"Enter Lifespan",if(ISBLANK(S43),"Enter AOV",$X$13*$X$14*S43)))),if(isblank(S36),"--",$X$17)) -> Enter AOV | U46: =if($X$16="Yes",if(isblank(U36),"--",if(isblank($X$13),"Enter GM%",if(isblank($X$14),"Enter Lifespan",if(ISBLANK(U43),"Enter AOV",$X$13*$X$14*U43)))),if(isblank(U36),"--",$X$17)) -> Enter AOV | W46: =if($X$16="Yes",if(isblank(W36),"--",if(isblank($X$13),"Enter GM%",if(isblank($X$14),"Enter Lifespan",if(ISBLANK(W43),"Enter AOV",$X$13*$X$14*W43)))),if(isblank(W36),"--",$X$17)) -> Enter AOV | Y46: =if($X$16="Yes",if(isblank(Y36),"--",if(isblank($X$13),"Enter GM%",if(isblank($X$14),"Enter Lifespan",if(ISBLANK(Y43),"Enter AOV",$X$13*$X$14*Y43)))),if(isblank(Y36),"--",$X$17)) -> Enter AOV | AA46: =if($X$16="Yes",if(isblank(AA36),"--",if(isblank($X$13),"Enter GM%",if(isblank($X$14),"Enter Lifespan",if(ISBLANK(AA43),"Enter AOV",$X$13*$X$14*AA43)))),if(isblank(AA36),"--",$X$17)) -> 13650 | AC46: =if($X$16="Yes",if(isblank(AC36),"--",if(isblank($X$13),"Enter GM%",if(isblank($X$14),"Enter Lifespan",if(ISBLANK(AC43),"Enter AOV",$X$13*$X$14*AC43)))),if(isblank(AC36),"--",$X$17)) -> Enter AOV | AE46: =if($X$16="Yes",if(isblank(AE36),"--",if(isblank($X$13),"Enter GM%",if(isblank($X$14),"Enter Lifespan",if(ISBLANK(AE43),"Enter AOV",$X$13*$X$14*AE43)))),if(isblank(AE36),"--",$X$17)) -> Enter AOV | AG46: =if($X$16="Yes",if(isblank(AG36),"--",if(isblank($X$13),"Enter GM%",if(isblank($X$14),"Enter Lifespan",if(ISBLANK(AG43),"Enter AOV",$X$13*$X$14*AG43)))),if(isblank(AG36),"--",$X$17)) -> Enter AOV | AI46: =if($X$16="Yes",if(isblank(AI36),"--",if(isblank($X$13),"Enter GM%",if(isblank($X$14),"Enter Lifespan",if(ISBLANK(AI43),"Enter AOV",$X$13*$X$14*AI43)))),if(isblank(AI36),"--",$X$17)) -> Enter AOV | AK46: =if($X$16="Yes",if(isblank(AK36),"--",if(isblank($X$13),"Enter GM%",if(isblank($X$14),"Enter Lifespan",if(ISBLANK(AK43),"Enter AOV",$X$13*$X$14*AK43)))),if(isblank(AK36),"--",$X$17)) -> Enter AOV | AM46: =if($X$16="Yes",if(isblank(AM36),"--",if(isblank($X$13),"Enter GM%",if(isblank($X$14),"Enter Lifespan",if(ISBLANK(AM43),"Enter AOV",$X$13*$X$14*AM43)))),if(isblank(AM36),"--",$X$17)) -> 42025 | AO46: =if($X$16="Yes",if(isblank(AO36),"--",if(isblank($X$13),"Enter GM%",if(isblank($X$14),"Enter Lifespan",if(ISBLANK(AO43),"Enter AOV",$X$13*$X$14*AO43)))),if(isblank(AO36),"--",$X$17)) -> Enter AOV | AQ46: =if($X$16="Yes",if(isblank(AQ36),"--",if(isblank($X$13),"Enter GM%",if(isblank($X$14),"Enter Lifespan",if(ISBLANK(AQ43),"Enter AOV",$X$13*$X$14*AQ43)))),if(isblank(AQ36),"--",$X$17)) -> Enter AOV | AS46: =if($X$16="Yes",if(isblank(AS36),"--",if(isblank($X$13),"Enter GM%",if(isblank($X$14),"Enter Lifespan",if(ISBLANK(AS43),"Enter AOV",$X$13*$X$14*AS43)))),if(isblank(AS36),"--",$X$17)) -> 65500 | AU46: =if($X$16="Yes",if(isblank(AU36),"--",if(isblank($X$13),"Enter GM%",if(isblank($X$14),"Enter Lifespan",if(ISBLANK(AU43),"Enter AOV",$X$13*$X$14*AU43)))),if(isblank(AU36),"--",$X$17)) -> Enter AOV | AW46: =if($X$16="Yes",if(isblank(AW36),"--",if(isblank($X$13),"Enter GM%",if(isblank($X$14),"Enter Lifespan",if(ISBLANK(AW43),"Enter AOV",$X$13*$X$14*AW43)))),if(isblank(AW36),"--",$X$17)) -> Enter AOV | AY46: =if($X$16="Yes",if(isblank(AY36),"--",if(isblank($X$13),"Enter GM%",if(isblank($X$14),"Enter Lifespan",if(ISBLANK(AY43),"Enter AOV",$X$13*$X$14*AY43)))),if(isblank(AY36),"--",$X$17)) -> Enter AOV | BA46: =if($X$16="Yes",if(isblank(BA36),"--",if(isblank($X$13),"Enter GM%",if(isblank($X$14),"Enter Lifespan",if(ISBLANK(BA43),"Enter AOV",$X$13*$X$14*BA43)))),if(isblank(BA36),"--",$X$17)) -> Enter AOV | BC46: =if($X$16="Yes",if(isblank(BC36),"--",if(isblank($X$13),"Enter GM%",if(isblank($X$14),"Enter Lifespan",if(ISBLANK(BC43),"Enter AOV",$X$13*$X$14*BC43)))),if(isblank(BC36),"--",$X$17)) -> Enter AOV | BE46: =if($X$16="Yes",if(isblank(BE36),"--",if(isblank($X$13),"Enter GM%",if(isblank($X$14),"Enter Lifespan",if(ISBLANK(BE43),"Enter AOV",$X$13*$X$14*BE43)))),if(isblank(BE36),"--",$X$17)) -> Enter AOV | BG46: =if($X$16="Yes",if(isblank(BG36),"--",if(isblank($X$13),"Enter GM%",if(isblank($X$14),"Enter Lifespan",if(ISBLANK(BG43),"Enter AOV",$X$13*$X$14*BG43)))),if(isblank(BG36),"--",$X$17)) -> Enter AOV | BI46: =if($X$16="Yes",if(isblank(BI36),"--",if(isblank($X$13),"Enter GM%",if(isblank($X$14),"Enter Lifespan",if(ISBLANK(BI43),"Enter AOV",$X$13*$X$14*BI43)))),if(isblank(BI36),"--",$X$17)) -> Enter AOV | BK46: =if($X$16="Yes",if(isblank(BK36),"--",if(isblank($X$13),"Enter GM%",if(isblank($X$14),"Enter Lifespan",if(ISBLANK(BK43),"Enter AOV",$X$13*$X$14*BK43)))),if(isblank(BK36),"--",$X$17)) -> Enter AOV | BM46: =if($X$16="Yes",if(isblank(BM36),"--",if(isblank($X$13),"Enter GM%",if(isblank($X$14),"Enter Lifespan",if(ISBLANK(BM43),"Enter AOV",$X$13*$X$14*BM43)))),if(isblank(BM36),"--",$X$17)) -> Enter AOV | BO46: =if($X$16="Yes",if(isblank(BO36),"--",if(isblank($X$13),"Enter GM%",if(isblank($X$14),"Enter Lifespan",if(ISBLANK(BO43),"Enter AOV",$X$13*$X$14*BO43)))),if(isblank(BO36),"--",$X$17)) -> 65748.462
B47: Total Est. Bookings | E47: =if(E36="--","--",sum(G47:BS47)) -> 1317030 | G47: =if(isblank(G36),"--",if(or(isblank(G42),G42=0),"No Customers",if(isnumber(G46),G46*G42,"No LTV"))) -> No Customers | I47: =if(isblank(I36),"--",if(or(isblank(I42),I42=0),"No Customers",if(isnumber(I46),I46*I42,"No LTV"))) -> No Customers | K47: =if(isblank(K36),"--",if(or(isblank(K42),K42=0),"No Customers",if(isnumber(K46),K46*K42,"No LTV"))) -> No Customers | M47: =if(isblank(M36),"--",if(or(isblank(M42),M42=0),"No Customers",if(isnumber(M46),M46*M42,"No LTV"))) -> No Customers | O47: =if(isblank(O36),"--",if(or(isblank(O42),O42=0),"No Customers",if(isnumber(O46),O46*O42,"No LTV"))) -> No Customers | Q47: =if(isblank(Q36),"--",if(or(isblank(Q42),Q42=0),"No Customers",if(isnumber(Q46),Q46*Q42,"No LTV"))) -> No Customers | S47: =if(isblank(S36),"--",if(or(isblank(S42),S42=0),"No Customers",if(isnumber(S46),S46*S42,"No LTV"))) -> No Customers | U47: =if(isblank(U36),"--",if(or(isblank(U42),U42=0),"No Customers",if(isnumber(U46),U46*U42,"No LTV"))) -> No Customers | W47: =if(isblank(W36),"--",if(or(isblank(W42),W42=0),"No Customers",if(isnumber(W46),W46*W42,"No LTV"))) -> No Customers | Y47: =if(isblank(Y36),"--",if(or(isblank(Y42),Y42=0),"No Customers",if(isnumber(Y46),Y46*Y42,"No LTV"))) -> No Customers | AA47: =if(isblank(AA36),"--",if(or(isblank(AA42),AA42=0),"No Customers",if(isnumber(AA46),AA46*AA42,"No LTV"))) -> 13650 | AC47: =if(isblank(AC36),"--",if(or(isblank(AC42),AC42=0),"No Customers",if(isnumber(AC46),AC46*AC42,"No LTV"))) -> No Customers | AE47: =if(isblank(AE36),"--",if(or(isblank(AE42),AE42=0),"No Customers",if(isnumber(AE46),AE46*AE42,"No LTV"))) -> No Customers | AG47: =if(isblank(AG36),"--",if(or(isblank(AG42),AG42=0),"No Customers",if(isnumber(AG46),AG46*AG42,"No LTV"))) -> No Customers | AI47: =if(isblank(AI36),"--",if(or(isblank(AI42),AI42=0),"No Customers",if(isnumber(AI46),AI46*AI42,"No LTV"))) -> No Customers | AK47: =if(isblank(AK36),"--",if(or(isblank(AK42),AK42=0),"No Customers",if(isnumber(AK46),AK46*AK42,"No LTV"))) -> No Customers | AM47: =if(isblank(AM36),"--",if(or(isblank(AM42),AM42=0),"No Customers",if(isnumber(AM46),AM46*AM42,"No LTV"))) -> 252150 | AO47: =if(isblank(AO36),"--",if(or(isblank(AO42),AO42=0),"No Customers",if(isnumber(AO46),AO46*AO42,"No LTV"))) -> No Customers | AQ47: =if(isblank(AQ36),"--",if(or(isblank(AQ42),AQ42=0),"No Customers",if(isnumber(AQ46),AQ46*AQ42,"No LTV"))) -> No Customers | AS47: =if(isblank(AS36),"--",if(or(isblank(AS42),AS42=0),"No Customers",if(isnumber(AS46),AS46*AS42,"No LTV"))) -> 196500 | AU47: =if(isblank(AU36),"--",if(or(isblank(AU42),AU42=0),"No Customers",if(isnumber(AU46),AU46*AU42,"No LTV"))) -> No Customers | AW47: =if(isblank(AW36),"--",if(or(isblank(AW42),AW42=0),"No Customers",if(isnumber(AW46),AW46*AW42,"No LTV"))) -> No Customers | AY47: =if(isblank(AY36),"--",if(or(isblank(AY42),AY42=0),"No Customers",if(isnumber(AY46),AY46*AY42,"No LTV"))) -> No Customers | BA47: =if(isblank(BA36),"--",if(or(isblank(BA42),BA42=0),"No Customers",if(isnumber(BA46),BA46*BA42,"No LTV"))) -> No Customers | BC47: =if(isblank(BC36),"--",if(or(isblank(BC42),BC42=0),"No Customers",if(isnumber(BC46),BC46*BC42,"No LTV"))) -> No Customers | BE47: =if(isblank(BE36),"--",if(or(isblank(BE42),BE42=0),"No Customers",if(isnumber(BE46),BE46*BE42,"No LTV"))) -> No Customers | BG47: =if(isblank(BG36),"--",if(or(isblank(BG42),BG42=0),"No Customers",if(isnumber(BG46),BG46*BG42,"No LTV"))) -> No Customers | BI47: =if(isblank(BI36),"--",if(or(isblank(BI42),BI42=0),"No Customers",if(isnumber(BI46),BI46*BI42,"No LTV"))) -> No Customers | BK47: =if(isblank(BK36),"--",if(or(isblank(BK42),BK42=0),"No Customers",if(isnumber(BK46),BK46*BK42,"No LTV"))) -> No Customers | BM47: =if(isblank(BM36),"--",if(or(isblank(BM42),BM42=0),"No Customers",if(isnumber(BM46),BM46*BM42,"No LTV"))) -> No Customers | BO47: =if(isblank(BO36),"--",if(or(isblank(BO42),BO42=0),"No Customers",if(isnumber(BO46),BO46*BO42,"No LTV"))) -> 854730
B48: Net Return | E48: =if(E36="--","--",sum(G48:BS48)) -> 1012798.2 | G48: =if(isblank(G36),"--",if(istext(G47),G47,G47-G36)) -> No Customers | I48: =if(isblank(I36),"--",if(istext(I47),I47,I47-I36)) -> No Customers | K48: =if(isblank(K36),"--",if(istext(K47),K47,K47-K36)) -> No Customers | M48: =if(isblank(M36),"--",if(istext(M47),M47,M47-M36)) -> No Customers | O48: =if(isblank(O36),"--",if(istext(O47),O47,O47-O36)) -> No Customers | Q48: =if(isblank(Q36),"--",if(istext(Q47),Q47,Q47-Q36)) -> No Customers | S48: =if(isblank(S36),"--",if(istext(S47),S47,S47-S36)) -> No Customers | U48: =if(isblank(U36),"--",if(istext(U47),U47,U47-U36)) -> No Customers | W48: =if(isblank(W36),"--",if(istext(W47),W47,W47-W36)) -> No Customers | Y48: =if(isblank(Y36),"--",if(istext(Y47),Y47,Y47-Y36)) -> No Customers | AA48: =if(isblank(AA36),"--",if(istext(AA47),AA47,AA47-AA36)) -> -2870.2446 | AC48: =if(isblank(AC36),"--",if(istext(AC47),AC47,AC47-AC36)) -> No Customers | AE48: =if(isblank(AE36),"--",if(istext(AE47),AE47,AE47-AE36)) -> No Customers | AG48: =if(isblank(AG36),"--",if(istext(AG47),AG47,AG47-AG36)) -> No Customers | AI48: =if(isblank(AI36),"--",if(istext(AI47),AI47,AI47-AI36)) -> No Customers | AK48: =if(isblank(AK36),"--",if(istext(AK47),AK47,AK47-AK36)) -> No Customers | AM48: =if(isblank(AM36),"--",if(istext(AM47),AM47,AM47-AM36)) -> 62304.027 | AO48: =if(isblank(AO36),"--",if(istext(AO47),AO47,AO47-AO36)) -> No Customers | AQ48: =if(isblank(AQ36),"--",if(istext(AQ47),AQ47,AQ47-AQ36)) -> No Customers | AS48: =if(isblank(AS36),"--",if(istext(AS47),AS47,AS47-AS36)) -> 124793.38 | AU48: =if(isblank(AU36),"--",if(istext(AU47),AU47,AU47-AU36)) -> No Customers | AW48: =if(isblank(AW36),"--",if(istext(AW47),AW47,AW47-AW36)) -> No Customers | AY48: =if(isblank(AY36),"--",if(istext(AY47),AY47,AY47-AY36)) -> No Customers | BA48: =if(isblank(BA36),"--",if(istext(BA47),BA47,BA47-BA36)) -> No Customers | BC48: =if(isblank(BC36),"--",if(istext(BC47),BC47,BC47-BC36)) -> No Customers | BE48: =if(isblank(BE36),"--",if(istext(BE47),BE47,BE47-BE36)) -> No Customers | BG48: =if(isblank(BG36),"--",if(istext(BG47),BG47,BG47-BG36)) -> No Customers | BI48: =if(isblank(BI36),"--",if(istext(BI47),BI47,BI47-BI36)) -> No Customers | BK48: =if(isblank(BK36),"--",if(istext(BK47),BK47,BK47-BK36)) -> No Customers | BM48: =if(isblank(BM36),"--",if(istext(BM47),BM47,BM47-BM36)) -> No Customers | BO48: =if(isblank(BO36),"--",if(istext(BO47),BO47,BO47-BO36)) -> 828571.01
B49: =if(ISBLANK(B37),"--","Cost-per-"&LEFT(B37,LEN(B37)-1)) -> Cost-per-Form Fill | E49: =iferror($E$36/E37,"--") -> 1380.5058 | G49: =iferror(G$36/G37,"--") -> 464.34447 | I49: =iferror(I$36/I37,"--") -> 2109.2938 | K49: =iferror(K$36/K37,"--") -> 9178.2575 | M49: =iferror(M$36/M37,"--") -> 6444.8495 | O49: =iferror(O$36/O37,"--") -> -- | Q49: =iferror(Q$36/Q37,"--") -> 2158.3951 | S49: =iferror(S$36/S37,"--") -> 7259.775 | U49: =iferror(U$36/U37,"--") -> 6924.6823 | W49: =iferror(W$36/W37,"--") -> 2148.0141 | Y49: =iferror(Y$36/Y37,"--") -> -- | AA49: =iferror(AA$36/AA37,"--") -> 1835.5827 | AC49: =iferror(AC$36/AC37,"--") -> -- | AE49: =iferror(AE$36/AE37,"--") -> -- | AG49: =iferror(AG$36/AG37,"--") -> -- | AI49: =iferror(AI$36/AI37,"--") -> 4943.1546 | AK49: =iferror(AK$36/AK37,"--") -> -- | AM49: =iferror(AM$36/AM37,"--") -> 1157.5974 | AO49: =iferror(AO$36/AO37,"--") -> 563.32926 | AQ49: =iferror(AQ$36/AQ37,"--") -> 1048.7614 | AS49: =iferror(AS$36/AS37,"--") -> 1748.9421 | AU49: =iferror(AU$36/AU37,"--") -> -- | AW49: =iferror(AW$36/AW37,"--") -> 707.08033 | AY49: =iferror(AY$36/AY37,"--") -> -- | BA49: =iferror(BA$36/BA37,"--") -> 12742.315 | BC49: =iferror(BC$36/BC37,"--") -> 1178.3963 | BE49: =iferror(BE$36/BE37,"--") -> -- | BG49: =iferror(BG$36/BG37,"--") -> -- | BI49: =iferror(BI$36/BI37,"--") -> -- | BK49: =iferror(BK$36/BK37,"--") -> -- | BM49: =iferror(BM$36/BM37,"--") -> 0 | BO49: =iferror(BO$36/BO37,"--") -> 207.61103
B50: =if(ISBLANK(B38),"--","Cost-per-"&LEFT(B38,LEN(B38)-1)) -> Cost-per-Intro Held | E50: =iferror($E$36/E38,"--") -> 2550.0496 | G50: =iferror(G$36/G38,"--") -> 696.5167 | I50: =iferror(I$36/I38,"--") -> -- | K50: =iferror(K$36/K38,"--") -> 6883.6932 | M50: =iferror(M$36/M38,"--") -> -- | O50: =iferror(O$36/O38,"--") -> -- | Q50: =iferror(Q$36/Q38,"--") -> -- | S50: =iferror(S$36/S38,"--") -> 10889.663 | U50: =iferror(U$36/U38,"--") -> 16157.592 | W50: =iferror(W$36/W38,"--") -> 2148.0141 | Y50: =iferror(Y$36/Y38,"--") -> -- | AA50: =iferror(AA$36/AA38,"--") -> 4130.0611 | AC50: =iferror(AC$36/AC38,"--") -> -- | AE50: =iferror(AE$36/AE38,"--") -> -- | AG50: =iferror(AG$36/AG38,"--") -> -- | AI50: =iferror(AI$36/AI38,"--") -> -- | AK50: =iferror(AK$36/AK38,"--") -> -- | AM50: =iferror(AM$36/AM38,"--") -> 2207.5113 | AO50: =iferror(AO$36/AO38,"--") -> 1689.9878 | AQ50: =iferror(AQ$36/AQ38,"--") -> 1594.692 | AS50: =iferror(AS$36/AS38,"--") -> 5975.552 | AU50: =iferror(AU$36/AU38,"--") -> -- | AW50: =iferror(AW$36/AW38,"--") -> 1349.8806 | AY50: =iferror(AY$36/AY38,"--") -> -- | BA50: =iferror(BA$36/BA38,"--") -> -- | BC50: =iferror(BC$36/BC38,"--") -> 4713.5852 | BE50: =iferror(BE$36/BE38,"--") -> -- | BG50: =iferror(BG$36/BG38,"--") -> -- | BI50: =iferror(BI$36/BI38,"--") -> -- | BK50: =iferror(BK$36/BK38,"--") -> -- | BM50: =iferror(BM$36/BM38,"--") -> 0 | BO50: =iferror(BO$36/BO38,"--") -> 297.26125
B51: =if(ISBLANK(B39),"--","Cost-per-"&LEFT(B39,LEN(B39)-1)) -> Cost-per-Strat Call Held | E51: =iferror($E$36/E39,"--") -> 6097.234 | G51: =iferror(G$36/G39,"--") -> 2089.5501 | I51: =iferror(I$36/I39,"--") -> -- | K51: =iferror(K$36/K39,"--") -> -- | M51: =iferror(M$36/M39,"--") -> -- | O51: =iferror(O$36/O39,"--") -> -- | Q51: =iferror(Q$36/Q39,"--") -> -- | S51: =iferror(S$36/S39,"--") -> -- | U51: =iferror(U$36/U39,"--") -> 16157.592 | W51: =iferror(W$36/W39,"--") -> -- | Y51: =iferror(Y$36/Y39,"--") -> -- | AA51: =iferror(AA$36/AA39,"--") -> 16520.245 | AC51: =iferror(AC$36/AC39,"--") -> -- | AE51: =iferror(AE$36/AE39,"--") -> -- | AG51: =iferror(AG$36/AG39,"--") -> -- | AI51: =iferror(AI$36/AI39,"--") -> -- | AK51: =iferror(AK$36/AK39,"--") -> -- | AM51: =iferror(AM$36/AM39,"--") -> 7593.8389 | AO51: =iferror(AO$36/AO39,"--") -> 4345.6829 | AQ51: =iferror(AQ$36/AQ39,"--") -> 8954.809 | AS51: =iferror(AS$36/AS39,"--") -> 7967.4027 | AU51: =iferror(AU$36/AU39,"--") -> -- | AW51: =iferror(AW$36/AW39,"--") -> 5939.4748 | AY51: =iferror(AY$36/AY39,"--") -> -- | BA51: =iferror(BA$36/BA39,"--") -> -- | BC51: =iferror(BC$36/BC39,"--") -> 7070.3778 | BE51: =iferror(BE$36/BE39,"--") -> -- | BG51: =iferror(BG$36/BG39,"--") -> -- | BI51: =iferror(BI$36/BI39,"--") -> -- | BK51: =iferror(BK$36/BK39,"--") -> -- | BM51: =iferror(BM$36/BM39,"--") -> 0 | BO51: =iferror(BO$36/BO39,"--") -> 379.1158
B52: =if(ISBLANK(B40),"--","Cost-per-"&LEFT(B40,LEN(B40)-1)) -> Cost-per-Proposal | E52: =iferror($E$36/E40,"--") -> 9145.851 | G52: =iferror(G$36/G40,"--") -> 1044.7751 | I52: =iferror(I$36/I40,"--") -> -- | K52: =iferror(K$36/K40,"--") -> -- | M52: =iferror(M$36/M40,"--") -> -- | O52: =iferror(O$36/O40,"--") -> -- | Q52: =iferror(Q$36/Q40,"--") -> -- | S52: =iferror(S$36/S40,"--") -> -- | U52: =iferror(U$36/U40,"--") -> 48472.776 | W52: =iferror(W$36/W40,"--") -> -- | Y52: =iferror(Y$36/Y40,"--") -> -- | AA52: =iferror(AA$36/AA40,"--") -> 8260.1223 | AC52: =iferror(AC$36/AC40,"--") -> -- | AE52: =iferror(AE$36/AE40,"--") -> -- | AG52: =iferror(AG$36/AG40,"--") -> -- | AI52: =iferror(AI$36/AI40,"--") -> -- | AK52: =iferror(AK$36/AK40,"--") -> -- | AM52: =iferror(AM$36/AM40,"--") -> 21093.997 | AO52: =iferror(AO$36/AO40,"--") -> 30419.78 | AQ52: =iferror(AQ$36/AQ40,"--") -> 8954.809 | AS52: =iferror(AS$36/AS40,"--") -> 23902.208 | AU52: =iferror(AU$36/AU40,"--") -> -- | AW52: =iferror(AW$36/AW40,"--") -> 6599.4164 | AY52: =iferror(AY$36/AY40,"--") -> -- | BA52: =iferror(BA$36/BA40,"--") -> -- | BC52: =iferror(BC$36/BC40,"--") -> -- | BE52: =iferror(BE$36/BE40,"--") -> -- | BG52: =iferror(BG$36/BG40,"--") -> -- | BI52: =iferror(BI$36/BI40,"--") -> -- | BK52: =iferror(BK$36/BK40,"--") -> -- | BM52: =iferror(BM$36/BM40,"--") -> -- | BO52: =iferror(BO$36/BO40,"--") -> 421.91919
B53: =if(ISBLANK(B41),"--","Cost-per-"&LEFT(B41,LEN(B41)-1)) -> -- | E53: =iferror($E$36/E41,"--") -> -- | G53: =iferror(G$36/G41,"--") -> -- | I53: =iferror(I$36/I41,"--") -> -- | K53: =iferror(K$36/K41,"--") -> -- | M53: =iferror(M$36/M41,"--") -> -- | O53: =iferror(O$36/O41,"--") -> -- | Q53: =iferror(Q$36/Q41,"--") -> -- | S53: =iferror(S$36/S41,"--") -> -- | U53: =iferror(U$36/U41,"--") -> -- | W53: =iferror(W$36/W41,"--") -> -- | Y53: =iferror(Y$36/Y41,"--") -> -- | AA53: =iferror(AA$36/AA41,"--") -> -- | AC53: =iferror(AC$36/AC41,"--") -> -- | AE53: =iferror(AE$36/AE41,"--") -> -- | AG53: =iferror(AG$36/AG41,"--") -> -- | AI53: =iferror(AI$36/AI41,"--") -> -- | AK53: =iferror(AK$36/AK41,"--") -> -- | AM53: =iferror(AM$36/AM41,"--") -> -- | AO53: =iferror(AO$36/AO41,"--") -> -- | AQ53: =iferror(AQ$36/AQ41,"--") -> -- | AS53: =iferror(AS$36/AS41,"--") -> -- | AU53: =iferror(AU$36/AU41,"--") -> -- | AW53: =iferror(AW$36/AW41,"--") -> -- | AY53: =iferror(AY$36/AY41,"--") -> -- | BA53: =iferror(BA$36/BA41,"--") -> -- | BC53: =iferror(BC$36/BC41,"--") -> -- | BE53: =iferror(BE$36/BE41,"--") -> -- | BG53: =iferror(BG$36/BG41,"--") -> -- | BI53: =iferror(BI$36/BI41,"--") -> -- | BK53: =iferror(BK$36/BK41,"--") -> -- | BM53: =iferror(BM$36/BM41,"--") -> -- | BO53: =iferror(BO$36/BO41,"--") -> --
B54: =if(ISBLANK(B42),"--","Cost-per-"&LEFT(B42,LEN(B42)-1)) -> Cost-per-Customer | E54: =iferror($E$36/E42,"--") -> 41355.152 | G54: =iferror(G$36/G42,"--") -> -- | I54: =iferror(I$36/I42,"--") -> -- | K54: =iferror(K$36/K42,"--") -> -- | M54: =iferror(M$36/M42,"--") -> -- | O54: =iferror(O$36/O42,"--") -> -- | Q54: =iferror(Q$36/Q42,"--") -> -- | S54: =iferror(S$36/S42,"--") -> -- | U54: =iferror(U$36/U42,"--") -> -- | W54: =iferror(W$36/W42,"--") -> -- | Y54: =iferror(Y$36/Y42,"--") -> -- | AA54: =iferror(AA$36/AA42,"--") -> 16520.245 | AC54: =iferror(AC$36/AC42,"--") -> -- | AE54: =iferror(AE$36/AE42,"--") -> -- | AG54: =iferror(AG$36/AG42,"--") -> -- | AI54: =iferror(AI$36/AI42,"--") -> -- | AK54: =iferror(AK$36/AK42,"--") -> -- | AM54: =iferror(AM$36/AM42,"--") -> 31640.996 | AO54: =iferror(AO$36/AO42,"--") -> -- | AQ54: =iferror(AQ$36/AQ42,"--") -> -- | AS54: =iferror(AS$36/AS42,"--") -> 23902.208 | AU54: =iferror(AU$36/AU42,"--") -> -- | AW54: =iferror(AW$36/AW42,"--") -> -- | AY54: =iferror(AY$36/AY42,"--") -> -- | BA54: =iferror(BA$36/BA42,"--") -> -- | BC54: =iferror(BC$36/BC42,"--") -> -- | BE54: =iferror(BE$36/BE42,"--") -> -- | BG54: =iferror(BG$36/BG42,"--") -> -- | BI54: =iferror(BI$36/BI42,"--") -> -- | BK54: =iferror(BK$36/BK42,"--") -> -- | BM54: =iferror(BM$36/BM42,"--") -> -- | BO54: =iferror(BO$36/BO42,"--") -> 2012.23
B55: =iferror(if(match(B37,$B$37:$B$41,0)=Counta($B$37:$B$41),LEFT(B37,LEN(B37)-1)&" > "&LEFT($B$42,LEN($B$42)-1),LEFT(B37,LEN(B37)-1)&" > "&LEFT(B38,LEN(B38)-1)),"--") -> Form Fill > Intro Held | E55: =iferror(if(match(B37,$B$37:$B$41,0)=Counta($B$37:$B$41),$E$42/E37,E38/E37),"--") -> 0.5413643 | G55: =iferror(if(match($B$37,$B$37:$B$41,0)=Counta($B$37:$B$41),G42/G37,G38/G37),"--") -> 0.66666667 | I55: =iferror(if(match($B$37,$B$37:$B$41,0)=Counta($B$37:$B$41),I42/I37,I38/I37),"--") -> 0 | K55: =iferror(if(match($B$37,$B$37:$B$41,0)=Counta($B$37:$B$41),K42/K37,K38/K37),"--") -> 1.3333333 | M55: =iferror(if(match($B$37,$B$37:$B$41,0)=Counta($B$37:$B$41),M42/M37,M38/M37),"--") -> 0 | O55: =iferror(if(match($B$37,$B$37:$B$41,0)=Counta($B$37:$B$41),O42/O37,O38/O37),"--") -> -- | Q55: =iferror(if(match($B$37,$B$37:$B$41,0)=Counta($B$37:$B$41),Q42/Q37,Q38/Q37),"--") -> 0 | S55: =iferror(if(match($B$37,$B$37:$B$41,0)=Counta($B$37:$B$41),S42/S37,S38/S37),"--") -> 0.66666667 | U55: =iferror(if(match($B$37,$B$37:$B$41,0)=Counta($B$37:$B$41),U42/U37,U38/U37),"--") -> 0.42857143 | W55: =iferror(if(match($B$37,$B$37:$B$41,0)=Counta($B$37:$B$41),W42/W37,W38/W37),"--") -> 1 | Y55: =iferror(if(match($B$37,$B$37:$B$41,0)=Counta($B$37:$B$41),Y42/Y37,Y38/Y37),"--") -> -- | AA55: =iferror(if(match($B$37,$B$37:$B$41,0)=Counta($B$37:$B$41),AA42/AA37,AA38/AA37),"--") -> 0.44444444 | AC55: =iferror(if(match($B$37,$B$37:$B$41,0)=Counta($B$37:$B$41),AC42/AC37,AC38/AC37),"--") -> -- | AE55: =iferror(if(match($B$37,$B$37:$B$41,0)=Counta($B$37:$B$41),AE42/AE37,AE38/AE37),"--") -> -- | AG55: =iferror(if(match($B$37,$B$37:$B$41,0)=Counta($B$37:$B$41),AG42/AG37,AG38/AG37),"--") -> -- | AI55: =iferror(if(match($B$37,$B$37:$B$41,0)=Counta($B$37:$B$41),AI42/AI37,AI38/AI37),"--") -> 0 | AK55: =iferror(if(match($B$37,$B$37:$B$41,0)=Counta($B$37:$B$41),AK42/AK37,AK38/AK37),"--") -> -- | AM55: =iferror(if(match($B$37,$B$37:$B$41,0)=Counta($B$37:$B$41),AM42/AM37,AM38/AM37),"--") -> 0.52439024 | AO55: =iferror(if(match($B$37,$B$37:$B$41,0)=Counta($B$37:$B$41),AO42/AO37,AO38/AO37),"--") -> 0.33333333 | AQ55: =iferror(if(match($B$37,$B$37:$B$41,0)=Counta($B$37:$B$41),AQ42/AQ37,AQ38/AQ37),"--") -> 0.65765766 | AS55: =iferror(if(match($B$37,$B$37:$B$41,0)=Counta($B$37:$B$41),AS42/AS37,AS38/AS37),"--") -> 0.29268293 | AU55: =iferror(if(match($B$37,$B$37:$B$41,0)=Counta($B$37:$B$41),AU42/AU37,AU38/AU37),"--") -> -- | AW55: =iferror(if(match($B$37,$B$37:$B$41,0)=Counta($B$37:$B$41),AW42/AW37,AW38/AW37),"--") -> 0.52380952 | AY55: =iferror(if(match($B$37,$B$37:$B$41,0)=Counta($B$37:$B$41),AY42/AY37,AY38/AY37),"--") -> -- | BA55: =iferror(if(match($B$37,$B$37:$B$41,0)=Counta($B$37:$B$41),BA42/BA37,BA38/BA37),"--") -> 0 | BC55: =iferror(if(match($B$37,$B$37:$B$41,0)=Counta($B$37:$B$41),BC42/BC37,BC38/BC37),"--") -> 0.25 | BE55: =iferror(if(match($B$37,$B$37:$B$41,0)=Counta($B$37:$B$41),BE42/BE37,BE38/BE37),"--") -> -- | BG55: =iferror(if(match($B$37,$B$37:$B$41,0)=Counta($B$37:$B$41),BG42/BG37,BG38/BG37),"--") -> -- | BI55: =iferror(if(match($B$37,$B$37:$B$41,0)=Counta($B$37:$B$41),BI42/BI37,BI38/BI37),"--") -> -- | BK55: =iferror(if(match($B$37,$B$37:$B$41,0)=Counta($B$37:$B$41),BK42/BK37,BK38/BK37),"--") -> -- | BM55: =iferror(if(match($B$37,$B$37:$B$41,0)=Counta($B$37:$B$41),BM42/BM37,BM38/BM37),"--") -> 0.45833333 | BO55: =iferror(if(match($B$37,$B$37:$B$41,0)=Counta($B$37:$B$41),BO42/BO37,BO38/BO37),"--") -> 0.6984127
B56: =iferror(if(match(B38,$B$37:$B$41,0)=Counta($B$37:$B$41),LEFT(B38,LEN(B38)-1)&" > "&LEFT($B$42,LEN($B$42)-1),LEFT(B38,LEN(B38)-1)&" > "&LEFT(B39,LEN(B39)-1)),"--") -> Intro Held > Strat Call Held | E56: =iferror(if(match(B38,$B$37:$B$41,0)=Counta($B$37:$B$41),$E$42/E38,E39/E38),"--") -> 0.41823056 | G56: =iferror(if(match($B$38,$B$37:$B$41,0)=Counta($B$37:$B$41),G42/G38,G39/G38),"--") -> 0.33333333 | I56: =iferror(if(match($B$38,$B$37:$B$41,0)=Counta($B$37:$B$41),I42/I38,I39/I38),"--") -> -- | K56: =iferror(if(match($B$38,$B$37:$B$41,0)=Counta($B$37:$B$41),K42/K38,K39/K38),"--") -> 0 | M56: =iferror(if(match($B$38,$B$37:$B$41,0)=Counta($B$37:$B$41),M42/M38,M39/M38),"--") -> -- | O56: =iferror(if(match($B$38,$B$37:$B$41,0)=Counta($B$37:$B$41),O42/O38,O39/O38),"--") -> -- | Q56: =iferror(if(match($B$38,$B$37:$B$41,0)=Counta($B$37:$B$41),Q42/Q38,Q39/Q38),"--") -> -- | S56: =iferror(if(match($B$38,$B$37:$B$41,0)=Counta($B$37:$B$41),S42/S38,S39/S38),"--") -> 0 | U56: =iferror(if(match($B$38,$B$37:$B$41,0)=Counta($B$37:$B$41),U42/U38,U39/U38),"--") -> 1 | W56: =iferror(if(match($B$38,$B$37:$B$41,0)=Counta($B$37:$B$41),W42/W38,W39/W38),"--") -> 0 | Y56: =iferror(if(match($B$38,$B$37:$B$41,0)=Counta($B$37:$B$41),Y42/Y38,Y39/Y38),"--") -> -- | AA56: =iferror(if(match($B$38,$B$37:$B$41,0)=Counta($B$37:$B$41),AA42/AA38,AA39/AA38),"--") -> 0.25 | AC56: =iferror(if(match($B$38,$B$37:$B$41,0)=Counta($B$37:$B$41),AC42/AC38,AC39/AC38),"--") -> -- | AE56: =iferror(if(match($B$38,$B$37:$B$41,0)=Counta($B$37:$B$41),AE42/AE38,AE39/AE38),"--") -> -- | AG56: =iferror(if(match($B$38,$B$37:$B$41,0)=Counta($B$37:$B$41),AG42/AG38,AG39/AG38),"--") -> -- | AI56: =iferror(if(match($B$38,$B$37:$B$41,0)=Counta($B$37:$B$41),AI42/AI38,AI39/AI38),"--") -> -- | AK56: =iferror(if(match($B$38,$B$37:$B$41,0)=Counta($B$37:$B$41),AK42/AK38,AK39/AK38),"--") -> -- | AM56: =iferror(if(match($B$38,$B$37:$B$41,0)=Counta($B$37:$B$41),AM42/AM38,AM39/AM38),"--") -> 0.29069767 | AO56: =iferror(if(match($B$38,$B$37:$B$41,0)=Counta($B$37:$B$41),AO42/AO38,AO39/AO38),"--") -> 0.38888889 | AQ56: =iferror(if(match($B$38,$B$37:$B$41,0)=Counta($B$37:$B$41),AQ42/AQ38,AQ39/AQ38),"--") -> 0.17808219 | AS56: =iferror(if(match($B$38,$B$37:$B$41,0)=Counta($B$37:$B$41),AS42/AS38,AS39/AS38),"--") -> 0.75 | AU56: =iferror(if(match($B$38,$B$37:$B$41,0)=Counta($B$37:$B$41),AU42/AU38,AU39/AU38),"--") -> -- | AW56: =iferror(if(match($B$38,$B$37:$B$41,0)=Counta($B$37:$B$41),AW42/AW38,AW39/AW38),"--") -> 0.22727273 | AY56: =iferror(if(match($B$38,$B$37:$B$41,0)=Counta($B$37:$B$41),AY42/AY38,AY39/AY38),"--") -> -- | BA56: =iferror(if(match($B$38,$B$37:$B$41,0)=Counta($B$37:$B$41),BA42/BA38,BA39/BA38),"--") -> -- | BC56: =iferror(if(match($B$38,$B$37:$B$41,0)=Counta($B$37:$B$41),BC42/BC38,BC39/BC38),"--") -> 0.66666667 | BE56: =iferror(if(match($B$38,$B$37:$B$41,0)=Counta($B$37:$B$41),BE42/BE38,BE39/BE38),"--") -> -- | BG56: =iferror(if(match($B$38,$B$37:$B$41,0)=Counta($B$37:$B$41),BG42/BG38,BG39/BG38),"--") -> -- | BI56: =iferror(if(match($B$38,$B$37:$B$41,0)=Counta($B$37:$B$41),BI42/BI38,BI39/BI38),"--") -> -- | BK56: =iferror(if(match($B$38,$B$37:$B$41,0)=Counta($B$37:$B$41),BK42/BK38,BK39/BK38),"--") -> -- | BM56: =iferror(if(match($B$38,$B$37:$B$41,0)=Counta($B$37:$B$41),BM42/BM38,BM39/BM38),"--") -> 0.68181818 | BO56: =iferror(if(match($B$38,$B$37:$B$41,0)=Counta($B$37:$B$41),BO42/BO38,BO39/BO38),"--") -> 0.78409091
B57: =iferror(if(match(B39,$B$37:$B$41,0)=Counta($B$37:$B$41),LEFT(B39,LEN(B39)-1)&" > "&LEFT($B$42,LEN($B$42)-1),LEFT(B39,LEN(B39)-1)&" > "&LEFT(B40,LEN(B40)-1)),"--") -> Strat Call Held > Proposal | E57: =iferror(if(match(B39,$B$37:$B$41,0)=Counta($B$37:$B$41),$E$42/E39,E40/E39),"--") -> 0.66666667 | G57: =iferror(if(match($B$39,$B$37:$B$41,0)=Counta($B$37:$B$41),G42/G39,G40/G39),"--") -> 2 | I57: =iferror(if(match($B$39,$B$37:$B$41,0)=Counta($B$37:$B$41),I42/I39,I40/I39),"--") -> -- | K57: =iferror(if(match($B$39,$B$37:$B$41,0)=Counta($B$37:$B$41),K42/K39,K40/K39),"--") -> -- | M57: =iferror(if(match($B$39,$B$37:$B$41,0)=Counta($B$37:$B$41),M42/M39,M40/M39),"--") -> -- | O57: =iferror(if(match($B$39,$B$37:$B$41,0)=Counta($B$37:$B$41),O42/O39,O40/O39),"--") -> -- | Q57: =iferror(if(match($B$39,$B$37:$B$41,0)=Counta($B$37:$B$41),Q42/Q39,Q40/Q39),"--") -> -- | S57: =iferror(if(match($B$39,$B$37:$B$41,0)=Counta($B$37:$B$41),S42/S39,S40/S39),"--") -> -- | U57: =iferror(if(match($B$39,$B$37:$B$41,0)=Counta($B$37:$B$41),U42/U39,U40/U39),"--") -> 0.33333333 | W57: =iferror(if(match($B$39,$B$37:$B$41,0)=Counta($B$37:$B$41),W42/W39,W40/W39),"--") -> -- | Y57: =iferror(if(match($B$39,$B$37:$B$41,0)=Counta($B$37:$B$41),Y42/Y39,Y40/Y39),"--") -> -- | AA57: =iferror(if(match($B$39,$B$37:$B$41,0)=Counta($B$37:$B$41),AA42/AA39,AA40/AA39),"--") -> 2 | AC57: =iferror(if(match($B$39,$B$37:$B$41,0)=Counta($B$37:$B$41),AC42/AC39,AC40/AC39),"--") -> -- | AE57: =iferror(if(match($B$39,$B$37:$B$41,0)=Counta($B$37:$B$41),AE42/AE39,AE40/AE39),"--") -> -- | AG57: =iferror(if(match($B$39,$B$37:$B$41,0)=Counta($B$37:$B$41),AG42/AG39,AG40/AG39),"--") -> -- | AI57: =iferror(if(match($B$39,$B$37:$B$41,0)=Counta($B$37:$B$41),AI42/AI39,AI40/AI39),"--") -> -- | AK57: =iferror(if(match($B$39,$B$37:$B$41,0)=Counta($B$37:$B$41),AK42/AK39,AK40/AK39),"--") -> -- | AM57: =iferror(if(match($B$39,$B$37:$B$41,0)=Counta($B$37:$B$41),AM42/AM39,AM40/AM39),"--") -> 0.36 | AO57: =iferror(if(match($B$39,$B$37:$B$41,0)=Counta($B$37:$B$41),AO42/AO39,AO40/AO39),"--") -> 0.14285714 | AQ57: =iferror(if(match($B$39,$B$37:$B$41,0)=Counta($B$37:$B$41),AQ42/AQ39,AQ40/AQ39),"--") -> 1 | AS57: =iferror(if(match($B$39,$B$37:$B$41,0)=Counta($B$37:$B$41),AS42/AS39,AS40/AS39),"--") -> 0.33333333 | AU57: =iferror(if(match($B$39,$B$37:$B$41,0)=Counta($B$37:$B$41),AU42/AU39,AU40/AU39),"--") -> -- | AW57: =iferror(if(match($B$39,$B$37:$B$41,0)=Counta($B$37:$B$41),AW42/AW39,AW40/AW39),"--") -> 0.9 | AY57: =iferror(if(match($B$39,$B$37:$B$41,0)=Counta($B$37:$B$41),AY42/AY39,AY40/AY39),"--") -> -- | BA57: =iferror(if(match($B$39,$B$37:$B$41,0)=Counta($B$37:$B$41),BA42/BA39,BA40/BA39),"--") -> -- | BC57: =iferror(if(match($B$39,$B$37:$B$41,0)=Counta($B$37:$B$41),BC42/BC39,BC40/BC39),"--") -> 0 | BE57: =iferror(if(match($B$39,$B$37:$B$41,0)=Counta($B$37:$B$41),BE42/BE39,BE40/BE39),"--") -> -- | BG57: =iferror(if(match($B$39,$B$37:$B$41,0)=Counta($B$37:$B$41),BG42/BG39,BG40/BG39),"--") -> -- | BI57: =iferror(if(match($B$39,$B$37:$B$41,0)=Counta($B$37:$B$41),BI42/BI39,BI40/BI39),"--") -> -- | BK57: =iferror(if(match($B$39,$B$37:$B$41,0)=Counta($B$37:$B$41),BK42/BK39,BK40/BK39),"--") -> -- | BM57: =iferror(if(match($B$39,$B$37:$B$41,0)=Counta($B$37:$B$41),BM42/BM39,BM40/BM39),"--") -> 0 | BO57: =iferror(if(match($B$39,$B$37:$B$41,0)=Counta($B$37:$B$41),BO42/BO39,BO40/BO39),"--") -> 0.89855072
B58: =iferror(if(match(B40,$B$37:$B$41,0)=Counta($B$37:$B$41),LEFT(B40,LEN(B40)-1)&" > "&LEFT($B$42,LEN($B$42)-1),LEFT(B40,LEN(B40)-1)&" > "&LEFT(B41,LEN(B41)-1)),"--") -> Proposal > Customer | E58: =iferror(if(match(B40,$B$37:$B$41,0)=Counta($B$37:$B$41),$E$42/E40,E41/E40),"--") -> 0.22115385 | G58: =iferror(if(match($B$40,$B$37:$B$41,0)=Counta($B$37:$B$41),G42/G40,G41/G40),"--") -> 0 | I58: =iferror(if(match($B$40,$B$37:$B$41,0)=Counta($B$37:$B$41),I42/I40,I41/I40),"--") -> -- | K58: =iferror(if(match($B$40,$B$37:$B$41,0)=Counta($B$37:$B$41),K42/K40,K41/K40),"--") -> -- | M58: =iferror(if(match($B$40,$B$37:$B$41,0)=Counta($B$37:$B$41),M42/M40,M41/M40),"--") -> -- | O58: =iferror(if(match($B$40,$B$37:$B$41,0)=Counta($B$37:$B$41),O42/O40,O41/O40),"--") -> -- | Q58: =iferror(if(match($B$40,$B$37:$B$41,0)=Counta($B$37:$B$41),Q42/Q40,Q41/Q40),"--") -> -- | S58: =iferror(if(match($B$40,$B$37:$B$41,0)=Counta($B$37:$B$41),S42/S40,S41/S40),"--") -> -- | U58: =iferror(if(match($B$40,$B$37:$B$41,0)=Counta($B$37:$B$41),U42/U40,U41/U40),"--") -> 0 | W58: =iferror(if(match($B$40,$B$37:$B$41,0)=Counta($B$37:$B$41),W42/W40,W41/W40),"--") -> -- | Y58: =iferror(if(match($B$40,$B$37:$B$41,0)=Counta($B$37:$B$41),Y42/Y40,Y41/Y40),"--") -> -- | AA58: =iferror(if(match($B$40,$B$37:$B$41,0)=Counta($B$37:$B$41),AA42/AA40,AA41/AA40),"--") -> 0.5 | AC58: =iferror(if(match($B$40,$B$37:$B$41,0)=Counta($B$37:$B$41),AC42/AC40,AC41/AC40),"--") -> -- | AE58: =iferror(if(match($B$40,$B$37:$B$41,0)=Counta($B$37:$B$41),AE42/AE40,AE41/AE40),"--") -> -- | AG58: =iferror(if(match($B$40,$B$37:$B$41,0)=Counta($B$37:$B$41),AG42/AG40,AG41/AG40),"--") -> -- | AI58: =iferror(if(match($B$40,$B$37:$B$41,0)=Counta($B$37:$B$41),AI42/AI40,AI41/AI40),"--") -> -- | AK58: =iferror(if(match($B$40,$B$37:$B$41,0)=Counta($B$37:$B$41),AK42/AK40,AK41/AK40),"--") -> -- | AM58: =iferror(if(match($B$40,$B$37:$B$41,0)=Counta($B$37:$B$41),AM42/AM40,AM41/AM40),"--") -> 0.66666667 | AO58: =iferror(if(match($B$40,$B$37:$B$41,0)=Counta($B$37:$B$41),AO42/AO40,AO41/AO40),"--") -> 0 | AQ58: =iferror(if(match($B$40,$B$37:$B$41,0)=Counta($B$37:$B$41),AQ42/AQ40,AQ41/AQ40),"--") -> 0 | AS58: =iferror(if(match($B$40,$B$37:$B$41,0)=Counta($B$37:$B$41),AS42/AS40,AS41/AS40),"--") -> 1 | AU58: =iferror(if(match($B$40,$B$37:$B$41,0)=Counta($B$37:$B$41),AU42/AU40,AU41/AU40),"--") -> -- | AW58: =iferror(if(match($B$40,$B$37:$B$41,0)=Counta($B$37:$B$41),AW42/AW40,AW41/AW40),"--") -> 0 | AY58: =iferror(if(match($B$40,$B$37:$B$41,0)=Counta($B$37:$B$41),AY42/AY40,AY41/AY40),"--") -> -- | BA58: =iferror(if(match($B$40,$B$37:$B$41,0)=Counta($B$37:$B$41),BA42/BA40,BA41/BA40),"--") -> -- | BC58: =iferror(if(match($B$40,$B$37:$B$41,0)=Counta($B$37:$B$41),BC42/BC40,BC41/BC40),"--") -> -- | BE58: =iferror(if(match($B$40,$B$37:$B$41,0)=Counta($B$37:$B$41),BE42/BE40,BE41/BE40),"--") -> -- | BG58: =iferror(if(match($B$40,$B$37:$B$41,0)=Counta($B$37:$B$41),BG42/BG40,BG41/BG40),"--") -> -- | BI58: =iferror(if(match($B$40,$B$37:$B$41,0)=Counta($B$37:$B$41),BI42/BI40,BI41/BI40),"--") -> -- | BK58: =iferror(if(match($B$40,$B$37:$B$41,0)=Counta($B$37:$B$41),BK42/BK40,BK41/BK40),"--") -> -- | BM58: =iferror(if(match($B$40,$B$37:$B$41,0)=Counta($B$37:$B$41),BM42/BM40,BM41/BM40),"--") -> -- | BO58: =iferror(if(match($B$40,$B$37:$B$41,0)=Counta($B$37:$B$41),BO42/BO40,BO41/BO40),"--") -> 0.20967742
B59: =iferror(if(match(B41,$B$37:$B$41,0)=Counta($B$37:$B$41),LEFT(B41,LEN(B41)-1)&" > "&LEFT($B$42,LEN($B$42)-1),LEFT(B41,LEN(B41)-1)&" > "&LEFT(B42,LEN(B42)-1)),"--") -> -- | E59: =iferror(if(match(B41,$B$37:$B$41,0)=Counta($B$37:$B$41),$E$42/E41,E42/E41),"--") -> -- | G59: =iferror(if(match($B$41,$B$37:$B$41,0)=Counta($B$37:$B$41),G42/G41,G42/G41),"--") -> -- | I59: =iferror(if(match($B$41,$B$37:$B$41,0)=Counta($B$37:$B$41),I42/I41,I42/I41),"--") -> -- | K59: =iferror(if(match($B$41,$B$37:$B$41,0)=Counta($B$37:$B$41),K42/K41,K42/K41),"--") -> -- | M59: =iferror(if(match($B$41,$B$37:$B$41,0)=Counta($B$37:$B$41),M42/M41,M42/M41),"--") -> -- | O59: =iferror(if(match($B$41,$B$37:$B$41,0)=Counta($B$37:$B$41),O42/O41,O42/O41),"--") -> -- | Q59: =iferror(if(match($B$41,$B$37:$B$41,0)=Counta($B$37:$B$41),Q42/Q41,Q42/Q41),"--") -> -- | S59: =iferror(if(match($B$41,$B$37:$B$41,0)=Counta($B$37:$B$41),S42/S41,S42/S41),"--") -> -- | U59: =iferror(if(match($B$41,$B$37:$B$41,0)=Counta($B$37:$B$41),U42/U41,U42/U41),"--") -> -- | W59: =iferror(if(match($B$41,$B$37:$B$41,0)=Counta($B$37:$B$41),W42/W41,W42/W41),"--") -> -- | Y59: =iferror(if(match($B$41,$B$37:$B$41,0)=Counta($B$37:$B$41),Y42/Y41,Y42/Y41),"--") -> -- | AA59: =iferror(if(match($B$41,$B$37:$B$41,0)=Counta($B$37:$B$41),AA42/AA41,AA42/AA41),"--") -> -- | AC59: =iferror(if(match($B$41,$B$37:$B$41,0)=Counta($B$37:$B$41),AC42/AC41,AC42/AC41),"--") -> -- | AE59: =iferror(if(match($B$41,$B$37:$B$41,0)=Counta($B$37:$B$41),AE42/AE41,AE42/AE41),"--") -> -- | AG59: =iferror(if(match($B$41,$B$37:$B$41,0)=Counta($B$37:$B$41),AG42/AG41,AG42/AG41),"--") -> -- | AI59: =iferror(if(match($B$41,$B$37:$B$41,0)=Counta($B$37:$B$41),AI42/AI41,AI42/AI41),"--") -> -- | AK59: =iferror(if(match($B$41,$B$37:$B$41,0)=Counta($B$37:$B$41),AK42/AK41,AK42/AK41),"--") -> -- | AM59: =iferror(if(match($B$41,$B$37:$B$41,0)=Counta($B$37:$B$41),AM42/AM41,AM42/AM41),"--") -> -- | AO59: =iferror(if(match($B$41,$B$37:$B$41,0)=Counta($B$37:$B$41),AO42/AO41,AO42/AO41),"--") -> -- | AQ59: =iferror(if(match($B$41,$B$37:$B$41,0)=Counta($B$37:$B$41),AQ42/AQ41,AQ42/AQ41),"--") -> -- | AS59: =iferror(if(match($B$41,$B$37:$B$41,0)=Counta($B$37:$B$41),AS42/AS41,AS42/AS41),"--") -> -- | AU59: =iferror(if(match($B$41,$B$37:$B$41,0)=Counta($B$37:$B$41),AU42/AU41,AU42/AU41),"--") -> -- | AW59: =iferror(if(match($B$41,$B$37:$B$41,0)=Counta($B$37:$B$41),AW42/AW41,AW42/AW41),"--") -> -- | AY59: =iferror(if(match($B$41,$B$37:$B$41,0)=Counta($B$37:$B$41),AY42/AY41,AY42/AY41),"--") -> -- | BA59: =iferror(if(match($B$41,$B$37:$B$41,0)=Counta($B$37:$B$41),BA42/BA41,BA42/BA41),"--") -> -- | BC59: =iferror(if(match($B$41,$B$37:$B$41,0)=Counta($B$37:$B$41),BC42/BC41,BC42/BC41),"--") -> -- | BE59: =iferror(if(match($B$41,$B$37:$B$41,0)=Counta($B$37:$B$41),BE42/BE41,BE42/BE41),"--") -> -- | BG59: =iferror(if(match($B$41,$B$37:$B$41,0)=Counta($B$37:$B$41),BG42/BG41,BG42/BG41),"--") -> -- | BI59: =iferror(if(match($B$41,$B$37:$B$41,0)=Counta($B$37:$B$41),BI42/BI41,BI42/BI41),"--") -> -- | BK59: =iferror(if(match($B$41,$B$37:$B$41,0)=Counta($B$37:$B$41),BK42/BK41,BK42/BK41),"--") -> -- | BM59: =iferror(if(match($B$41,$B$37:$B$41,0)=Counta($B$37:$B$41),BM42/BM41,BM42/BM41),"--") -> -- | BO59: =iferror(if(match($B$41,$B$37:$B$41,0)=Counta($B$37:$B$41),BO42/BO41,BO42/BO41),"--") -> --
B60: =LEFT(B37,LEN(B37)-1)&" > "&LEFT(B42,LEN(B42)-1) -> Form Fill > Customer | E60: =iferror(E42/E37,"--") -> 0.033381713 | G60: =iferror(if(isblank(G42),"--",G42/G37),"--") -> 0 | I60: =iferror(if(isblank(I42),"--",I42/I37),"--") -> 0 | K60: =iferror(if(isblank(K42),"--",K42/K37),"--") -> 0 | M60: =iferror(if(isblank(M42),"--",M42/M37),"--") -> 0 | O60: =iferror(if(isblank(O42),"--",O42/O37),"--") -> -- | Q60: =iferror(if(isblank(Q42),"--",Q42/Q37),"--") -> 0 | S60: =iferror(if(isblank(S42),"--",S42/S37),"--") -> 0 | U60: =iferror(if(isblank(U42),"--",U42/U37),"--") -> 0 | W60: =iferror(if(isblank(W42),"--",W42/W37),"--") -> 0 | Y60: =iferror(if(isblank(Y42),"--",Y42/Y37),"--") -> -- | AA60: =iferror(if(isblank(AA42),"--",AA42/AA37),"--") -> 0.11111111 | AC60: =iferror(if(isblank(AC42),"--",AC42/AC37),"--") -> -- | AE60: =iferror(if(isblank(AE42),"--",AE42/AE37),"--") -> -- | AG60: =iferror(if(isblank(AG42),"--",AG42/AG37),"--") -> -- | AI60: =iferror(if(isblank(AI42),"--",AI42/AI37),"--") -> 0 | AK60: =iferror(if(isblank(AK42),"--",AK42/AK37),"--") -> -- | AM60: =iferror(if(isblank(AM42),"--",AM42/AM37),"--") -> 0.036585366 | AO60: =iferror(if(isblank(AO42),"--",AO42/AO37),"--") -> 0 | AQ60: =iferror(if(isblank(AQ42),"--",AQ42/AQ37),"--") -> 0 | AS60: =iferror(if(isblank(AS42),"--",AS42/AS37),"--") -> 0.073170732 | AU60: =iferror(if(isblank(AU42),"--",AU42/AU37),"--") -> -- | AW60: =iferror(if(isblank(AW42),"--",AW42/AW37),"--") -> 0 | AY60: =iferror(if(isblank(AY42),"--",AY42/AY37),"--") -> -- | BA60: =iferror(if(isblank(BA42),"--",BA42/BA37),"--") -> 0 | BC60: =iferror(if(isblank(BC42),"--",BC42/BC37),"--") -> 0 | BE60: =iferror(if(isblank(BE42),"--",BE42/BE37),"--") -> -- | BG60: =iferror(if(isblank(BG42),"--",BG42/BG37),"--") -> -- | BI60: =iferror(if(isblank(BI42),"--",BI42/BI37),"--") -> -- | BK60: =iferror(if(isblank(BK42),"--",BK42/BK37),"--") -> -- | BM60: =iferror(if(isblank(BM42),"--",BM42/BM37),"--") -> 0 | BO60: =iferror(if(isblank(BO42),"--",BO42/BO37),"--") -> 0.1031746
F65: =IFERROR(__xludf.DUMMYFUNCTION("FILTER(B37:B42,NOT(ISBLANK(B37:B42)))"),"Form Fills") -> Form Fills | G65: =if(H65="","",(max($H$65:$H$70)-H65)/2) -> 0 | H65: =ifna(VLOOKUP(F65,$B$37:$F$42,4,false),"") -> 689 | I65: =IFERROR(__xludf.DUMMYFUNCTION("FILTER(B55:B59,NOT(B55:B59=""--""))"),"Form Fill > Intro Held") -> Form Fill > Intro Held | J65: =ifna(VLOOKUP(I65,$B$55:$F$59,4,false),"") -> 0.5413643
F66: =IFERROR(__xludf.DUMMYFUNCTION("""COMPUTED_VALUE"""),"Intro Held ") -> Intro Held | G66: =if(H66="","",(max($H$65:$H$70)-H66)/2) -> 158 | H66: =ifna(VLOOKUP(F66,$B$37:$F$42,4,false),"") -> 373 | I66: =IFERROR(__xludf.DUMMYFUNCTION("""COMPUTED_VALUE"""),"Intro Held > Strat Call Held") -> Intro Held > Strat Call Held | J66: =ifna(VLOOKUP(I66,$B$55:$F$59,4,false),"") -> 0.41823056
F67: =IFERROR(__xludf.DUMMYFUNCTION("""COMPUTED_VALUE"""),"Strat Call Held ") -> Strat Call Held | G67: =if(H67="","",(max($H$65:$H$70)-H67)/2) -> 266.5 | H67: =ifna(VLOOKUP(F67,$B$37:$F$42,4,false),"") -> 156 | I67: =IFERROR(__xludf.DUMMYFUNCTION("""COMPUTED_VALUE"""),"Strat Call Held > Proposal") -> Strat Call Held > Proposal | J67: =ifna(VLOOKUP(I67,$B$55:$F$59,4,false),"") -> 0.66666667
F68: =IFERROR(__xludf.DUMMYFUNCTION("""COMPUTED_VALUE"""),"Proposals") -> Proposals | G68: =if(H68="","",(max($H$65:$H$70)-H68)/2) -> 292.5 | H68: =ifna(VLOOKUP(F68,$B$37:$F$42,4,false),"") -> 104 | I68: =IFERROR(__xludf.DUMMYFUNCTION("""COMPUTED_VALUE"""),"Proposal > Customer") -> Proposal > Customer | J68: =ifna(VLOOKUP(I68,$B$55:$F$59,4,false),"") -> 0.22115385
F69: =IFERROR(__xludf.DUMMYFUNCTION("""COMPUTED_VALUE"""),"Customers") -> Customers | G69: =if(H69="","",(max($H$65:$H$70)-H69)/2) -> 333 | H69: =ifna(VLOOKUP(F69,$B$37:$F$42,4,false),"") -> 23 | J69: =ifna(VLOOKUP(I69,$B$55:$F$59,4,false),"")
G70: =if(H70="","",(max($H$65:$H$70)-H70)/2) | H70: =ifna(VLOOKUP(F70,$B$37:$F$42,4,false),"") | J70: =ifna(VLOOKUP(I70,$B$55:$F$59,4,false),"")

Sheet Removing spend from underperfor
B2: GET STARTED | BF2: NOTE
B3: Enter the values needed for calculating LTV in cells T14:T17, then customize your channels and funnel stages in the 'Current Quarter Actuals' table below. | BF3: Only edit highlighted cells.
BF4: Try not to alter cells that contain a formula.
B5: As you enter data in the 'Current Quarter Actuals' tab, this sheet will automatically update to show a summary of the quarter.
B10: Current Quarter Summary
T12: Lifetime Value (LTV)
T13: Gross Margin (%) | X13: 0.6
D14: =IFERROR(__xludf.DUMMYFUNCTION("iferror(SPARKLINE(C22,{""charttype"",""column"";""ymin"", 0; ""ymax"",MAX(C22:H22);""firstcolor"",""#304458""}),"""")"),"") | F14: =IFERROR(__xludf.DUMMYFUNCTION("iferror(SPARKLINE(F22,{""charttype"",""column"";""ymin"", 0; ""ymax"",MAX(C22:H22);""firstcolor"",""#f46524""}),"""")"),"") | T14: Lifespan of Customer (months) | X14: 12
T15: Monthly Avg. Order Value | X15: 15293 | Z15: =X15*12 -> 183516
T16: Channel-level AOV's? | X16: No
T17: Lifetime Value (LTV) | X17: =if(X16="No",if(isblank(X13),"Enter GM%",if(isblank(X14),"Enter Lifespan",if(ISBLANK(X15),"Enter AOV",X13*X14*X15))),"See Below") -> 110109.6
M20: =F62 -> Form Fills | N20: =H62 -> 815 | S20: =IFERROR(__xludf.DUMMYFUNCTION("iferror(SPARKLINE(G62:H62,{""charttype"",""bar"";""max"",MAX($H$62:$H$67);""color1"",""#ebedef"";""color2"",""#073763""}),"""")"),"")
C21: Total Spend | F21: Total Est. Bookings | M21: =F63 -> Intro Held | N21: =H63 -> 430 | S21: =IFERROR(__xludf.DUMMYFUNCTION("iferror(SPARKLINE(G63:H63,{""charttype"",""bar"";""max"",MAX($H$62:$H$67);""color1"",""#ebedef"";""color2"",""#0b5394""}),"""")"),"") | W21: =iferror(if(J62="","","🔽 "&(ROUND(J62,2)*100)&"%"),"--") -> 🔽 53% | X21: =if(I62="","",I62) -> Form Fill > Intro Held
C22: =E35 -> 234963.85 | F22: =E44 -> 2532520.8 | M22: =F64 -> Strat Call Held | N22: =H64 -> 173 | S22: =IFERROR(__xludf.DUMMYFUNCTION("iferror(SPARKLINE(G64:H64,{""charttype"",""bar"";""max"",MAX(H62:H67);""color1"",""#ebedef"";""color2"",""#3d85c6""}),"""")"),"") | W22: =iferror(if(J63="","","🔽 "&(ROUND(J63,2)*100)&"%"),"--") -> 🔽 40% | X22: =if(I63="","",I63) -> Intro Held > Strat Call Held
M23: =F65 -> Proposals | N23: =H65 -> 122 | S23: =IFERROR(__xludf.DUMMYFUNCTION("iferror(SPARKLINE(G65:H65,{""charttype"",""bar"";""max"",MAX($H$62:$H$67);""color1"",""#ebedef"";""color2"",""#6fa8dc""}),"""")"),"") | W23: =iferror(if(J64="","","🔽 "&(ROUND(J64,2)*100)&"%"),"--") -> 🔽 71% | X23: =if(I64="","",I64) -> Strat Call Held > Proposal | AD23: 44805
M24: =F66 -> Customers | N24: =H66 -> 23 | S24: =IFERROR(__xludf.DUMMYFUNCTION("iferror(SPARKLINE(G66:H66,{""charttype"",""bar"";""max"",MAX($H$62:$H$67);""color1"",""#ebedef"";""color2"",""#9fc5e8""}),"""")"),"") | W24: =iferror(if(J65="","","🔽 "&(ROUND(J65,2)*100)&"%"),"--") -> 🔽 19% | X24: =if(I65="","",I65) -> Proposal > Customer | AD24: 44876
C25: LTV:CAC Ratio | F25: =E31 -> 10.78 | M25: =F67 | N25: =H67 | S25: {=iferror(SPARKLINE(G67:H67,{"charttype","bar";"max",MAX($H$62:$H$67);"color1","#ebedef";"color2","#cfe2f3"}),"")} | W25: =iferror(if(J66="","","🔽 "&(ROUND(J66,2)*100)&"%"),"--") | X25: =if(I66="","",I66) | AD25: =days(AD24,AD23) -> 71
C26: Net Return | F26: =E45 -> 2369381.2 | AD26: 44926
AD27: =days(AD26,AD23) -> 121
B28: Current Quarter Actuals
I29: 25000 | AM29: 35000 | AO29: 5000 | AQ29: 30000 | AS29: 60000 | AW29: 40000
E30: Total | G30: Google - Brand | I30: Google - Non-Brand: Demand Gen | K30: Google - Non-Brand: Marketing | M30: Google - Non-Brand: MOPs | O30: Google - Non-Brand: Paid Media | Q30: Google - Non-Brand: Social | S30: Google - Non-Brand: Creative | U30: Google - Non-Brand: Performance Marketing | W30: Google - Non-Brand: SEO | Y30: Google - Non-Brand: Strategy | AA30: Google - Non-Brand: Video | AC30: Google - YouTube | AE30: Google - Display | AG30: Google - Non-Brand: Events Support | AI30: Google - Non-Brand: RLSA | AK30: LinkedIn - Brand Ads | AM30: LinkedIn - Convo Ads GC | AO30: LinkedIn - Line Specific GC | AQ30: LinkedIn - Strategy GC | AS30: LinkedIn - SPC GC | AU30: Facebook/IG - Brand Ads | AW30: Facebook - SPC GC | AY30: Instagram - SPC GC | BA30: StackAdapt | BC30: Clutch.io | BE30: Manifest | BG30: Twitter - Brand | BI30: Organic | BK30: Non-Paid Media
B31: LTV:CAC Ratio | E31: =if(E35="--","--",if(istext(E43),"No LTV",if(or(isblank(E41),E41=0),0,Round(E43/E51,2)))) -> 10.78 | G31: =if(isblank(G35),"--",if(istext(G43),"No LTV",if(or(isblank(G41),G41=0),0,Round(G43/G51,2)))) -> 0 | I31: =if(isblank(I35),"--",if(istext(I43),"No LTV",if(or(isblank(I41),I41=0),0,Round(I43/I51,2)))) -> 0 | K31: =if(isblank(K35),"--",if(istext(K43),"No LTV",if(or(isblank(K41),K41=0),0,Round(K43/K51,2)))) -> 0 | M31: =if(isblank(M35),"--",if(istext(M43),"No LTV",if(or(isblank(M41),M41=0),0,Round(M43/M51,2)))) -> 0 | O31: =if(isblank(O35),"--",if(istext(O43),"No LTV",if(or(isblank(O41),O41=0),0,Round(O43/O51,2)))) -> 0 | Q31: =if(isblank(Q35),"--",if(istext(Q43),"No LTV",if(or(isblank(Q41),Q41=0),0,Round(Q43/Q51,2)))) -> 0 | S31: =if(isblank(S35),"--",if(istext(S43),"No LTV",if(or(isblank(S41),S41=0),0,Round(S43/S51,2)))) -> 0 | U31: =if(isblank(U35),"--",if(istext(U43),"No LTV",if(or(isblank(U41),U41=0),0,Round(U43/U51,2)))) -> 0 | W31: =if(isblank(W35),"--",if(istext(W43),"No LTV",if(or(isblank(W41),W41=0),0,Round(W43/W51,2)))) -> 0 | Y31: =if(isblank(Y35),"--",if(istext(Y43),"No LTV",if(or(isblank(Y41),Y41=0),0,Round(Y43/Y51,2)))) -> 0 | AA31: =if(isblank(AA35),"--",if(istext(AA43),"No LTV",if(or(isblank(AA41),AA41=0),0,Round(AA43/AA51,2)))) -> 15.12 | AC31: =if(isblank(AC35),"--",if(istext(AC43),"No LTV",if(or(isblank(AC41),AC41=0),0,Round(AC43/AC51,2)))) -> 0 | AE31: =if(isblank(AE35),"--",if(istext(AE43),"No LTV",if(or(isblank(AE41),AE41=0),0,Round(AE43/AE51,2)))) -> 0 | AG31: =if(isblank(AG35),"--",if(istext(AG43),"No LTV",if(or(isblank(AG41),AG41=0),0,Round(AG43/AG51,2)))) -> 0 | AI31: =if(isblank(AI35),"--",if(istext(AI43),"No LTV",if(or(isblank(AI41),AI41=0),0,Round(AI43/AI51,2)))) -> 0 | AK31: =if(isblank(AK35),"--",if(istext(AK43),"No LTV",if(or(isblank(AK41),AK41=0),0,Round(AK43/AK51,2)))) -> 0 | AM31: =if(isblank(AM35),"--",if(istext(AM43),"No LTV",if(or(isblank(AM41),AM41=0),0,Round(AM43/AM51,2)))) -> 7.08 | AO31: =if(isblank(AO35),"--",if(istext(AO43),"No LTV",if(or(isblank(AO41),AO41=0),0,Round(AO43/AO51,2)))) -> 0 | AQ31: =if(isblank(AQ35),"--",if(istext(AQ43),"No LTV",if(or(isblank(AQ41),AQ41=0),0,Round(AQ43/AQ51,2)))) -> 0 | AS31: =if(isblank(AS35),"--",if(istext(AS43),"No LTV",if(or(isblank(AS41),AS41=0),0,Round(AS43/AS51,2)))) -> 9.73 | AU31: =if(isblank(AU35),"--",if(istext(AU43),"No LTV",if(or(isblank(AU41),AU41=0),0,Round(AU43/AU51,2)))) -> 0 | AW31: =if(isblank(AW35),"--",if(istext(AW43),"No LTV",if(or(isblank(AW41),AW41=0),0,Round(AW43/AW51,2)))) -> 0 | BA31: =if(isblank(BA35),"--",if(istext(BA43),"No LTV",if(or(isblank(BA41),BA41=0),0,Round(BA43/BA51,2)))) -> 0 | BC31: =if(isblank(BC35),"--",if(istext(BC43),"No LTV",if(or(isblank(BC41),BC41=0),0,Round(BC43/BC51,2)))) -> 0 | BE31: =if(isblank(BE35),"--",if(istext(BE43),"No LTV",if(or(isblank(BE41),BE41=0),0,Round(BE43/BE51,2)))) -> 0 | BG31: =if(isblank(BG35),"--",if(istext(BG43),"No LTV",if(or(isblank(BG41),BG41=0),0,Round(BG43/BG51,2)))) -> 0 | BK31: =if(isblank(BK35),"--",if(istext(BK43),"No LTV",if(or(isblank(BK41),BK41=0),0,Round(BK43/BK51,2)))) -> 50.02
B32: Total Ad Spend | E32: =if(sum(G32:BL32)=0,"--",sum(G32:BL32)) -> 373616.6 | G32: 2155.39 | I32: 790.57 | K32: 11873.54 | M32: 10561.68 | O32: 190.35 | Q32: 2938.97 | S32: 9149.52 | U32: 19840.22 | W32: 8230.18 | Y32: 13142.76 | AA32: 7280.6 | AC32: 3545.79 | AE32: 0 | AG32: 795.72 | AI32: 2262.57 | AK32: 14064.04 | AM32: 76709.27 | AO32: 12423.41 | AQ32: 49727.22 | AS32: 33934.74 | AU32: 14028.09 | AW32: 34249.84 | AY32: 19218.96 | BA32: 16001.67 | BC32: =2650+2650 -> 5300 | BE32: =650+650 -> 1300 | BG32: 3901.5 | BI32: 0 | BK32: 0
B33: Resource Cost | E33: =if(sum(G33:BL33)=0,"--",sum(G33:BL33)) -> --
B34: Incentive Cost | E34: =if(sum(G34:BL34)=0,"--",sum(G34:BL34)) -> 47975 | AM34: 16600 | AW34: 2760 | BK34: 28615
B35: Total Spend | E35: =if(sum(G35:BL35)=0,"--",sum(G35:BL35)) -> 234963.85 | G35: =sum(G32:H34) -> 2155.39 | I35: =sum(I32:J34) -> 790.57 | K35: 0 | M35: 0 | O35: =sum(O32:P34) -> 190.35 | Q35: 0 | S35: 0 | U35: 0 | W35: 0 | Y35: 0 | AA35: =sum(AA32:AB34) -> 7280.6 | AC35: 0 | AE35: =sum(AE32:AF34) -> 0 | AG35: =sum(AG32:AH34) -> 795.72 | AI35: 0 | AK35: 0 | AM35: =sum(AM32:AN34) -> 93309.27 | AO35: =sum(AO32:AP34) -> 12423.41 | AQ35: 2000 | AS35: =sum(AS32:AT34) -> 33934.74 | AU35: 0 | AW35: 34249.84 | AY35: 19218.96 | BA35: 0 | BC35: 0 | BE35: 0 | BG35: 0 | BI35: =sum(BI32:BJ34) -> 0 | BK35: =sum(BK32:BL34) -> 28615
B36: Form Fills | E36: =if(isblank(B36),,if($E$35="--","--",sum(G36:BL36))) -> 815 | G36: 9 | I36: 1 | K36: 7 | M36: 4 | O36: 0 | Q36: 3 | S36: 5 | U36: 9 | W36: 9 | Y36: 2 | AA36: 12 | AC36: 0 | AE36: 0 | AG36: 0 | AI36: 1 | AK36: 0 | AM36: 197 | AO36: 58 | AQ36: 124 | AS36: 61 | AU36: 0 | AW36: 93 | BA36: 12 | BC36: 12 | BE36: 1 | BG36: 0 | BI36: 54 | BK36: 141
B37: Intro Held | E37: =if(isblank(B37),,if($E$35="--","--",sum(G37:BL37))) -> 430 | G37: 6 | I37: 0 | K37: 4 | M37: 0 | O37: 0 | Q37: 0 | S37: 2 | U37: 5 | W37: 8 | Y37: 1 | AA37: 6 | AC37: 0 | AE37: 0 | AG37: 0 | AI37: 0 | AK37: 0 | AM37: 97 | AO37: 19 | AQ37: 82 | AS37: 17 | AU37: 0 | AW37: 52 | BA37: 4 | BC37: 4 | BE37: 1 | BG37: 0 | BI37: 26 | BK37: 96
B38: Strat Call Held | E38: =if(isblank(B38),,if($E$35="--","--",sum(G38:BL38))) -> 173 | G38: 1 | I38: 0 | K38: 0 | M38: 0 | O38: 0 | Q38: 0 | S38: 0 | U38: 3 | W38: 0 | Y38: 0 | AA38: 1 | AC38: 0 | AE38: 0 | AG38: 0 | AI38: 0 | AK38: 0 | AM38: 29 | AO38: 8 | AQ38: 18 | AS38: 12 | AU38: 0 | AW38: 14 | BA38: 1 | BC38: 1 | BE38: 1 | BG38: 0 | BI38: 15 | BK38: 69
B39: Proposals | E39: =if(isblank(B39),,if($E$35="--","--",sum(G39:BL39))) -> 122 | G39: 3 | I39: 0 | K39: 0 | M39: 0 | O39: 0 | Q39: 0 | S39: 0 | U39: 1 | W39: 0 | Y39: 0 | AA39: 2 | AC39: 0 | AE39: 0 | AG39: 0 | AI39: 0 | AK39: 0 | AM39: 11 | AO39: 4 | AQ39: 13 | AS39: 7 | AU39: 0 | AW39: 9 | BA39: 1 | BC39: 1 | BE39: 0 | BG39: 0 | BI39: 1 | BK39: 69
E40: =if(isblank(B40),,if($E$35="--","--",sum(G40:BL40)))
B41: Customers | E41: =if(isblank(B41),,if($E$35="--","--",sum(G41:BL41))) -> 23 | G41: 0 | I41: 0 | K41: 0 | M41: 0 | O41: 0 | Q41: 0 | S41: 0 | U41: 0 | W41: 0 | Y41: 0 | AA41: 1 | AC41: 0 | AE41: 0 | AG41: 0 | AI41: 0 | AK41: 0 | AM41: 6 | AO41: 0 | AQ41: 0 | AS41: 3 | AU41: 0 | AW41: 0 | BA41: 0 | BC41: 0 | BE41: 0 | BG41: 0 | BI41: 0 | BK41: 13
B42: Average Order Value | E42: =if(X16="Yes",iferror(average(G42:BL42),""),X15) -> 15293
B43: Lifetime Value (LTV) | E43: =if(E35="--","--", if(X16="No",$X$17,iferror(average(G43:BL43),""))) -> 110109.6 | G43: =if($X$16="Yes",if(isblank(G35),"--",if(isblank($X$13),"Enter GM%",if(isblank($X$14),"Enter Lifespan",if(ISBLANK(G42),"Enter AOV",$X$13*$X$14*G42)))),if(isblank(G35),"--",$X$17)) -> 110109.6 | I43: =if($X$16="Yes",if(isblank(I35),"--",if(isblank($X$13),"Enter GM%",if(isblank($X$14),"Enter Lifespan",if(ISBLANK(I42),"Enter AOV",$X$13*$X$14*I42)))),if(isblank(I35),"--",$X$17)) -> 110109.6 | K43: =if($X$16="Yes",if(isblank(K35),"--",if(isblank($X$13),"Enter GM%",if(isblank($X$14),"Enter Lifespan",if(ISBLANK(K42),"Enter AOV",$X$13*$X$14*K42)))),if(isblank(K35),"--",$X$17)) -> 110109.6 | M43: =if($X$16="Yes",if(isblank(M35),"--",if(isblank($X$13),"Enter GM%",if(isblank($X$14),"Enter Lifespan",if(ISBLANK(M42),"Enter AOV",$X$13*$X$14*M42)))),if(isblank(M35),"--",$X$17)) -> 110109.6 | O43: =if($X$16="Yes",if(isblank(O35),"--",if(isblank($X$13),"Enter GM%",if(isblank($X$14),"Enter Lifespan",if(ISBLANK(O42),"Enter AOV",$X$13*$X$14*O42)))),if(isblank(O35),"--",$X$17)) -> 110109.6 | Q43: =if($X$16="Yes",if(isblank(Q35),"--",if(isblank($X$13),"Enter GM%",if(isblank($X$14),"Enter Lifespan",if(ISBLANK(Q42),"Enter AOV",$X$13*$X$14*Q42)))),if(isblank(Q35),"--",$X$17)) -> 110109.6 | S43: =if($X$16="Yes",if(isblank(S35),"--",if(isblank($X$13),"Enter GM%",if(isblank($X$14),"Enter Lifespan",if(ISBLANK(S42),"Enter AOV",$X$13*$X$14*S42)))),if(isblank(S35),"--",$X$17)) -> 110109.6 | U43: =if($X$16="Yes",if(isblank(U35),"--",if(isblank($X$13),"Enter GM%",if(isblank($X$14),"Enter Lifespan",if(ISBLANK(U42),"Enter AOV",$X$13*$X$14*U42)))),if(isblank(U35),"--",$X$17)) -> 110109.6 | W43: =if($X$16="Yes",if(isblank(W35),"--",if(isblank($X$13),"Enter GM%",if(isblank($X$14),"Enter Lifespan",if(ISBLANK(W42),"Enter AOV",$X$13*$X$14*W42)))),if(isblank(W35),"--",$X$17)) -> 110109.6 | Y43: =if($X$16="Yes",if(isblank(Y35),"--",if(isblank($X$13),"Enter GM%",if(isblank($X$14),"Enter Lifespan",if(ISBLANK(Y42),"Enter AOV",$X$13*$X$14*Y42)))),if(isblank(Y35),"--",$X$17)) -> 110109.6 | AA43: =if($X$16="Yes",if(isblank(AA35),"--",if(isblank($X$13),"Enter GM%",if(isblank($X$14),"Enter Lifespan",if(ISBLANK(AA42),"Enter AOV",$X$13*$X$14*AA42)))),if(isblank(AA35),"--",$X$17)) -> 110109.6 | AC43: =if($X$16="Yes",if(isblank(AC35),"--",if(isblank($X$13),"Enter GM%",if(isblank($X$14),"Enter Lifespan",if(ISBLANK(AC42),"Enter AOV",$X$13*$X$14*AC42)))),if(isblank(AC35),"--",$X$17)) -> 110109.6 | AE43: =if($X$16="Yes",if(isblank(AE35),"--",if(isblank($X$13),"Enter GM%",if(isblank($X$14),"Enter Lifespan",if(ISBLANK(AE42),"Enter AOV",$X$13*$X$14*AE42)))),if(isblank(AE35),"--",$X$17)) -> 110109.6 | AG43: =if($X$16="Yes",if(isblank(AG35),"--",if(isblank($X$13),"Enter GM%",if(isblank($X$14),"Enter Lifespan",if(ISBLANK(AG42),"Enter AOV",$X$13*$X$14*AG42)))),if(isblank(AG35),"--",$X$17)) -> 110109.6 | AI43: =if($X$16="Yes",if(isblank(AI35),"--",if(isblank($X$13),"Enter GM%",if(isblank($X$14),"Enter Lifespan",if(ISBLANK(AI42),"Enter AOV",$X$13*$X$14*AI42)))),if(isblank(AI35),"--",$X$17)) -> 110109.6 | AK43: =if($X$16="Yes",if(isblank(AK35),"--",if(isblank($X$13),"Enter GM%",if(isblank($X$14),"Enter Lifespan",if(ISBLANK(AK42),"Enter AOV",$X$13*$X$14*AK42)))),if(isblank(AK35),"--",$X$17)) -> 110109.6 | AM43: =if($X$16="Yes",if(isblank(AM35),"--",if(isblank($X$13),"Enter GM%",if(isblank($X$14),"Enter Lifespan",if(ISBLANK(AM42),"Enter AOV",$X$13*$X$14*AM42)))),if(isblank(AM35),"--",$X$17)) -> 110109.6 | AO43: =if($X$16="Yes",if(isblank(AO35),"--",if(isblank($X$13),"Enter GM%",if(isblank($X$14),"Enter Lifespan",if(ISBLANK(AO42),"Enter AOV",$X$13*$X$14*AO42)))),if(isblank(AO35),"--",$X$17)) -> 110109.6 | AQ43: =if($X$16="Yes",if(isblank(AQ35),"--",if(isblank($X$13),"Enter GM%",if(isblank($X$14),"Enter Lifespan",if(ISBLANK(AQ42),"Enter AOV",$X$13*$X$14*AQ42)))),if(isblank(AQ35),"--",$X$17)) -> 110109.6 | AS43: =if($X$16="Yes",if(isblank(AS35),"--",if(isblank($X$13),"Enter GM%",if(isblank($X$14),"Enter Lifespan",if(ISBLANK(AS42),"Enter AOV",$X$13*$X$14*AS42)))),if(isblank(AS35),"--",$X$17)) -> 110109.6 | AU43: =if($X$16="Yes",if(isblank(AU35),"--",if(isblank($X$13),"Enter GM%",if(isblank($X$14),"Enter Lifespan",if(ISBLANK(AU42),"Enter AOV",$X$13*$X$14*AU42)))),if(isblank(AU35),"--",$X$17)) -> 110109.6 | AW43: =if($X$16="Yes",if(isblank(AW35),"--",if(isblank($X$13),"Enter GM%",if(isblank($X$14),"Enter Lifespan",if(ISBLANK(AW42),"Enter AOV",$X$13*$X$14*AW42)))),if(isblank(AW35),"--",$X$17)) -> 110109.6 | AY43: =if($X$16="Yes",if(isblank(AY35),"--",if(isblank($X$13),"Enter GM%",if(isblank($X$14),"Enter Lifespan",if(ISBLANK(AY42),"Enter AOV",$X$13*$X$14*AY42)))),if(isblank(AY35),"--",$X$17)) -> 110109.6 | BA43: =if($X$16="Yes",if(isblank(BA35),"--",if(isblank($X$13),"Enter GM%",if(isblank($X$14),"Enter Lifespan",if(ISBLANK(BA42),"Enter AOV",$X$13*$X$14*BA42)))),if(isblank(BA35),"--",$X$17)) -> 110109.6 | BC43: =if($X$16="Yes",if(isblank(BC35),"--",if(isblank($X$13),"Enter GM%",if(isblank($X$14),"Enter Lifespan",if(ISBLANK(BC42),"Enter AOV",$X$13*$X$14*BC42)))),if(isblank(BC35),"--",$X$17)) -> 110109.6 | BE43: =if($X$16="Yes",if(isblank(BE35),"--",if(isblank($X$13),"Enter GM%",if(isblank($X$14),"Enter Lifespan",if(ISBLANK(BE42),"Enter AOV",$X$13*$X$14*BE42)))),if(isblank(BE35),"--",$X$17)) -> 110109.6 | BG43: =if($X$16="Yes",if(isblank(BG35),"--",if(isblank($X$13),"Enter GM%",if(isblank($X$14),"Enter Lifespan",if(ISBLANK(BG42),"Enter AOV",$X$13*$X$14*BG42)))),if(isblank(BG35),"--",$X$17)) -> 110109.6 | BI43: =if($X$16="Yes",if(isblank(BI35),"--",if(isblank($X$13),"Enter GM%",if(isblank($X$14),"Enter Lifespan",if(ISBLANK(BI42),"Enter AOV",$X$13*$X$14*BI42)))),if(isblank(BI35),"--",$X$17)) -> 110109.6 | BK43: =if($X$16="Yes",if(isblank(BK35),"--",if(isblank($X$13),"Enter GM%",if(isblank($X$14),"Enter Lifespan",if(ISBLANK(BK42),"Enter AOV",$X$13*$X$14*BK42)))),if(isblank(BK35),"--",$X$17)) -> 110109.6
B44: Total Est. Bookings | E44: =if(E35="--","--",sum(G44:BL44)) -> 2532520.8 | G44: =if(isblank(G35),"--",if(or(isblank(G41),G41=0),"No Customers",if(isnumber(G43),G43*G41,"No LTV"))) -> No Customers | I44: =if(isblank(I35),"--",if(or(isblank(I41),I41=0),"No Customers",if(isnumber(I43),I43*I41,"No LTV"))) -> No Customers | K44: =if(isblank(K35),"--",if(or(isblank(K41),K41=0),"No Customers",if(isnumber(K43),K43*K41,"No LTV"))) -> No Customers | M44: =if(isblank(M35),"--",if(or(isblank(M41),M41=0),"No Customers",if(isnumber(M43),M43*M41,"No LTV"))) -> No Customers | O44: =if(isblank(O35),"--",if(or(isblank(O41),O41=0),"No Customers",if(isnumber(O43),O43*O41,"No LTV"))) -> No Customers | Q44: =if(isblank(Q35),"--",if(or(isblank(Q41),Q41=0),"No Customers",if(isnumber(Q43),Q43*Q41,"No LTV"))) -> No Customers | S44: =if(isblank(S35),"--",if(or(isblank(S41),S41=0),"No Customers",if(isnumber(S43),S43*S41,"No LTV"))) -> No Customers | U44: =if(isblank(U35),"--",if(or(isblank(U41),U41=0),"No Customers",if(isnumber(U43),U43*U41,"No LTV"))) -> No Customers | W44: =if(isblank(W35),"--",if(or(isblank(W41),W41=0),"No Customers",if(isnumber(W43),W43*W41,"No LTV"))) -> No Customers | Y44: =if(isblank(Y35),"--",if(or(isblank(Y41),Y41=0),"No Customers",if(isnumber(Y43),Y43*Y41,"No LTV"))) -> No Customers | AA44: =if(isblank(AA35),"--",if(or(isblank(AA41),AA41=0),"No Customers",if(isnumber(AA43),AA43*AA41,"No LTV"))) -> 110109.6 | AC44: =if(isblank(AC35),"--",if(or(isblank(AC41),AC41=0),"No Customers",if(isnumber(AC43),AC43*AC41,"No LTV"))) -> No Customers | AE44: =if(isblank(AE35),"--",if(or(isblank(AE41),AE41=0),"No Customers",if(isnumber(AE43),AE43*AE41,"No LTV"))) -> No Customers | AG44: =if(isblank(AG35),"--",if(or(isblank(AG41),AG41=0),"No Customers",if(isnumber(AG43),AG43*AG41,"No LTV"))) -> No Customers | AI44: =if(isblank(AI35),"--",if(or(isblank(AI41),AI41=0),"No Customers",if(isnumber(AI43),AI43*AI41,"No LTV"))) -> No Customers | AK44: =if(isblank(AK35),"--",if(or(isblank(AK41),AK41=0),"No Customers",if(isnumber(AK43),AK43*AK41,"No LTV"))) -> No Customers | AM44: =if(isblank(AM35),"--",if(or(isblank(AM41),AM41=0),"No Customers",if(isnumber(AM43),AM43*AM41,"No LTV"))) -> 660657.6 | AO44: =if(isblank(AO35),"--",if(or(isblank(AO41),AO41=0),"No Customers",if(isnumber(AO43),AO43*AO41,"No LTV"))) -> No Customers | AQ44: =if(isblank(AQ35),"--",if(or(isblank(AQ41),AQ41=0),"No Customers",if(isnumber(AQ43),AQ43*AQ41,"No LTV"))) -> No Customers | AS44: =if(isblank(AS35),"--",if(or(isblank(AS41),AS41=0),"No Customers",if(isnumber(AS43),AS43*AS41,"No LTV"))) -> 330328.8 | AU44: =if(isblank(AU35),"--",if(or(isblank(AU41),AU41=0),"No Customers",if(isnumber(AU43),AU43*AU41,"No LTV"))) -> No Customers | AW44: =if(isblank(AW35),"--",if(or(isblank(AW41),AW41=0),"No Customers",if(isnumber(AW43),AW43*AW41,"No LTV"))) -> No Customers | AY44: =if(isblank(AY35),"--",if(or(isblank(AY41),AY41=0),"No Customers",if(isnumber(AY43),AY43*AY41,"No LTV"))) -> No Customers | BA44: =if(isblank(BA35),"--",if(or(isblank(BA41),BA41=0),"No Customers",if(isnumber(BA43),BA43*BA41,"No LTV"))) -> No Customers | BC44: =if(isblank(BC35),"--",if(or(isblank(BC41),BC41=0),"No Customers",if(isnumber(BC43),BC43*BC41,"No LTV"))) -> No Customers | BE44: =if(isblank(BE35),"--",if(or(isblank(BE41),BE41=0),"No Customers",if(isnumber(BE43),BE43*BE41,"No LTV"))) -> No Customers | BG44: =if(isblank(BG35),"--",if(or(isblank(BG41),BG41=0),"No Customers",if(isnumber(BG43),BG43*BG41,"No LTV"))) -> No Customers | BI44: =if(isblank(BI35),"--",if(or(isblank(BI41),BI41=0),"No Customers",if(isnumber(BI43),BI43*BI41,"No LTV"))) -> No Customers | BK44: =if(isblank(BK35),"--",if(or(isblank(BK41),BK41=0),"No Customers",if(isnumber(BK43),BK43*BK41,"No LTV"))) -> 1431424.8
B45: Net Return | E45: =if(E35="--","--",sum(G45:BL45)) -> 2369381.2 | G45: =if(isblank(G35),"--",if(istext(G44),G44,G44-G35)) -> No Customers | I45: =if(isblank(I35),"--",if(istext(I44),I44,I44-I35)) -> No Customers | K45: =if(isblank(K35),"--",if(istext(K44),K44,K44-K35)) -> No Customers | M45: =if(isblank(M35),"--",if(istext(M44),M44,M44-M35)) -> No Customers | O45: =if(isblank(O35),"--",if(istext(O44),O44,O44-O35)) -> No Customers | Q45: =if(isblank(Q35),"--",if(istext(Q44),Q44,Q44-Q35)) -> No Customers | S45: =if(isblank(S35),"--",if(istext(S44),S44,S44-S35)) -> No Customers | U45: =if(isblank(U35),"--",if(istext(U44),U44,U44-U35)) -> No Customers | W45: =if(isblank(W35),"--",if(istext(W44),W44,W44-W35)) -> No Customers | Y45: =if(isblank(Y35),"--",if(istext(Y44),Y44,Y44-Y35)) -> No Customers | AA45: =if(isblank(AA35),"--",if(istext(AA44),AA44,AA44-AA35)) -> 102829 | AC45: =if(isblank(AC35),"--",if(istext(AC44),AC44,AC44-AC35)) -> No Customers | AE45: =if(isblank(AE35),"--",if(istext(AE44),AE44,AE44-AE35)) -> No Customers | AG45: =if(isblank(AG35),"--",if(istext(AG44),AG44,AG44-AG35)) -> No Customers | AI45: =if(isblank(AI35),"--",if(istext(AI44),AI44,AI44-AI35)) -> No Customers | AK45: =if(isblank(AK35),"--",if(istext(AK44),AK44,AK44-AK35)) -> No Customers | AM45: =if(isblank(AM35),"--",if(istext(AM44),AM44,AM44-AM35)) -> 567348.33 | AO45: =if(isblank(AO35),"--",if(istext(AO44),AO44,AO44-AO35)) -> No Customers | AQ45: =if(isblank(AQ35),"--",if(istext(AQ44),AQ44,AQ44-AQ35)) -> No Customers | AS45: =if(isblank(AS35),"--",if(istext(AS44),AS44,AS44-AS35)) -> 296394.06 | AU45: =if(isblank(AU35),"--",if(istext(AU44),AU44,AU44-AU35)) -> No Customers | AW45: =if(isblank(AW35),"--",if(istext(AW44),AW44,AW44-AW35)) -> No Customers | AY45: =if(isblank(AY35),"--",if(istext(AY44),AY44,AY44-AY35)) -> No Customers | BA45: =if(isblank(BA35),"--",if(istext(BA44),BA44,BA44-BA35)) -> No Customers | BC45: =if(isblank(BC35),"--",if(istext(BC44),BC44,BC44-BC35)) -> No Customers | BE45: =if(isblank(BE35),"--",if(istext(BE44),BE44,BE44-BE35)) -> No Customers | BG45: =if(isblank(BG35),"--",if(istext(BG44),BG44,BG44-BG35)) -> No Customers | BI45: =if(isblank(BI35),"--",if(istext(BI44),BI44,BI44-BI35)) -> No Customers | BK45: =if(isblank(BK35),"--",if(istext(BK44),BK44,BK44-BK35)) -> 1402809.8
B46: =if(ISBLANK(B36),"--","Cost-per-"&LEFT(B36,LEN(B36)-1)) -> Cost-per-Form Fill | E46: =iferror($E$35/E36,"--") -> 288.2992 | G46: =iferror(G$35/G36,"--") -> 239.48778 | I46: =iferror(I$35/I36,"--") -> 790.57 | K46: =iferror(K$35/K36,"--") -> 0 | M46: =iferror(M$35/M36,"--") -> 0 | O46: =iferror(O$35/O36,"--") -> -- | Q46: =iferror(Q$35/Q36,"--") -> 0 | S46: =iferror(S$35/S36,"--") -> 0 | U46: =iferror(U$35/U36,"--") -> 0 | W46: =iferror(W$35/W36,"--") -> 0 | Y46: =iferror(Y$35/Y36,"--") -> 0 | AA46: =iferror(AA$35/AA36,"--") -> 606.71667 | AC46: =iferror(AC$35/AC36,"--") -> -- | AE46: =iferror(AE$35/AE36,"--") -> -- | AG46: =iferror(AG$35/AG36,"--") -> -- | AI46: =iferror(AI$35/AI36,"--") -> 0 | AK46: =iferror(AK$35/AK36,"--") -> -- | AM46: =iferror(AM$35/AM36,"--") -> 473.65112 | AO46: =iferror(AO$35/AO36,"--") -> 214.19672 | AQ46: =iferror(AQ$35/AQ36,"--") -> 16.129032 | AS46: =iferror(AS$35/AS36,"--") -> 556.30721 | AU46: =iferror(AU$35/AU36,"--") -> -- | AW46: =iferror(AW$35/AW36,"--") -> 368.27785 | AY46: =iferror(AY$35/AY36,"--") -> -- | BA46: =iferror(BA$35/BA36,"--") -> 0 | BC46: =iferror(BC$35/BC36,"--") -> 0 | BE46: =iferror(BE$35/BE36,"--") -> 0 | BG46: =iferror(BG$35/BG36,"--") -> -- | BI46: =iferror(BI$35/BI36,"--") -> 0 | BK46: =iferror(BK$35/BK36,"--") -> 202.94326
B47: =if(ISBLANK(B37),"--","Cost-per-"&LEFT(B37,LEN(B37)-1)) -> Cost-per-Intro Held | E47: =iferror($E$35/E37,"--") -> 546.42756 | G47: =iferror(G$35/G37,"--") -> 359.23167 | I47: =iferror(I$35/I37,"--") -> -- | K47: =iferror(K$35/K37,"--") -> 0 | M47: =iferror(M$35/M37,"--") -> -- | O47: =iferror(O$35/O37,"--") -> -- | Q47: =iferror(Q$35/Q37,"--") -> -- | S47: =iferror(S$35/S37,"--") -> 0 | U47: =iferror(U$35/U37,"--") -> 0 | W47: =iferror(W$35/W37,"--") -> 0 | Y47: =iferror(Y$35/Y37,"--") -> 0 | AA47: =iferror(AA$35/AA37,"--") -> 1213.4333 | AC47: =iferror(AC$35/AC37,"--") -> -- | AE47: =iferror(AE$35/AE37,"--") -> -- | AG47: =iferror(AG$35/AG37,"--") -> -- | AI47: =iferror(AI$35/AI37,"--") -> -- | AK47: =iferror(AK$35/AK37,"--") -> -- | AM47: =iferror(AM$35/AM37,"--") -> 961.95124 | AO47: =iferror(AO$35/AO37,"--") -> 653.86368 | AQ47: =iferror(AQ$35/AQ37,"--") -> 24.390244 | AS47: =iferror(AS$35/AS37,"--") -> 1996.1612 | AU47: =iferror(AU$35/AU37,"--") -> -- | AW47: =iferror(AW$35/AW37,"--") -> 658.65077 | AY47: =iferror(AY$35/AY37,"--") -> -- | BA47: =iferror(BA$35/BA37,"--") -> 0 | BC47: =iferror(BC$35/BC37,"--") -> 0 | BE47: =iferror(BE$35/BE37,"--") -> 0 | BG47: =iferror(BG$35/BG37,"--") -> -- | BI47: =iferror(BI$35/BI37,"--") -> 0 | BK47: =iferror(BK$35/BK37,"--") -> 298.07292
B48: =if(ISBLANK(B38),"--","Cost-per-"&LEFT(B38,LEN(B38)-1)) -> Cost-per-Strat Call Held | E48: =iferror($E$35/E38,"--") -> 1358.1725 | G48: =iferror(G$35/G38,"--") -> 2155.39 | I48: =iferror(I$35/I38,"--") -> -- | K48: =iferror(K$35/K38,"--") -> -- | M48: =iferror(M$35/M38,"--") -> -- | O48: =iferror(O$35/O38,"--") -> -- | Q48: =iferror(Q$35/Q38,"--") -> -- | S48: =iferror(S$35/S38,"--") -> -- | U48: =iferror(U$35/U38,"--") -> 0 | W48: =iferror(W$35/W38,"--") -> -- | Y48: =iferror(Y$35/Y38,"--") -> -- | AA48: =iferror(AA$35/AA38,"--") -> 7280.6 | AC48: =iferror(AC$35/AC38,"--") -> -- | AE48: =iferror(AE$35/AE38,"--") -> -- | AG48: =iferror(AG$35/AG38,"--") -> -- | AI48: =iferror(AI$35/AI38,"--") -> -- | AK48: =iferror(AK$35/AK38,"--") -> -- | AM48: =iferror(AM$35/AM38,"--") -> 3217.561 | AO48: =iferror(AO$35/AO38,"--") -> 1552.9262 | AQ48: =iferror(AQ$35/AQ38,"--") -> 111.11111 | AS48: =iferror(AS$35/AS38,"--") -> 2827.895 | AU48: =iferror(AU$35/AU38,"--") -> -- | AW48: =iferror(AW$35/AW38,"--") -> 2446.4171 | AY48: =iferror(AY$35/AY38,"--") -> -- | BA48: =iferror(BA$35/BA38,"--") -> 0 | BC48: =iferror(BC$35/BC38,"--") -> 0 | BE48: =iferror(BE$35/BE38,"--") -> 0 | BG48: =iferror(BG$35/BG38,"--") -> -- | BI48: =iferror(BI$35/BI38,"--") -> 0 | BK48: =iferror(BK$35/BK38,"--") -> 414.71014
B49: =if(ISBLANK(B39),"--","Cost-per-"&LEFT(B39,LEN(B39)-1)) -> Cost-per-Proposal | E49: =iferror($E$35/E39,"--") -> 1925.9332 | G49: =iferror(G$35/G39,"--") -> 718.46333 | I49: =iferror(I$35/I39,"--") -> -- | K49: =iferror(K$35/K39,"--") -> -- | M49: =iferror(M$35/M39,"--") -> -- | O49: =iferror(O$35/O39,"--") -> -- | Q49: =iferror(Q$35/Q39,"--") -> -- | S49: =iferror(S$35/S39,"--") -> -- | U49: =iferror(U$35/U39,"--") -> 0 | W49: =iferror(W$35/W39,"--") -> -- | Y49: =iferror(Y$35/Y39,"--") -> -- | AA49: =iferror(AA$35/AA39,"--") -> 3640.3 | AC49: =iferror(AC$35/AC39,"--") -> -- | AE49: =iferror(AE$35/AE39,"--") -> -- | AG49: =iferror(AG$35/AG39,"--") -> -- | AI49: =iferror(AI$35/AI39,"--") -> -- | AK49: =iferror(AK$35/AK39,"--") -> -- | AM49: =iferror(AM$35/AM39,"--") -> 8482.6609 | AO49: =iferror(AO$35/AO39,"--") -> 3105.8525 | AQ49: =iferror(AQ$35/AQ39,"--") -> 153.84615 | AS49: =iferror(AS$35/AS39,"--") -> 4847.82 | AU49: =iferror(AU$35/AU39,"--") -> -- | AW49: =iferror(AW$35/AW39,"--") -> 3805.5378 | AY49: =iferror(AY$35/AY39,"--") -> -- | BA49: =iferror(BA$35/BA39,"--") -> 0 | BC49: =iferror(BC$35/BC39,"--") -> 0 | BE49: =iferror(BE$35/BE39,"--") -> -- | BG49: =iferror(BG$35/BG39,"--") -> -- | BI49: =iferror(BI$35/BI39,"--") -> 0 | BK49: =iferror(BK$35/BK39,"--") -> 414.71014
B50: =if(ISBLANK(B40),"--","Cost-per-"&LEFT(B40,LEN(B40)-1)) -> -- | E50: =iferror($E$35/E40,"--") -> -- | G50: =iferror(G$35/G40,"--") -> -- | I50: =iferror(I$35/I40,"--") -> -- | K50: =iferror(K$35/K40,"--") -> -- | M50: =iferror(M$35/M40,"--") -> -- | O50: =iferror(O$35/O40,"--") -> -- | Q50: =iferror(Q$35/Q40,"--") -> -- | S50: =iferror(S$35/S40,"--") -> -- | U50: =iferror(U$35/U40,"--") -> -- | W50: =iferror(W$35/W40,"--") -> -- | Y50: =iferror(Y$35/Y40,"--") -> -- | AA50: =iferror(AA$35/AA40,"--") -> -- | AC50: =iferror(AC$35/AC40,"--") -> -- | AE50: =iferror(AE$35/AE40,"--") -> -- | AG50: =iferror(AG$35/AG40,"--") -> -- | AI50: =iferror(AI$35/AI40,"--") -> -- | AK50: =iferror(AK$35/AK40,"--") -> -- | AM50: =iferror(AM$35/AM40,"--") -> -- | AO50: =iferror(AO$35/AO40,"--") -> -- | AQ50: =iferror(AQ$35/AQ40,"--") -> -- | AS50: =iferror(AS$35/AS40,"--") -> -- | AU50: =iferror(AU$35/AU40,"--") -> -- | AW50: =iferror(AW$35/AW40,"--") -> -- | AY50: =iferror(AY$35/AY40,"--") -> -- | BA50: =iferror(BA$35/BA40,"--") -> -- | BC50: =iferror(BC$35/BC40,"--") -> -- | BE50: =iferror(BE$35/BE40,"--") -> -- | BG50: =iferror(BG$35/BG40,"--") -> -- | BI50: =iferror(BI$35/BI40,"--") -> -- | BK50: =iferror(BK$35/BK40,"--") -> --
B51: =if(ISBLANK(B41),"--","Cost-per-"&LEFT(B41,LEN(B41)-1)) -> Cost-per-Customer | E51: =iferror($E$35/E41,"--") -> 10215.82 | G51: =iferror(G$35/G41,"--") -> -- | I51: =iferror(I$35/I41,"--") -> -- | K51: =iferror(K$35/K41,"--") -> -- | M51: =iferror(M$35/M41,"--") -> -- | O51: =iferror(O$35/O41,"--") -> -- | Q51: =iferror(Q$35/Q41,"--") -> -- | S51: =iferror(S$35/S41,"--") -> -- | U51: =iferror(U$35/U41,"--") -> -- | W51: =iferror(W$35/W41,"--") -> -- | Y51: =iferror(Y$35/Y41,"--") -> -- | AA51: =iferror(AA$35/AA41,"--") -> 7280.6 | AC51: =iferror(AC$35/AC41,"--") -> -- | AE51: =iferror(AE$35/AE41,"--") -> -- | AG51: =iferror(AG$35/AG41,"--") -> -- | AI51: =iferror(AI$35/AI41,"--") -> -- | AK51: =iferror(AK$35/AK41,"--") -> -- | AM51: =iferror(AM$35/AM41,"--") -> 15551.545 | AO51: =iferror(AO$35/AO41,"--") -> -- | AQ51: =iferror(AQ$35/AQ41,"--") -> -- | AS51: =iferror(AS$35/AS41,"--") -> 11311.58 | AU51: =iferror(AU$35/AU41,"--") -> -- | AW51: =iferror(AW$35/AW41,"--") -> -- | AY51: =iferror(AY$35/AY41,"--") -> -- | BA51: =iferror(BA$35/BA41,"--") -> -- | BC51: =iferror(BC$35/BC41,"--") -> -- | BE51: =iferror(BE$35/BE41,"--") -> -- | BG51: =iferror(BG$35/BG41,"--") -> -- | BI51: =iferror(BI$35/BI41,"--") -> -- | BK51: =iferror(BK$35/BK41,"--") -> 2201.1538
B52: =iferror(if(match(B36,$B$36:$B$40,0)=Counta($B$36:$B$40),LEFT(B36,LEN(B36)-1)&" > "&LEFT($B$41,LEN($B$41)-1),LEFT(B36,LEN(B36)-1)&" > "&LEFT(B37,LEN(B37)-1)),"--") -> Form Fill > Intro Held | E52: =iferror(if(match(B36,$B$36:$B$40,0)=Counta($B$36:$B$40),$E$41/E36,E37/E36),"--") -> 0.52760736 | G52: =iferror(if(match($B$36,$B$36:$B$40,0)=Counta($B$36:$B$40),G41/G36,G37/G36),"--") -> 0.66666667 | I52: =iferror(if(match($B$36,$B$36:$B$40,0)=Counta($B$36:$B$40),I41/I36,I37/I36),"--") -> 0 | K52: =iferror(if(match($B$36,$B$36:$B$40,0)=Counta($B$36:$B$40),K41/K36,K37/K36),"--") -> 0.57142857 | M52: =iferror(if(match($B$36,$B$36:$B$40,0)=Counta($B$36:$B$40),M41/M36,M37/M36),"--") -> 0 | O52: =iferror(if(match($B$36,$B$36:$B$40,0)=Counta($B$36:$B$40),O41/O36,O37/O36),"--") -> -- | Q52: =iferror(if(match($B$36,$B$36:$B$40,0)=Counta($B$36:$B$40),Q41/Q36,Q37/Q36),"--") -> 0 | S52: =iferror(if(match($B$36,$B$36:$B$40,0)=Counta($B$36:$B$40),S41/S36,S37/S36),"--") -> 0.4 | U52: =iferror(if(match($B$36,$B$36:$B$40,0)=Counta($B$36:$B$40),U41/U36,U37/U36),"--") -> 0.55555556 | W52: =iferror(if(match($B$36,$B$36:$B$40,0)=Counta($B$36:$B$40),W41/W36,W37/W36),"--") -> 0.88888889 | Y52: =iferror(if(match($B$36,$B$36:$B$40,0)=Counta($B$36:$B$40),Y41/Y36,Y37/Y36),"--") -> 0.5 | AA52: =iferror(if(match($B$36,$B$36:$B$40,0)=Counta($B$36:$B$40),AA41/AA36,AA37/AA36),"--") -> 0.5 | AC52: =iferror(if(match($B$36,$B$36:$B$40,0)=Counta($B$36:$B$40),AC41/AC36,AC37/AC36),"--") -> -- | AE52: =iferror(if(match($B$36,$B$36:$B$40,0)=Counta($B$36:$B$40),AE41/AE36,AE37/AE36),"--") -> -- | AG52: =iferror(if(match($B$36,$B$36:$B$40,0)=Counta($B$36:$B$40),AG41/AG36,AG37/AG36),"--") -> -- | AI52: =iferror(if(match($B$36,$B$36:$B$40,0)=Counta($B$36:$B$40),AI41/AI36,AI37/AI36),"--") -> 0 | AK52: =iferror(if(match($B$36,$B$36:$B$40,0)=Counta($B$36:$B$40),AK41/AK36,AK37/AK36),"--") -> -- | AM52: =iferror(if(match($B$36,$B$36:$B$40,0)=Counta($B$36:$B$40),AM41/AM36,AM37/AM36),"--") -> 0.49238579 | AO52: =iferror(if(match($B$36,$B$36:$B$40,0)=Counta($B$36:$B$40),AO41/AO36,AO37/AO36),"--") -> 0.32758621 | AQ52: =iferror(if(match($B$36,$B$36:$B$40,0)=Counta($B$36:$B$40),AQ41/AQ36,AQ37/AQ36),"--") -> 0.66129032 | AS52: =iferror(if(match($B$36,$B$36:$B$40,0)=Counta($B$36:$B$40),AS41/AS36,AS37/AS36),"--") -> 0.27868852 | AU52: =iferror(if(match($B$36,$B$36:$B$40,0)=Counta($B$36:$B$40),AU41/AU36,AU37/AU36),"--") -> -- | AW52: =iferror(if(match($B$36,$B$36:$B$40,0)=Counta($B$36:$B$40),AW41/AW36,AW37/AW36),"--") -> 0.55913978 | AY52: =iferror(if(match($B$36,$B$36:$B$40,0)=Counta($B$36:$B$40),AY41/AY36,AY37/AY36),"--") -> -- | BA52: =iferror(if(match($B$36,$B$36:$B$40,0)=Counta($B$36:$B$40),BA41/BA36,BA37/BA36),"--") -> 0.33333333 | BC52: =iferror(if(match($B$36,$B$36:$B$40,0)=Counta($B$36:$B$40),BC41/BC36,BC37/BC36),"--") -> 0.33333333 | BE52: =iferror(if(match($B$36,$B$36:$B$40,0)=Counta($B$36:$B$40),BE41/BE36,BE37/BE36),"--") -> 1 | BG52: =iferror(if(match($B$36,$B$36:$B$40,0)=Counta($B$36:$B$40),BG41/BG36,BG37/BG36),"--") -> -- | BI52: =iferror(if(match($B$36,$B$36:$B$40,0)=Counta($B$36:$B$40),BI41/BI36,BI37/BI36),"--") -> 0.48148148 | BK52: =iferror(if(match($B$36,$B$36:$B$40,0)=Counta($B$36:$B$40),BK41/BK36,BK37/BK36),"--") -> 0.68085106
B53: =iferror(if(match(B37,$B$36:$B$40,0)=Counta($B$36:$B$40),LEFT(B37,LEN(B37)-1)&" > "&LEFT($B$41,LEN($B$41)-1),LEFT(B37,LEN(B37)-1)&" > "&LEFT(B38,LEN(B38)-1)),"--") -> Intro Held > Strat Call Held | E53: =iferror(if(match(B37,$B$36:$B$40,0)=Counta($B$36:$B$40),$E$41/E37,E38/E37),"--") -> 0.40232558 | G53: =iferror(if(match($B$37,$B$36:$B$40,0)=Counta($B$36:$B$40),G41/G37,G38/G37),"--") -> 0.16666667 | I53: =iferror(if(match($B$37,$B$36:$B$40,0)=Counta($B$36:$B$40),I41/I37,I38/I37),"--") -> -- | K53: =iferror(if(match($B$37,$B$36:$B$40,0)=Counta($B$36:$B$40),K41/K37,K38/K37),"--") -> 0 | M53: =iferror(if(match($B$37,$B$36:$B$40,0)=Counta($B$36:$B$40),M41/M37,M38/M37),"--") -> -- | O53: =iferror(if(match($B$37,$B$36:$B$40,0)=Counta($B$36:$B$40),O41/O37,O38/O37),"--") -> -- | Q53: =iferror(if(match($B$37,$B$36:$B$40,0)=Counta($B$36:$B$40),Q41/Q37,Q38/Q37),"--") -> -- | S53: =iferror(if(match($B$37,$B$36:$B$40,0)=Counta($B$36:$B$40),S41/S37,S38/S37),"--") -> 0 | U53: =iferror(if(match($B$37,$B$36:$B$40,0)=Counta($B$36:$B$40),U41/U37,U38/U37),"--") -> 0.6 | W53: =iferror(if(match($B$37,$B$36:$B$40,0)=Counta($B$36:$B$40),W41/W37,W38/W37),"--") -> 0 | Y53: =iferror(if(match($B$37,$B$36:$B$40,0)=Counta($B$36:$B$40),Y41/Y37,Y38/Y37),"--") -> 0 | AA53: =iferror(if(match($B$37,$B$36:$B$40,0)=Counta($B$36:$B$40),AA41/AA37,AA38/AA37),"--") -> 0.16666667 | AC53: =iferror(if(match($B$37,$B$36:$B$40,0)=Counta($B$36:$B$40),AC41/AC37,AC38/AC37),"--") -> -- | AE53: =iferror(if(match($B$37,$B$36:$B$40,0)=Counta($B$36:$B$40),AE41/AE37,AE38/AE37),"--") -> -- | AG53: =iferror(if(match($B$37,$B$36:$B$40,0)=Counta($B$36:$B$40),AG41/AG37,AG38/AG37),"--") -> -- | AI53: =iferror(if(match($B$37,$B$36:$B$40,0)=Counta($B$36:$B$40),AI41/AI37,AI38/AI37),"--") -> -- | AK53: =iferror(if(match($B$37,$B$36:$B$40,0)=Counta($B$36:$B$40),AK41/AK37,AK38/AK37),"--") -> -- | AM53: =iferror(if(match($B$37,$B$36:$B$40,0)=Counta($B$36:$B$40),AM41/AM37,AM38/AM37),"--") -> 0.29896907 | AO53: =iferror(if(match($B$37,$B$36:$B$40,0)=Counta($B$36:$B$40),AO41/AO37,AO38/AO37),"--") -> 0.42105263 | AQ53: =iferror(if(match($B$37,$B$36:$B$40,0)=Counta($B$36:$B$40),AQ41/AQ37,AQ38/AQ37),"--") -> 0.2195122 | AS53: =iferror(if(match($B$37,$B$36:$B$40,0)=Counta($B$36:$B$40),AS41/AS37,AS38/AS37),"--") -> 0.70588235 | AU53: =iferror(if(match($B$37,$B$36:$B$40,0)=Counta($B$36:$B$40),AU41/AU37,AU38/AU37),"--") -> -- | AW53: =iferror(if(match($B$37,$B$36:$B$40,0)=Counta($B$36:$B$40),AW41/AW37,AW38/AW37),"--") -> 0.26923077 | AY53: =iferror(if(match($B$37,$B$36:$B$40,0)=Counta($B$36:$B$40),AY41/AY37,AY38/AY37),"--") -> -- | BA53: =iferror(if(match($B$37,$B$36:$B$40,0)=Counta($B$36:$B$40),BA41/BA37,BA38/BA37),"--") -> 0.25 | BC53: =iferror(if(match($B$37,$B$36:$B$40,0)=Counta($B$36:$B$40),BC41/BC37,BC38/BC37),"--") -> 0.25 | BE53: =iferror(if(match($B$37,$B$36:$B$40,0)=Counta($B$36:$B$40),BE41/BE37,BE38/BE37),"--") -> 1 | BG53: =iferror(if(match($B$37,$B$36:$B$40,0)=Counta($B$36:$B$40),BG41/BG37,BG38/BG37),"--") -> -- | BI53: =iferror(if(match($B$37,$B$36:$B$40,0)=Counta($B$36:$B$40),BI41/BI37,BI38/BI37),"--") -> 0.57692308 | BK53: =iferror(if(match($B$37,$B$36:$B$40,0)=Counta($B$36:$B$40),BK41/BK37,BK38/BK37),"--") -> 0.71875
B54: =iferror(if(match(B38,$B$36:$B$40,0)=Counta($B$36:$B$40),LEFT(B38,LEN(B38)-1)&" > "&LEFT($B$41,LEN($B$41)-1),LEFT(B38,LEN(B38)-1)&" > "&LEFT(B39,LEN(B39)-1)),"--") -> Strat Call Held > Proposal | E54: =iferror(if(match(B38,$B$36:$B$40,0)=Counta($B$36:$B$40),$E$41/E38,E39/E38),"--") -> 0.70520231 | G54: =iferror(if(match($B$38,$B$36:$B$40,0)=Counta($B$36:$B$40),G41/G38,G39/G38),"--") -> 3 | I54: =iferror(if(match($B$38,$B$36:$B$40,0)=Counta($B$36:$B$40),I41/I38,I39/I38),"--") -> -- | K54: =iferror(if(match($B$38,$B$36:$B$40,0)=Counta($B$36:$B$40),K41/K38,K39/K38),"--") -> -- | M54: =iferror(if(match($B$38,$B$36:$B$40,0)=Counta($B$36:$B$40),M41/M38,M39/M38),"--") -> -- | O54: =iferror(if(match($B$38,$B$36:$B$40,0)=Counta($B$36:$B$40),O41/O38,O39/O38),"--") -> -- | Q54: =iferror(if(match($B$38,$B$36:$B$40,0)=Counta($B$36:$B$40),Q41/Q38,Q39/Q38),"--") -> -- | S54: =iferror(if(match($B$38,$B$36:$B$40,0)=Counta($B$36:$B$40),S41/S38,S39/S38),"--") -> -- | U54: =iferror(if(match($B$38,$B$36:$B$40,0)=Counta($B$36:$B$40),U41/U38,U39/U38),"--") -> 0.33333333 | W54: =iferror(if(match($B$38,$B$36:$B$40,0)=Counta($B$36:$B$40),W41/W38,W39/W38),"--") -> -- | Y54: =iferror(if(match($B$38,$B$36:$B$40,0)=Counta($B$36:$B$40),Y41/Y38,Y39/Y38),"--") -> -- | AA54: =iferror(if(match($B$38,$B$36:$B$40,0)=Counta($B$36:$B$40),AA41/AA38,AA39/AA38),"--") -> 2 | AC54: =iferror(if(match($B$38,$B$36:$B$40,0)=Counta($B$36:$B$40),AC41/AC38,AC39/AC38),"--") -> -- | AE54: =iferror(if(match($B$38,$B$36:$B$40,0)=Counta($B$36:$B$40),AE41/AE38,AE39/AE38),"--") -> -- | AG54: =iferror(if(match($B$38,$B$36:$B$40,0)=Counta($B$36:$B$40),AG41/AG38,AG39/AG38),"--") -> -- | AI54: =iferror(if(match($B$38,$B$36:$B$40,0)=Counta($B$36:$B$40),AI41/AI38,AI39/AI38),"--") -> -- | AK54: =iferror(if(match($B$38,$B$36:$B$40,0)=Counta($B$36:$B$40),AK41/AK38,AK39/AK38),"--") -> -- | AM54: =iferror(if(match($B$38,$B$36:$B$40,0)=Counta($B$36:$B$40),AM41/AM38,AM39/AM38),"--") -> 0.37931034 | AO54: =iferror(if(match($B$38,$B$36:$B$40,0)=Counta($B$36:$B$40),AO41/AO38,AO39/AO38),"--") -> 0.5 | AQ54: =iferror(if(match($B$38,$B$36:$B$40,0)=Counta($B$36:$B$40),AQ41/AQ38,AQ39/AQ38),"--") -> 0.72222222 | AS54: =iferror(if(match($B$38,$B$36:$B$40,0)=Counta($B$36:$B$40),AS41/AS38,AS39/AS38),"--") -> 0.58333333 | AU54: =iferror(if(match($B$38,$B$36:$B$40,0)=Counta($B$36:$B$40),AU41/AU38,AU39/AU38),"--") -> -- | AW54: =iferror(if(match($B$38,$B$36:$B$40,0)=Counta($B$36:$B$40),AW41/AW38,AW39/AW38),"--") -> 0.64285714 | AY54: =iferror(if(match($B$38,$B$36:$B$40,0)=Counta($B$36:$B$40),AY41/AY38,AY39/AY38),"--") -> -- | BA54: =iferror(if(match($B$38,$B$36:$B$40,0)=Counta($B$36:$B$40),BA41/BA38,BA39/BA38),"--") -> 1 | BC54: =iferror(if(match($B$38,$B$36:$B$40,0)=Counta($B$36:$B$40),BC41/BC38,BC39/BC38),"--") -> 1 | BE54: =iferror(if(match($B$38,$B$36:$B$40,0)=Counta($B$36:$B$40),BE41/BE38,BE39/BE38),"--") -> 0 | BG54: =iferror(if(match($B$38,$B$36:$B$40,0)=Counta($B$36:$B$40),BG41/BG38,BG39/BG38),"--") -> -- | BI54: =iferror(if(match($B$38,$B$36:$B$40,0)=Counta($B$36:$B$40),BI41/BI38,BI39/BI38),"--") -> 0.066666667 | BK54: =iferror(if(match($B$38,$B$36:$B$40,0)=Counta($B$36:$B$40),BK41/BK38,BK39/BK38),"--") -> 1
B55: =iferror(if(match(B39,$B$36:$B$40,0)=Counta($B$36:$B$40),LEFT(B39,LEN(B39)-1)&" > "&LEFT($B$41,LEN($B$41)-1),LEFT(B39,LEN(B39)-1)&" > "&LEFT(B40,LEN(B40)-1)),"--") -> Proposal > Customer | E55: =iferror(if(match(B39,$B$36:$B$40,0)=Counta($B$36:$B$40),$E$41/E39,E40/E39),"--") -> 0.18852459 | G55: =iferror(if(match($B$39,$B$36:$B$40,0)=Counta($B$36:$B$40),G41/G39,G40/G39),"--") -> 0 | I55: =iferror(if(match($B$39,$B$36:$B$40,0)=Counta($B$36:$B$40),I41/I39,I40/I39),"--") -> -- | K55: =iferror(if(match($B$39,$B$36:$B$40,0)=Counta($B$36:$B$40),K41/K39,K40/K39),"--") -> -- | M55: =iferror(if(match($B$39,$B$36:$B$40,0)=Counta($B$36:$B$40),M41/M39,M40/M39),"--") -> -- | O55: =iferror(if(match($B$39,$B$36:$B$40,0)=Counta($B$36:$B$40),O41/O39,O40/O39),"--") -> -- | Q55: =iferror(if(match($B$39,$B$36:$B$40,0)=Counta($B$36:$B$40),Q41/Q39,Q40/Q39),"--") -> -- | S55: =iferror(if(match($B$39,$B$36:$B$40,0)=Counta($B$36:$B$40),S41/S39,S40/S39),"--") -> -- | U55: =iferror(if(match($B$39,$B$36:$B$40,0)=Counta($B$36:$B$40),U41/U39,U40/U39),"--") -> 0 | W55: =iferror(if(match($B$39,$B$36:$B$40,0)=Counta($B$36:$B$40),W41/W39,W40/W39),"--") -> -- | Y55: =iferror(if(match($B$39,$B$36:$B$40,0)=Counta($B$36:$B$40),Y41/Y39,Y40/Y39),"--") -> -- | AA55: =iferror(if(match($B$39,$B$36:$B$40,0)=Counta($B$36:$B$40),AA41/AA39,AA40/AA39),"--") -> 0.5 | AC55: =iferror(if(match($B$39,$B$36:$B$40,0)=Counta($B$36:$B$40),AC41/AC39,AC40/AC39),"--") -> -- | AE55: =iferror(if(match($B$39,$B$36:$B$40,0)=Counta($B$36:$B$40),AE41/AE39,AE40/AE39),"--") -> -- | AG55: =iferror(if(match($B$39,$B$36:$B$40,0)=Counta($B$36:$B$40),AG41/AG39,AG40/AG39),"--") -> -- | AI55: =iferror(if(match($B$39,$B$36:$B$40,0)=Counta($B$36:$B$40),AI41/AI39,AI40/AI39),"--") -> -- | AK55: =iferror(if(match($B$39,$B$36:$B$40,0)=Counta($B$36:$B$40),AK41/AK39,AK40/AK39),"--") -> -- | AM55: =iferror(if(match($B$39,$B$36:$B$40,0)=Counta($B$36:$B$40),AM41/AM39,AM40/AM39),"--") -> 0.54545455 | AO55: =iferror(if(match($B$39,$B$36:$B$40,0)=Counta($B$36:$B$40),AO41/AO39,AO40/AO39),"--") -> 0 | AQ55: =iferror(if(match($B$39,$B$36:$B$40,0)=Counta($B$36:$B$40),AQ41/AQ39,AQ40/AQ39),"--") -> 0 | AS55: =iferror(if(match($B$39,$B$36:$B$40,0)=Counta($B$36:$B$40),AS41/AS39,AS40/AS39),"--") -> 0.42857143 | AU55: =iferror(if(match($B$39,$B$36:$B$40,0)=Counta($B$36:$B$40),AU41/AU39,AU40/AU39),"--") -> -- | AW55: =iferror(if(match($B$39,$B$36:$B$40,0)=Counta($B$36:$B$40),AW41/AW39,AW40/AW39),"--") -> 0 | AY55: =iferror(if(match($B$39,$B$36:$B$40,0)=Counta($B$36:$B$40),AY41/AY39,AY40/AY39),"--") -> -- | BA55: =iferror(if(match($B$39,$B$36:$B$40,0)=Counta($B$36:$B$40),BA41/BA39,BA40/BA39),"--") -> 0 | BC55: =iferror(if(match($B$39,$B$36:$B$40,0)=Counta($B$36:$B$40),BC41/BC39,BC40/BC39),"--") -> 0 | BE55: =iferror(if(match($B$39,$B$36:$B$40,0)=Counta($B$36:$B$40),BE41/BE39,BE40/BE39),"--") -> -- | BG55: =iferror(if(match($B$39,$B$36:$B$40,0)=Counta($B$36:$B$40),BG41/BG39,BG40/BG39),"--") -> -- | BI55: =iferror(if(match($B$39,$B$36:$B$40,0)=Counta($B$36:$B$40),BI41/BI39,BI40/BI39),"--") -> 0 | BK55: =iferror(if(match($B$39,$B$36:$B$40,0)=Counta($B$36:$B$40),BK41/BK39,BK40/BK39),"--") -> 0.1884058
B56: =iferror(if(match(B40,$B$36:$B$40,0)=Counta($B$36:$B$40),LEFT(B40,LEN(B40)-1)&" > "&LEFT($B$41,LEN($B$41)-1),LEFT(B40,LEN(B40)-1)&" > "&LEFT(B41,LEN(B41)-1)),"--") -> -- | E56: =iferror(if(match(B40,$B$36:$B$40,0)=Counta($B$36:$B$40),$E$41/E40,E41/E40),"--") -> -- | G56: =iferror(if(match($B$40,$B$36:$B$40,0)=Counta($B$36:$B$40),G41/G40,G41/G40),"--") -> -- | I56: =iferror(if(match($B$40,$B$36:$B$40,0)=Counta($B$36:$B$40),I41/I40,I41/I40),"--") -> -- | K56: =iferror(if(match($B$40,$B$36:$B$40,0)=Counta($B$36:$B$40),K41/K40,K41/K40),"--") -> -- | M56: =iferror(if(match($B$40,$B$36:$B$40,0)=Counta($B$36:$B$40),M41/M40,M41/M40),"--") -> -- | O56: =iferror(if(match($B$40,$B$36:$B$40,0)=Counta($B$36:$B$40),O41/O40,O41/O40),"--") -> -- | Q56: =iferror(if(match($B$40,$B$36:$B$40,0)=Counta($B$36:$B$40),Q41/Q40,Q41/Q40),"--") -> -- | S56: =iferror(if(match($B$40,$B$36:$B$40,0)=Counta($B$36:$B$40),S41/S40,S41/S40),"--") -> -- | U56: =iferror(if(match($B$40,$B$36:$B$40,0)=Counta($B$36:$B$40),U41/U40,U41/U40),"--") -> -- | W56: =iferror(if(match($B$40,$B$36:$B$40,0)=Counta($B$36:$B$40),W41/W40,W41/W40),"--") -> -- | Y56: =iferror(if(match($B$40,$B$36:$B$40,0)=Counta($B$36:$B$40),Y41/Y40,Y41/Y40),"--") -> -- | AA56: =iferror(if(match($B$40,$B$36:$B$40,0)=Counta($B$36:$B$40),AA41/AA40,AA41/AA40),"--") -> -- | AC56: =iferror(if(match($B$40,$B$36:$B$40,0)=Counta($B$36:$B$40),AC41/AC40,AC41/AC40),"--") -> -- | AE56: =iferror(if(match($B$40,$B$36:$B$40,0)=Counta($B$36:$B$40),AE41/AE40,AE41/AE40),"--") -> -- | AG56: =iferror(if(match($B$40,$B$36:$B$40,0)=Counta($B$36:$B$40),AG41/AG40,AG41/AG40),"--") -> -- | AI56: =iferror(if(match($B$40,$B$36:$B$40,0)=Counta($B$36:$B$40),AI41/AI40,AI41/AI40),"--") -> -- | AK56: =iferror(if(match($B$40,$B$36:$B$40,0)=Counta($B$36:$B$40),AK41/AK40,AK41/AK40),"--") -> -- | AM56: =iferror(if(match($B$40,$B$36:$B$40,0)=Counta($B$36:$B$40),AM41/AM40,AM41/AM40),"--") -> -- | AO56: =iferror(if(match($B$40,$B$36:$B$40,0)=Counta($B$36:$B$40),AO41/AO40,AO41/AO40),"--") -> -- | AQ56: =iferror(if(match($B$40,$B$36:$B$40,0)=Counta($B$36:$B$40),AQ41/AQ40,AQ41/AQ40),"--") -> -- | AS56: =iferror(if(match($B$40,$B$36:$B$40,0)=Counta($B$36:$B$40),AS41/AS40,AS41/AS40),"--") -> -- | AU56: =iferror(if(match($B$40,$B$36:$B$40,0)=Counta($B$36:$B$40),AU41/AU40,AU41/AU40),"--") -> -- | AW56: =iferror(if(match($B$40,$B$36:$B$40,0)=Counta($B$36:$B$40),AW41/AW40,AW41/AW40),"--") -> -- | AY56: =iferror(if(match($B$40,$B$36:$B$40,0)=Counta($B$36:$B$40),AY41/AY40,AY41/AY40),"--") -> -- | BA56: =iferror(if(match($B$40,$B$36:$B$40,0)=Counta($B$36:$B$40),BA41/BA40,BA41/BA40),"--") -> -- | BC56: =iferror(if(match($B$40,$B$36:$B$40,0)=Counta($B$36:$B$40),BC41/BC40,BC41/BC40),"--") -> -- | BE56: =iferror(if(match($B$40,$B$36:$B$40,0)=Counta($B$36:$B$40),BE41/BE40,BE41/BE40),"--") -> -- | BG56: =iferror(if(match($B$40,$B$36:$B$40,0)=Counta($B$36:$B$40),BG41/BG40,BG41/BG40),"--") -> -- | BI56: =iferror(if(match($B$40,$B$36:$B$40,0)=Counta($B$36:$B$40),BI41/BI40,BI41/BI40),"--") -> -- | BK56: =iferror(if(match($B$40,$B$36:$B$40,0)=Counta($B$36:$B$40),BK41/BK40,BK41/BK40),"--") -> --
B57: =LEFT(B36,LEN(B36)-1)&" > "&LEFT(B41,LEN(B41)-1) -> Form Fill > Customer | E57: =iferror(E41/E36,"--") -> 0.028220859 | G57: =iferror(if(isblank(G41),"--",G41/G36),"--") -> 0 | I57: =iferror(if(isblank(I41),"--",I41/I36),"--") -> 0 | K57: =iferror(if(isblank(K41),"--",K41/K36),"--") -> 0 | M57: =iferror(if(isblank(M41),"--",M41/M36),"--") -> 0 | O57: =iferror(if(isblank(O41),"--",O41/O36),"--") -> -- | Q57: =iferror(if(isblank(Q41),"--",Q41/Q36),"--") -> 0 | S57: =iferror(if(isblank(S41),"--",S41/S36),"--") -> 0 | U57: =iferror(if(isblank(U41),"--",U41/U36),"--") -> 0 | W57: =iferror(if(isblank(W41),"--",W41/W36),"--") -> 0 | Y57: =iferror(if(isblank(Y41),"--",Y41/Y36),"--") -> 0 | AA57: =iferror(if(isblank(AA41),"--",AA41/AA36),"--") -> 0.083333333 | AC57: =iferror(if(isblank(AC41),"--",AC41/AC36),"--") -> -- | AE57: =iferror(if(isblank(AE41),"--",AE41/AE36),"--") -> -- | AG57: =iferror(if(isblank(AG41),"--",AG41/AG36),"--") -> -- | AI57: =iferror(if(isblank(AI41),"--",AI41/AI36),"--") -> 0 | AK57: =iferror(if(isblank(AK41),"--",AK41/AK36),"--") -> -- | AM57: =iferror(if(isblank(AM41),"--",AM41/AM36),"--") -> 0.030456853 | AO57: =iferror(if(isblank(AO41),"--",AO41/AO36),"--") -> 0 | AQ57: =iferror(if(isblank(AQ41),"--",AQ41/AQ36),"--") -> 0 | AS57: =iferror(if(isblank(AS41),"--",AS41/AS36),"--") -> 0.049180328 | AU57: =iferror(if(isblank(AU41),"--",AU41/AU36),"--") -> -- | AW57: =iferror(if(isblank(AW41),"--",AW41/AW36),"--") -> 0 | AY57: =iferror(if(isblank(AY41),"--",AY41/AY36),"--") -> -- | BA57: =iferror(if(isblank(BA41),"--",BA41/BA36),"--") -> 0 | BC57: =iferror(if(isblank(BC41),"--",BC41/BC36),"--") -> 0 | BE57: =iferror(if(isblank(BE41),"--",BE41/BE36),"--") -> 0 | BG57: =iferror(if(isblank(BG41),"--",BG41/BG36),"--") -> -- | BI57: =iferror(if(isblank(BI41),"--",BI41/BI36),"--") -> 0 | BK57: =iferror(if(isblank(BK41),"--",BK41/BK36),"--") -> 0.092198582
F62: =IFERROR(__xludf.DUMMYFUNCTION("FILTER(B36:B41,NOT(ISBLANK(B36:B41)))"),"Form Fills") -> Form Fills | G62: =if(H62="","",(max($H$62:$H$67)-H62)/2) -> 0 | H62: =ifna(VLOOKUP(F62,$B$36:$F$41,4,false),"") -> 815 | I62: =IFERROR(__xludf.DUMMYFUNCTION("FILTER(B52:B56,NOT(B52:B56=""--""))"),"Form Fill > Intro Held") -> Form Fill > Intro Held | J62: =ifna(VLOOKUP(I62,$B$52:$F$56,4,false),"") -> 0.52760736
F63: =IFERROR(__xludf.DUMMYFUNCTION("""COMPUTED_VALUE"""),"Intro Held ") -> Intro Held | G63: =if(H63="","",(max($H$62:$H$67)-H63)/2) -> 192.5 | H63: =ifna(VLOOKUP(F63,$B$36:$F$41,4,false),"") -> 430 | I63: =IFERROR(__xludf.DUMMYFUNCTION("""COMPUTED_VALUE"""),"Intro Held > Strat Call Held") -> Intro Held > Strat Call Held | J63: =ifna(VLOOKUP(I63,$B$52:$F$56,4,false),"") -> 0.40232558
F64: =IFERROR(__xludf.DUMMYFUNCTION("""COMPUTED_VALUE"""),"Strat Call Held ") -> Strat Call Held | G64: =if(H64="","",(max($H$62:$H$67)-H64)/2) -> 321 | H64: =ifna(VLOOKUP(F64,$B$36:$F$41,4,false),"") -> 173 | I64: =IFERROR(__xludf.DUMMYFUNCTION("""COMPUTED_VALUE"""),"Strat Call Held > Proposal") -> Strat Call Held > Proposal | J64: =ifna(VLOOKUP(I64,$B$52:$F$56,4,false),"") -> 0.70520231
F65: =IFERROR(__xludf.DUMMYFUNCTION("""COMPUTED_VALUE"""),"Proposals") -> Proposals | G65: =if(H65="","",(max($H$62:$H$67)-H65)/2) -> 346.5 | H65: =ifna(VLOOKUP(F65,$B$36:$F$41,4,false),"") -> 122 | I65: =IFERROR(__xludf.DUMMYFUNCTION("""COMPUTED_VALUE"""),"Proposal > Customer") -> Proposal > Customer | J65: =ifna(VLOOKUP(I65,$B$52:$F$56,4,false),"") -> 0.18852459
F66: =IFERROR(__xludf.DUMMYFUNCTION("""COMPUTED_VALUE"""),"Customers") -> Customers | G66: =if(H66="","",(max($H$62:$H$67)-H66)/2) -> 396 | H66: =ifna(VLOOKUP(F66,$B$36:$F$41,4,false),"") -> 23 | J66: =ifna(VLOOKUP(I66,$B$52:$F$56,4,false),"")
G67: =if(H67="","",(max($H$62:$H$67)-H67)/2) | H67: =ifna(VLOOKUP(F67,$B$36:$F$41,4,false),"") | J67: =ifna(VLOOKUP(I67,$B$52:$F$56,4,false),"")

Sheet Projections (w data)
B2: GET STARTED
B3: Select the goal type in cell D12, then enter the goal value in cell D15. | P3: RESOURCES:
B4: As you enter values, this sheet will automatically update to show a summary of projections using current conversion rates and cost-per's. | M4: Client Benchmark Library (Directive Data)
M5: Industry Benchmarks (3rd Party Data)
B6: NOTE | M6: WHAT: Defining Client NSMs (Notion)
B7: Only edit highlighted cells. | E7: Try not to alter cells that contain a formula.
B11: Goal Setting | J11: Projections
B12: Goal Type: | D12: Customers | L12: Goal | N12: Prior | P12: %diff
J13: =IFERROR(__xludf.DUMMYFUNCTION("filter('LTVCAC Analysis'!B37:B42,Not(ISBLANK('LTVCAC Analysis'!B37:B42)))"),"Form Fills") -> Form Fills | L13: =if(isblank(D18),,iferror(if($D$12="LTV:CAC",if(J13=$O$45,N27/D18,L14/(vlookup(J13,$D$40:$G$45,4,false))),D18/vlookup(J13,D40:I45,6,false)),)) -> 689 | N13: =iferror(VLOOKUP(J13,$D$40:$E$45,2,false),) -> 689 | P13: =if(isblank(L13),,IFERROR((L13-N13)/N13,)) -> 0
F14: ="Prior "&D12 -> Prior Customers | H14: % diff | J14: =IFERROR(__xludf.DUMMYFUNCTION("""COMPUTED_VALUE"""),"Intro Held ") -> Intro Held | L14: =if(isblank(D18),,iferror(if($D$12="LTV:CAC",if(J14=$O$45,N27/D18,L15/vlookup(J14,D40:G44,4,false)),D18/vlookup(J14,D40:I45,6,false)),)) -> 373 | N14: =iferror(VLOOKUP(J14,$D$40:$E$45,2,false),) -> 373 | P14: =if(isblank(L14),,iferror((L14-N14)/N14,)) -> 0
B15: =D12&" Goal" -> Customers Goal | D15: 23 | F15: =if(D12="LTV:CAC",L41,if(D12=B45,E45,if(D12=B44,E44,if(D12=B43,E43,if(D12=B42,E42,if(D12=B41,E41,if(D12=D40,E40,))))))) -> 23 | H15: =if(isblank(D15),,iferror(((D15-F15)/F15),)) -> 0 | J15: =IFERROR(__xludf.DUMMYFUNCTION("""COMPUTED_VALUE"""),"Strat Call Held ") -> Strat Call Held | L15: =if(isblank(D18),,iferror(if($D$12="LTV:CAC",if(J15=$O$45,N27/D18,L16/vlookup(J15,D40:G44,4,false)),D18/vlookup(J15,D40:I45,6,false)),)) -> 156 | N15: =iferror(VLOOKUP(J15,$D$40:$E$45,2,false),) -> 156 | P15: =if(isblank(L15),,iferror((L15-N15)/N15,)) -> 0
J16: =IFERROR(__xludf.DUMMYFUNCTION("""COMPUTED_VALUE"""),"Proposals") -> Proposals | L16: =if(isblank(D18),,iferror(if($D$12="LTV:CAC",if(J16=$O$45,N27/D18,L17/vlookup(J16,D40:G44,4,false)),D18/vlookup(J16,D40:I45,6,false)),)) -> 104 | N16: =iferror(VLOOKUP(J16,$D$40:$E$45,2,false),) -> 104 | P16: =if(isblank(L16),,iferror((L16-N16)/N16,)) -> 0
F17: =if(D12="LTV:CAC","Prior CAC","Prior Spend") -> Prior Spend | H17: % diff | J17: =IFERROR(__xludf.DUMMYFUNCTION("""COMPUTED_VALUE"""),"Customers") -> Customers | L17: =if(isblank(D18),,iferror(if($D$12="LTV:CAC",(if(J17=$O$45,N27/D18,L18/vlookup(J17,D40:G45,4,false))),D18/vlookup(J17,D40:I45,6,false)),)) -> 23 | N17: =iferror(VLOOKUP(J17,$D$40:$E$45,2,false),) -> 23 | P17: =if(isblank(L17),,iferror((L17-N17)/N17,)) -> 0
B18: =if(D12="LTV:CAC","CAC Target","Spend Needed") -> Spend Needed | D18: =if(isblank(D15),,if(D12="LTV:CAC",$L$42/D15,if(D12=B45,D15*I45,if(D12=B44,D15*I44,if(D12=B43,D15*I43,if(D12=B42,D15*I42,if(D12=B41,D15*I41,if(D12=D40,D15*I40,)))))))) -> 951168.5 | F18: =if(D12="LTV:CAC",(VLOOKUP(P45,H40:I45,2,false)),N27) -> 951168.5 | H18: =if(isblank(D18),,iferror(((D18-F18)/F18),)) -> 0 | L18: =if(isblank(D18),,iferror(if($D$12="LTV:CAC",if(J18=$O$45,N27/D18,""),D18/vlookup(J18,D40:I45,6,false)),)) | N18: =iferror(VLOOKUP(J18,$D$40:$E$45,2,false),) | P18: =if(isblank(L18),,iferror((L18-N18)/N18,))
B20: To reach your goal, you need to: | J20: Est. Net Bookings | L20: =if(VLOOKUP($O$45,J13:M18,3,false)="","--",if(istext(N29),"No LTV",(VLOOKUP($O$45,J13:M18,3,false)*N29))) -> 1074809.9 | N20: =N30 -> 1317030 | P20: =iferror(((L20-N20)/N20),) -> -0.18391388
B21: =if(isblank(D18),,"Achieve the $"&round(D18,0)&" "&B18&" by adjusting the "&F17&" by "&round((H18*100),2)&"%.") -> Achieve the $951169 Spend Needed by adjusting the Prior Spend by 0%. | J21: Net Return | L21: =iferror(L20-D18,"--") -> 123641.4 | N21: =N31 -> 1012798.2 | P21: =iferror(((L21-N21)/N21),) -> -0.87792098
B26: ='LTVCAC Analysis'!B28 -> Sept-Oct Actuals
B27: =F40 -> Form Fill > Intro Held | D27: =iferror(VLOOKUP(B27,$F$40:$G$45,2,false),) -> 0.5413643 | G27: =H40 -> Cost-per-Form Fill | I27: =iferror(VLOOKUP(G27,$H$40:$I$44,2,false),) -> 1380.5058 | L27: ='LTVCAC Analysis'!B36 -> Total Spend | N27: =L40 -> 951168.5
B28: =F41 -> Intro Held > Strat Call Held | D28: =iferror(VLOOKUP(B28,$F$40:$G$45,2,false),) -> 0.41823056 | G28: =H41 -> Cost-per-Intro Held | I28: =iferror(VLOOKUP(G28,$H$40:$I$44,2,false),) -> 2550.0496 | L28: ='LTVCAC Analysis'!B31 -> LTV:CAC Ratio | N28: =L41 -> 1.13
B29: =F42 -> Strat Call Held > Proposal | D29: =iferror(VLOOKUP(B29,$F$40:$G$45,2,false),) -> 0.66666667 | G29: =H42 -> Cost-per-Strat Call Held | I29: =iferror(VLOOKUP(G29,$H$40:$I$44,2,false),) -> 6097.234 | L29: ='LTVCAC Analysis'!B46 -> Lifetime Value (LTV) | N29: =L42 -> 46730.865
B30: =F43 -> Proposal > Customer | D30: =iferror(VLOOKUP(B30,$F$40:$G$45,2,false),) -> 0.22115385 | G30: =H43 -> Cost-per-Proposal | I30: =iferror(VLOOKUP(G30,$H$40:$I$44,2,false),) -> 9145.851 | L30: Est. Net Bookings | N30: =L43 -> 1317030
B31: =F44 -> Form Fill > Customer | D31: =iferror(VLOOKUP(B31,$F$40:$G$45,2,false),) -> 0.033381713 | G31: =H44 -> Cost-per-Customer | I31: =iferror(VLOOKUP(G31,$H$40:$I$44,2,false),) -> 41355.152 | L31: Net Return | N31: =L44 -> 1012798.2
B32: =F45 | D32: =iferror(VLOOKUP(B32,$F$40:$G$45,2,false),) | G32: =H45 | I32: =iferror(VLOOKUP(G32,$H$40:$I$44,2,false),)
B39: Goal Type: | D39: stages | F39: stage cvr | H39: $/stage
B40: =IFERROR(__xludf.DUMMYFUNCTION("filter(D40:D46,Not(ISBLANK(D40:D46)))"),"Form Fills") -> Form Fills | D40: =IFERROR(__xludf.DUMMYFUNCTION("filter('LTVCAC Analysis'!B37:B42,Not(ISBLANK('LTVCAC Analysis'!B37:B42)))"),"Form Fills") -> Form Fills | E40: =iferror(VLOOKUP(D40,'LTVCAC Analysis'!$B$31:$F$42,4,false),) -> 689 | F40: =IFERROR(__xludf.DUMMYFUNCTION("filter('LTVCAC Analysis'!$B$55:$B$60,NOT('LTVCAC Analysis'!B55:B60=""--""))"),"Form Fill > Intro Held") -> Form Fill > Intro Held | G40: =iferror(VLOOKUP(F40,'LTVCAC Analysis'!$B$55:$F$60,4,false),) -> 0.5413643 | H40: =IFERROR(__xludf.DUMMYFUNCTION("FILTER('LTVCAC Analysis'!B49:B54,NOT('LTVCAC Analysis'!B49:B54=""--""))"),"Cost-per-Form Fill") -> Cost-per-Form Fill | I40: =iferror(VLOOKUP(H40,'LTVCAC Analysis'!$B$49:$F$54,4,false),) -> 1380.5058 | K40: Total Spend | L40: ='LTVCAC Analysis'!C22 -> 951168.5 | N40: 1 | O40: ='LTVCAC Analysis'!B37 -> Form Fills | P40: ='LTVCAC Analysis'!B49 -> Cost-per-Form Fill
B41: =IFERROR(__xludf.DUMMYFUNCTION("""COMPUTED_VALUE"""),"Intro Held ") -> Intro Held | D41: =IFERROR(__xludf.DUMMYFUNCTION("""COMPUTED_VALUE"""),"Intro Held ") -> Intro Held | E41: =iferror(VLOOKUP(D41,'LTVCAC Analysis'!$B$31:$F$42,4,false),) -> 373 | F41: =IFERROR(__xludf.DUMMYFUNCTION("""COMPUTED_VALUE"""),"Intro Held > Strat Call Held") -> Intro Held > Strat Call Held | G41: =iferror(VLOOKUP(F41,'LTVCAC Analysis'!$B$55:$F$60,4,false),) -> 0.41823056 | H41: =IFERROR(__xludf.DUMMYFUNCTION("""COMPUTED_VALUE"""),"Cost-per-Intro Held") -> Cost-per-Intro Held | I41: =iferror(VLOOKUP(H41,'LTVCAC Analysis'!$B$49:$F$54,4,false),) -> 2550.0496 | K41: LTV:CAC Ratio | L41: ='LTVCAC Analysis'!F25 -> 1.13 | N41: 2 | O41: ='LTVCAC Analysis'!B38 -> Intro Held | P41: ='LTVCAC Analysis'!B50 -> Cost-per-Intro Held
B42: =IFERROR(__xludf.DUMMYFUNCTION("""COMPUTED_VALUE"""),"Strat Call Held ") -> Strat Call Held | D42: =IFERROR(__xludf.DUMMYFUNCTION("""COMPUTED_VALUE"""),"Strat Call Held ") -> Strat Call Held | E42: =iferror(VLOOKUP(D42,'LTVCAC Analysis'!$B$31:$F$42,4,false),) -> 156 | F42: =IFERROR(__xludf.DUMMYFUNCTION("""COMPUTED_VALUE"""),"Strat Call Held > Proposal") -> Strat Call Held > Proposal | G42: =iferror(VLOOKUP(F42,'LTVCAC Analysis'!$B$55:$F$60,4,false),) -> 0.66666667 | H42: =IFERROR(__xludf.DUMMYFUNCTION("""COMPUTED_VALUE"""),"Cost-per-Strat Call Held") -> Cost-per-Strat Call Held | I42: =iferror(VLOOKUP(H42,'LTVCAC Analysis'!$B$49:$F$54,4,false),) -> 6097.234 | K42: Lifetime Value (LTV) | L42: =if(istext('LTVCAC Analysis'!E46),"No LTV",'LTVCAC Analysis'!E46) -> 46730.865 | N42: 3 | O42: ='LTVCAC Analysis'!B39 -> Strat Call Held | P42: ='LTVCAC Analysis'!B51 -> Cost-per-Strat Call Held
B43: =IFERROR(__xludf.DUMMYFUNCTION("""COMPUTED_VALUE"""),"Proposals") -> Proposals | D43: =IFERROR(__xludf.DUMMYFUNCTION("""COMPUTED_VALUE"""),"Proposals") -> Proposals | E43: =iferror(VLOOKUP(D43,'LTVCAC Analysis'!$B$31:$F$42,4,false),) -> 104 | F43: =IFERROR(__xludf.DUMMYFUNCTION("""COMPUTED_VALUE"""),"Proposal > Customer") -> Proposal > Customer | G43: =iferror(VLOOKUP(F43,'LTVCAC Analysis'!$B$55:$F$60,4,false),) -> 0.22115385 | H43: =IFERROR(__xludf.DUMMYFUNCTION("""COMPUTED_VALUE"""),"Cost-per-Proposal") -> Cost-per-Proposal | I43: =iferror(VLOOKUP(H43,'LTVCAC Analysis'!$B$49:$F$54,4,false),) -> 9145.851 | K43: Est. Net Bookings | L43: ='LTVCAC Analysis'!F22 -> 1317030 | N43: 4 | O43: ='LTVCAC Analysis'!B40 -> Proposals | P43: ='LTVCAC Analysis'!B52 -> Cost-per-Proposal
B44: =IFERROR(__xludf.DUMMYFUNCTION("""COMPUTED_VALUE"""),"Customers") -> Customers | D44: =IFERROR(__xludf.DUMMYFUNCTION("""COMPUTED_VALUE"""),"Customers") -> Customers | E44: =iferror(VLOOKUP(D44,'LTVCAC Analysis'!$B$31:$F$42,4,false),) -> 23 | F44: =IFERROR(__xludf.DUMMYFUNCTION("""COMPUTED_VALUE"""),"Form Fill > Customer") -> Form Fill > Customer | G44: =iferror(VLOOKUP(F44,'LTVCAC Analysis'!$B$55:$F$60,4,false),) -> 0.033381713 | H44: =IFERROR(__xludf.DUMMYFUNCTION("""COMPUTED_VALUE"""),"Cost-per-Customer") -> Cost-per-Customer | I44: =iferror(VLOOKUP(H44,'LTVCAC Analysis'!$B$49:$F$54,4,false),) -> 41355.152 | K44: Net Return | L44: ='LTVCAC Analysis'!F26 -> 1012798.2 | N44: 5 | O44: ='LTVCAC Analysis'!B41 | P44: ='LTVCAC Analysis'!B53 -> --
B45: =IFERROR(__xludf.DUMMYFUNCTION("""COMPUTED_VALUE"""),"LTV:CAC") -> LTV:CAC | E45: =iferror(VLOOKUP(D45,'LTVCAC Analysis'!$B$31:$F$42,4,false),) | G45: =iferror(VLOOKUP(F45,'LTVCAC Analysis'!$B$55:$F$60,4,false),) | I45: =iferror(VLOOKUP(H45,'LTVCAC Analysis'!$B$49:$F$54,4,false),) | N45: 6 | O45: ='LTVCAC Analysis'!B42 -> Customers | P45: ='LTVCAC Analysis'!B54 -> Cost-per-Customer
D46: =if(istext(L41),,"LTV:CAC") -> LTV:CAC

Sheet Projections (no data)
B2: GET STARTED
B3: Start with entering in data in the Lead Stages, Conversion Rates, and LTV tables in the "Custom Inputs" section at the bottom. Next, select the goal type in cell G13 and the goal value in cell D15, then enter in the Total Budget in cells D17. | P3: RESOURCES:
L4: Client Benchmark Library (Directive Data)
B5: As you enter values, this sheet will automatically update to show a summary of projections using the conversion rates inputted. | L5: Industry Benchmarks (3rd Party Data)
L6: WHAT: Defining Client NSMs (Notion)
B7: NOTE
B8: Only edit highlighted cells. | E8: Try not to alter cells that contain a formula.
F11: Re-select goal type ▼
B12: Goal Setting | K12: Projections
E13: Goal Type: | G13: Customers
B15: =G13&" Goal" -> Customers Goal | D15: 23 | M15: Goal | O15: Cost-per
B17: Quarterly Budget | D17: 200000 | K17: =IFERROR(__xludf.DUMMYFUNCTION("filter(C39:C44,Not(ISBLANK(C39:C44)))"),"Form Fills") -> Form Fills | M17: =if(counta(C39:C43)=0,"Enter Stages", ifna(round(if($G$13="LTV:CAC",if(K17=C44,$D$17/$D$18,M18/VLOOKUP(K17,$C$39:$I$44,6,false)), if($G$13=K17,$D$15,if(MATCH(K17,$C$39:$C$44,0)<MATCH($G$13,$C$39:$C$44,0),(M18/VLOOKUP(K17,$C$39:$I$44,6,false)),M15*VLOOKUP(K15,$C$39:$I$44,6,false)))),0),"")) -> 575 | O17: =iferror($D$17/M17,"") -> 347.82609
B18: =if(G13="LTV:CAC","Cost-per-Customer Needed","Cost-per-"&LEFT(G13,LEN(G13)-1)&" Needed") -> Cost-per-Customer Needed | D18: =if(or(isblank(D17),isblank(D15)),,if(G13="LTV:CAC",iferror(O42/D15,O42),D17/D15)) -> 8695.6522 | K18: =IFERROR(__xludf.DUMMYFUNCTION("""COMPUTED_VALUE"""),"Intro Calls Held ") -> Intro Calls Held | M18: =ifna(round(if($G$13="LTV:CAC",if(K18=C44,$D$17/$D$18,M19/VLOOKUP(K18,$C$39:$I$44,6,false)), if($G$13=K18,$D$15,if(MATCH(K18,$C$39:$C$44,0)<MATCH($G$13,$C$39:$C$44,0),(M19/VLOOKUP(K18,$C$39:$I$44,6,false)),M17*VLOOKUP(K17,$C$39:$I$44,6,false)))),0),"") -> 374 | O18: =iferror($D$17/M18,"") -> 534.75936
K19: =IFERROR(__xludf.DUMMYFUNCTION("""COMPUTED_VALUE"""),"Strat Calls") -> Strat Calls | M19: =ifna(round(if($G$13="LTV:CAC",if(K19=C44,$D$17/$D$18,M20/VLOOKUP(K19,$C$39:$I$44,6,false)), if($G$13=K19,$D$15,if(MATCH(K19,$C$39:$C$44,0)<MATCH($G$13,$C$39:$C$44,0),(M20/VLOOKUP(K19,$C$39:$I$44,6,false)),M18*VLOOKUP(K18,$C$39:$I$44,6,false)))),0),"") -> 157 | O19: =iferror($D$17/M19,"") -> 1273.8854
B20: ✨ Reality Check ✨ | K20: =IFERROR(__xludf.DUMMYFUNCTION("""COMPUTED_VALUE"""),"Proposals") -> Proposals | M20: =ifna(round(if($G$13="LTV:CAC",if(K20=C44,$D$17/$D$18,M21/VLOOKUP(K20,$C$39:$I$44,6,false)), if($G$13=K20,$D$15,if(MATCH(K20,$C$39:$C$44,0)<MATCH($G$13,$C$39:$C$44,0),(M21/VLOOKUP(K20,$C$39:$I$44,6,false)),M19*VLOOKUP(K19,$C$39:$I$44,6,false)))),0),"") -> 105 | O20: =iferror($D$17/M20,"") -> 1904.7619
K21: =IFERROR(__xludf.DUMMYFUNCTION("""COMPUTED_VALUE"""),"Customers") -> Customers | M21: =ifna(round(if($G$13="LTV:CAC",if(K21=C44,$D$17/$D$18,M22/VLOOKUP(K21,$C$39:$I$44,6,false)), if($G$13=K21,$D$15,if(MATCH(K21,$C$39:$C$44,0)<MATCH($G$13,$C$39:$C$44,0),(M22/VLOOKUP(K21,$C$39:$I$44,6,false)),M20*VLOOKUP(K20,$C$39:$I$44,6,false)))),0),"") -> 23 | O21: =iferror($D$17/M21,"") -> 8695.6522
C22: 1. Start off with entering the Target CTR and CVR. | M22: =ifna(round(if($G$13="LTV:CAC",if(K22=C44,$D$17/$D$18,M23/VLOOKUP(K22,$C$39:$I$44,6,false)), if($G$13=K22,$D$15,if(MATCH(K22,$C$39:$C$44,0)<MATCH($G$13,$C$39:$C$44,0),(M23/VLOOKUP(K22,$C$39:$I$44,6,false)),M21*VLOOKUP(K21,$C$39:$I$44,6,false)))),0),"") | O22: =iferror($D$17/M22,"")
C23: Ex. I expect my ads will have a X% CTR and my LP to have a X% CVR.
C24: Ad Click-through Rate: | D24: 0.025 | F24: What is your target CTR? | K24: LTV:CAC Ratio | M24: =if(ISTEXT(O42),"No LTV",Round(O42/VLOOKUP(C44,K17:P22,5,false),2)) -> 10.97
C25: Landing Page Conv. Rate: | D25: 0.05 | F25: What is your target LP CVR? | K25: Est. Bookings | M25: =if(istext(O42),"No LTV",(VLOOKUP(C44,$K$17:$N$22,3,false))*O42) -> 2194851.4
K26: Net Return | M26: =if(istext(O42),"No LTV",(VLOOKUP(C44,$K$17:$N$22,3,false)*O42)-D17) -> 1994851.4
C27: 2. Compare the Impr. and Clicks needed with the platform estimates.
C28: Ex. I need 100k impr, but LinkedIn is forecasting only 50K with my audience size.
C29: Ex. I need 30k clicks, but Google Ads is forecasting only 10K with my search volume.
C30: Impressions Needed: | D30: =if(D31="","",if(isblank(D24),"Enter CTR",if(isblank(D25),"Enter CVR",D31/D24))) -> 460000 | F30: Is my TAM large enough for this?
C31: Clicks Needed: | D31: =iferror(if(isblank(D25),"Enter CVR",M17/D25),"") -> 11500 | F31: Is my audience/keyword volume big enough?
C32: Cost per Click Needed: | D32: =iferror(D17/D31,"") -> 17.391304 | F32: Is this realistic based on my channel mix?
B35: Custom Inputs | D35: 1. Adjust the stages to Client's stages. Use Client's overall stage conversion rates; if they don't have that use the Benchmark Library.
D36: 2. Enter Client's overall GM%, Customer Lifespan, & AOV to get LTV; if they don't have that leave blank & don't use LTV:CAC as goal.
B38: Stages | F38: Conversion Rates | K38: Lifetime Value (LTV)
B39: First | C39: Form Fills | F39: =iferror(if(match(C39,$C$39:$C$43,0)=Counta($C$39:$C$43),LEFT(C39,LEN(C39)-1)&" > "&LEFT($C$44,LEN($C$44)-1),LEFT(C39,LEN(C39)-1)&" > "&LEFT(C40,LEN(C40)-1)),"--") -> Form Fill > Intro Calls Held | H39: 0.65 | K39: Gross Margin (%) | O39: 0.52
B40: 2nd | C40: Intro Calls Held | F40: =iferror(if(match(C40,$C$39:$C$43,0)=Counta($C$39:$C$43),LEFT(C40,LEN(C40)-1)&" > "&LEFT($C$44,LEN($C$44)-1),LEFT(C40,LEN(C40)-1)&" > "&LEFT(C41,LEN(C41)-1)),"--") -> Intro Calls Held > Strat Call | H40: 0.42 | K40: Lifespan of Customer (months) | O40: 12
B41: 3rd | C41: Strat Calls | F41: =iferror(if(match(C41,$C$39:$C$43,0)=Counta($C$39:$C$43),LEFT(C41,LEN(C41)-1)&" > "&LEFT($C$44,LEN($C$44)-1),LEFT(C41,LEN(C41)-1)&" > "&LEFT(C42,LEN(C42)-1)),"--") -> Strat Call > Proposal | H41: 0.67 | K41: Monthly Avg. Order Value | O41: 15293
B42: 4th | C42: Proposals | F42: =iferror(if(match(C42,$C$39:$C$43,0)=Counta($C$39:$C$43),LEFT(C42,LEN(C42)-1)&" > "&LEFT($C$44,LEN($C$44)-1),LEFT(C42,LEN(C42)-1)&" > "&LEFT(C43,LEN(C43)-1)),"--") -> Proposal > Customer | H42: 0.22 | K42: Lifetime Value (LTV) | O42: =if(isblank(O39),"Enter GM%",if(isblank(O40),"Enter Lifespan",if(ISBLANK(O41),"Enter AOV",O39*O40*O41))) -> 95428.32
B43: 5th | F43: =iferror(if(match(C43,$C$39:$C$43,0)=Counta($C$39:$C$43),LEFT(C43,LEN(C43)-1)&" > "&LEFT($C$44,LEN($C$44)-1),LEFT(C43,LEN(C43)-1)&" > "&LEFT(C44,LEN(C44)-1)),"--") -> --
B44: Last | C44: Customers
B45: Note: Use the plural form of the stage (ex. Leads, not Lead)
B49: Goal Type:
B50: =IFERROR(__xludf.DUMMYFUNCTION("filter(C50:C56,not(isblank(C50:C56)))"),"Form Fills") -> Form Fills | C50: =IFERROR(__xludf.DUMMYFUNCTION("filter(C39:C44,Not(ISBLANK(C39:C44)))"),"Form Fills") -> Form Fills
B51: =IFERROR(__xludf.DUMMYFUNCTION("""COMPUTED_VALUE"""),"Intro Calls Held ") -> Intro Calls Held | C51: =IFERROR(__xludf.DUMMYFUNCTION("""COMPUTED_VALUE"""),"Intro Calls Held ") -> Intro Calls Held
B52: =IFERROR(__xludf.DUMMYFUNCTION("""COMPUTED_VALUE"""),"Strat Calls") -> Strat Calls | C52: =IFERROR(__xludf.DUMMYFUNCTION("""COMPUTED_VALUE"""),"Strat Calls") -> Strat Calls
B53: =IFERROR(__xludf.DUMMYFUNCTION("""COMPUTED_VALUE"""),"Proposals") -> Proposals | C53: =IFERROR(__xludf.DUMMYFUNCTION("""COMPUTED_VALUE"""),"Proposals") -> Proposals
B54: =IFERROR(__xludf.DUMMYFUNCTION("""COMPUTED_VALUE"""),"Customers") -> Customers | C54: =IFERROR(__xludf.DUMMYFUNCTION("""COMPUTED_VALUE"""),"Customers") -> Customers
B55: =IFERROR(__xludf.DUMMYFUNCTION("""COMPUTED_VALUE"""),"LTV:CAC") -> LTV:CAC
C56: =if(istext(O42),,"LTV:CAC") -> LTV:CAC

Sheet Nov22 LTVCAC (Action Date)
B2: GET STARTED | BF2: NOTE
B3: Enter the values needed for calculating LTV in cells T14:T17, then customize your channels and funnel stages in the 'Current Quarter Actuals' table below. | BF3: Only edit highlighted cells.
BF4: Try not to alter cells that contain a formula.
B5: As you enter data in the 'Current Quarter Actuals' tab, this sheet will automatically update to show a summary of the quarter.
B10: Nov Summary
T12: Lifetime Value (LTV) | AC12: Lifetime Value (LTV)
T13: Gross Margin (%) | X13: 0.6 | AC13: Company Gross Margin (%) | AG13: 0.52
D14: =IFERROR(__xludf.DUMMYFUNCTION("iferror(SPARKLINE(C22,{""charttype"",""column"";""ymin"", 0; ""ymax"",MAX(C22:H22);""firstcolor"",""#304458""}),"""")"),"") | F14: =IFERROR(__xludf.DUMMYFUNCTION("iferror(SPARKLINE(F22,{""charttype"",""column"";""ymin"", 0; ""ymax"",MAX(C22:H22);""firstcolor"",""#f46524""}),"""")"),"") | T14: Lifespan of Customer (months) | X14: 12 | AC14: Retention % | AG14: 0.424
T15: Monthly Avg. Order Value | X15: 7522.73 | Z15: =X15*12 -> 90272.76
T16: Channel-level AOV's? | X16: Yes
T17: Lifetime Value (LTV) | X17: =if(X16="No",if(isblank(X13),"Enter GM%",if(isblank(X14),"Enter Lifespan",if(ISBLANK(X15),"Enter AOV",X13*X14*X15))),"See Below") -> See Below
M20: =F65 -> Form Fills | N20: =H65 -> 285 | S20: =IFERROR(__xludf.DUMMYFUNCTION("iferror(SPARKLINE(G65:H65,{""charttype"",""bar"";""max"",MAX($H$65:$H$70);""color1"",""#ebedef"";""color2"",""#073763""}),"""")"),"")
C21: Total Spend | F21: Total Est. Bookings | M21: =F66 -> Intro Held | N21: =H66 -> 134 | S21: =IFERROR(__xludf.DUMMYFUNCTION("iferror(SPARKLINE(G66:H66,{""charttype"",""bar"";""max"",MAX($H$65:$H$70);""color1"",""#ebedef"";""color2"",""#0b5394""}),"""")"),"") | W21: =iferror(if(J65="","","🔽 "&(ROUND(J65,2)*100)&"%"),"--") -> 🔽 47% | X21: =if(I65="","",I65) -> Form Fill > Intro Held
C22: =E36 -> 462566.65 | F22: =E47 -> 504600.26 | M22: =F67 -> Strat Call Held | N22: =H67 -> 45 | S22: =IFERROR(__xludf.DUMMYFUNCTION("iferror(SPARKLINE(G67:H67,{""charttype"",""bar"";""max"",MAX(H65:H70);""color1"",""#ebedef"";""color2"",""#3d85c6""}),"""")"),"") | W22: =iferror(if(J66="","","🔽 "&(ROUND(J66,2)*100)&"%"),"--") -> 🔽 34% | X22: =if(I66="","",I66) -> Intro Held > Strat Call Held
M23: =F68 -> Proposals | N23: =H68 -> 32 | S23: =IFERROR(__xludf.DUMMYFUNCTION("iferror(SPARKLINE(G68:H68,{""charttype"",""bar"";""max"",MAX($H$65:$H$70);""color1"",""#ebedef"";""color2"",""#6fa8dc""}),"""")"),"") | W23: =iferror(if(J67="","","🔽 "&(ROUND(J67,2)*100)&"%"),"--") -> 🔽 71% | X23: =if(I67="","",I67) -> Strat Call Held > Proposal
M24: =F69 -> Customers | N24: =H69 -> 11 | S24: =IFERROR(__xludf.DUMMYFUNCTION("iferror(SPARKLINE(G69:H69,{""charttype"",""bar"";""max"",MAX($H$65:$H$70);""color1"",""#ebedef"";""color2"",""#9fc5e8""}),"""")"),"") | W24: =iferror(if(J68="","","🔽 "&(ROUND(J68,2)*100)&"%"),"--") -> 🔽 34% | X24: =if(I68="","",I68) -> Proposal > Customer
C25: LTV:CAC Ratio | F25: =E31 -> 0.94 | M25: =F70 | N25: =H70 | S25: {=iferror(SPARKLINE(G70:H70,{"charttype","bar";"max",MAX($H$65:$H$70);"color1","#ebedef";"color2","#cfe2f3"}),"")} | W25: =iferror(if(J69="","","🔽 "&(ROUND(J69,2)*100)&"%"),"--") | X25: =if(I69="","",I69)
C26: Net Return | F26: =E48 -> 465626.09
B28: NOVEMBER - FINAL
G29: =sum(G32) -> 1662.15 | I29: =sum(I32:AJ32) -> 23044.72 | AK29: =sum(AK32:AT32) -> 88031.3 | AU29: =sum(AU32:AZ32) -> 29833.94 | BA29: =BA32 -> 14095.62 | BC29: 2650 | BE29: 650 | BI29: =BI32 -> 4218.42
E30: Total | G30: Google - Brand | I30: Google - Non-Brand: Demand Gen | K30: Google - Non-Brand: Marketing | M30: Google - Non-Brand: MOPs | O30: Google - Non-Brand: Paid Media | Q30: Google - Non-Brand: Social | S30: Google - Non-Brand: Creative | U30: Google - Non-Brand: Performance Marketing | W30: Google - Non-Brand: SEO | Y30: Google - Non-Brand: Strategy | AA30: Google - Non-Brand: Video | AC30: Google - YouTube | AE30: Google - Display | AG30: Google - Non-Brand: Events Support | AI30: Google - Non-Brand: RLSA | AK30: LinkedIn - Brand Ads | AM30: LinkedIn - Convo Ads GC | AO30: LinkedIn - Line Specific GC | AQ30: LinkedIn - Strategy GC | AS30: LinkedIn - SPC GC | AU30: Facebook/IG - Brand Ads | AW30: Facebook - SPC GC | AY30: Instagram - SPC GC | BA30: StackAdapt | BC30: Clutch.io | BE30: Manifest | BG30: Twitter - Brand | BI30: TikTok | BK30: Events | BM30: Organic | BO30: Non-Paid Media | BQ30: Total
B31: LTV:CAC Ratio | E31: =if(E36="--","--",if(istext(E46),"No LTV",if(or(isblank(E42),E42=0),0,Round(E46/E54,2)))) -> 0.94 | G31: =if(isblank(G36),"--",if(istext(G46),"No LTV",if(or(isblank(G42),G42=0),0,Round(G46/G54,2)))) -> No LTV | I31: =if(isblank(I36),"--",if(istext(I46),"No LTV",if(or(isblank(I42),I42=0),0,Round(I46/I54,2)))) -> No LTV | K31: =if(isblank(K36),"--",if(istext(K46),"No LTV",if(or(isblank(K42),K42=0),0,Round(K46/K54,2)))) -> No LTV | M31: =if(isblank(M36),"--",if(istext(M46),"No LTV",if(or(isblank(M42),M42=0),0,Round(M46/M54,2)))) -> No LTV | O31: =if(isblank(O36),"--",if(istext(O46),"No LTV",if(or(isblank(O42),O42=0),0,Round(O46/O54,2)))) -> No LTV | Q31: =if(isblank(Q36),"--",if(istext(Q46),"No LTV",if(or(isblank(Q42),Q42=0),0,Round(Q46/Q54,2)))) -> No LTV | S31: =if(isblank(S36),"--",if(istext(S46),"No LTV",if(or(isblank(S42),S42=0),0,Round(S46/S54,2)))) -> No LTV | U31: =if(isblank(U36),"--",if(istext(U46),"No LTV",if(or(isblank(U42),U42=0),0,Round(U46/U54,2)))) -> No LTV | W31: =if(isblank(W36),"--",if(istext(W46),"No LTV",if(or(isblank(W42),W42=0),0,Round(W46/W54,2)))) -> No LTV | Y31: =if(isblank(Y36),"--",if(istext(Y46),"No LTV",if(or(isblank(Y42),Y42=0),0,Round(Y46/Y54,2)))) -> No LTV | AA31: =if(isblank(AA36),"--",if(istext(AA46),"No LTV",if(or(isblank(AA42),AA42=0),0,Round(AA46/AA54,2)))) -> No LTV | AC31: =if(isblank(AC36),"--",if(istext(AC46),"No LTV",if(or(isblank(AC42),AC42=0),0,Round(AC46/AC54,2)))) -> No LTV | AE31: =if(isblank(AE36),"--",if(istext(AE46),"No LTV",if(or(isblank(AE42),AE42=0),0,Round(AE46/AE54,2)))) -> No LTV | AG31: =if(isblank(AG36),"--",if(istext(AG46),"No LTV",if(or(isblank(AG42),AG42=0),0,Round(AG46/AG54,2)))) -> No LTV | AI31: =if(isblank(AI36),"--",if(istext(AI46),"No LTV",if(or(isblank(AI42),AI42=0),0,Round(AI46/AI54,2)))) -> No LTV | AK31: =if(isblank(AK36),"--",if(istext(AK46),"No LTV",if(or(isblank(AK42),AK42=0),0,Round(AK46/AK54,2)))) -> No LTV | AM31: =if(isblank(AM36),"--",if(istext(AM46),"No LTV",if(or(isblank(AM42),AM42=0),0,Round(AM46/AM54,2)))) -> No LTV | AO31: =if(isblank(AO36),"--",if(istext(AO46),"No LTV",if(or(isblank(AO42),AO42=0),0,Round(AO46/AO54,2)))) -> No LTV | AQ31: =if(isblank(AQ36),"--",if(istext(AQ46),"No LTV",if(or(isblank(AQ42),AQ42=0),0,Round(AQ46/AQ54,2)))) -> No LTV | AS31: =if(isblank(AS36),"--",if(istext(AS46),"No LTV",if(or(isblank(AS42),AS42=0),0,Round(AS46/AS54,2)))) -> No LTV | AU31: =if(isblank(AU36),"--",if(istext(AU46),"No LTV",if(or(isblank(AU42),AU42=0),0,Round(AU46/AU54,2)))) -> No LTV | AW31: =if(isblank(AW36),"--",if(istext(AW46),"No LTV",if(or(isblank(AW42),AW42=0),0,Round(AW46/AW54,2)))) -> 1.7 | AY31: =if(isblank(AY36),"--",if(istext(AY46),"No LTV",if(or(isblank(AY42),AY42=0),0,Round(AY46/AY54,2)))) -> No LTV | BA31: =if(isblank(BA36),"--",if(istext(BA46),"No LTV",if(or(isblank(BA42),BA42=0),0,Round(BA46/BA54,2)))) -> No LTV | BC31: =if(isblank(BC36),"--",if(istext(BC46),"No LTV",if(or(isblank(BC42),BC42=0),0,Round(BC46/BC54,2)))) -> No LTV | BE31: =if(isblank(BE36),"--",if(istext(BE46),"No LTV",if(or(isblank(BE42),BE42=0),0,Round(BE46/BE54,2)))) -> No LTV | BG31: =if(isblank(BG36),"--",if(istext(BG46),"No LTV",if(or(isblank(BG42),BG42=0),0,Round(BG46/BG54,2)))) -> No LTV | BI31: =if(isblank(BI36),"--",if(istext(BI46),"No LTV",if(or(isblank(BI42),BI42=0),0,Round(BI46/BI54,2)))) -> No LTV | BK31: =if(isblank(BK36),"--",if(istext(BK46),"No LTV",if(or(isblank(BK42),BK42=0),0,Round(BK46/BK54,2)))) -> No LTV | BM31: =if(isblank(BM36),"--",if(istext(BM46),"No LTV",if(or(isblank(BM42),BM42=0),0,Round(BM46/BM54,2)))) -> #DIV/0! | BO31: =if(isblank(BO36),"--",if(istext(BO46),"No LTV",if(or(isblank(BO42),BO42=0),0,Round(BO46/BO54,2)))) -> 1036.06
B32: Total Ad Spend | E32: =if(sum(G32:BP32)=0,"--",sum(G32:BP32)) -> 164186.15 | G32: 1662.15 | I32: 181.09 | K32: 3490.73 | M32: 1319.05 | O32: 7.97 | Q32: 605.92 | S32: 1474.72 | U32: 2864.7 | W32: 3523.12 | Y32: 1897.8 | AA32: 2119.79 | AC32: 1520.59 | AE32: 0 | AG32: 2748.43 | AI32: 1290.81 | AK32: 9238.63 | AM32: 35811.47 | AO32: 4278.5 | AQ32: 6674.98 | AS32: 32027.72 | AU32: 7945.56 | AW32: 13917.67 | AY32: 7970.71 | BA32: 14095.62 | BC32: =2650 -> 2650 | BE32: =650 -> 650 | BG32: 0 | BI32: 4218.42 | BK32: 0 | BM32: 0 | BO32: 0
B33: Resource Cost | E33: =567941/2 -> 283970.5 | G33: =(G32/$E$32)*$E$33 -> 2874.7953 | I33: =(I32/$E$32)*$E$33 -> 313.2068 | K33: =(K32/$E$32)*$E$33 -> 6037.4419 | M33: =(M32/$E$32)*$E$33 -> 2281.3818 | O33: =(O32/$E$32)*$E$33 -> 13.784627 | Q33: =(Q32/$E$32)*$E$33 -> 1047.9776 | S33: =(S32/$E$32)*$E$33 -> 2550.623 | U33: =(U32/$E$32)*$E$33 -> 4954.6828 | W33: =(W32/$E$32)*$E$33 -> 6093.4625 | Y33: =(Y32/$E$32)*$E$33 -> 3282.3671 | AA33: =(AA32/$E$32)*$E$33 -> 3666.3131 | AC33: =(AC32/$E$32)*$E$33 -> 2629.9581 | AE33: =(AE32/$E$32)*$E$33 -> 0 | AG33: =(AG32/$E$32)*$E$33 -> 4753.5863 | AI33: =(AI32/$E$32)*$E$33 -> 2232.5389 | AK33: =(AK32/$E$32)*$E$33 -> 15978.804 | AM33: =(AM32/$E$32)*$E$33 -> 61938.239 | AO33: =(AO32/$E$32)*$E$33 -> 7399.9408 | AQ33: =(AQ32/$E$32)*$E$33 -> 11544.807 | AS33: =(AS32/$E$32)*$E$33 -> 55394 | AU33: =(AU32/$E$32)*$E$33 -> 13742.357 | AW33: =(AW32/$E$32)*$E$33 -> 24071.505 | AY33: =(AY32/$E$32)*$E$33 -> 13785.855 | BA33: =(BA32/$E$32)*$E$33 -> 24379.281 | BC33: =(BC32/$E$32)*$E$33 -> 4583.3453 | BE33: =(BE32/$E$32)*$E$33 -> 1124.2168 | BG33: =(BG32/$E$32)*$E$33 -> 0 | BI33: =(BI32/$E$32)*$E$33 -> 7296.0285 | BK33: =(BK32/$E$32)*$E$33 -> 0 | BM33: =(BM32/$E$32)*$E$33 -> 0 | BO33: =(BO32/$E$32)*$E$33 -> 0 | BQ33: =SUM(G33:BP33) -> 283970.5
G34: =G36/$E$36 -> 0.0098081979 | I34: =I36/$E$36 -> 0.0010685958 | K34: =K36/$E$36 -> 0.020598484 | M34: =M36/$E$36 -> 0.0077835956 | O34: =O36/$E$36 -> 4.7030255e-05 | Q34: =Q36/$E$36 -> 0.0035754795 | S34: =S36/$E$36 -> 0.0087021903 | U34: =U36/$E$36 -> 0.016904338 | W34: =W36/$E$36 -> 0.020789615 | Y34: =Y36/$E$36 -> 0.011198747 | AA34: =AA36/$E$36 -> 0.012508691 | AC34: =AC36/$E$36 -> 0.0089728651 | AE34: =AE36/$E$36 -> 0 | AG34: =AG36/$E$36 -> 0.016218239 | AI34: =AI36/$E$36 -> 0.0076169539 | AK34: =AK36/$E$36 -> 0.054516326 | AM34: =AM36/$E$36 -> 0.24034311 | AO34: =AO36/$E$36 -> 0.025247044 | AQ34: =AQ36/$E$36 -> 0.039388458 | AS34: =AS36/$E$36 -> 0.1889927 | AU34: =AU36/$E$36 -> 0.046886036 | AW34: =AW36/$E$36 -> 0.083488887 | AY34: =AY36/$E$36 -> 0.047034444 | BA34: =BA36/$E$36 -> 0.083176988 | BC34: =BC36/$E$36 -> 0.015637412 | BE34: =BE36/$E$36 -> 0.0038355917 | BG34: =BG36/$E$36 -> 0 | BI34: =BI36/$E$36 -> 0.024892518 | BK34: =BK36/$E$36 -> 0 | BM34: =BM36/$E$36 -> 0 | BO34: =BO36/$E$36 -> 0.00076745697
B35: Incentive Cost | E35: =if(sum(G35:BP35)=0,"--",sum(G35:BP35)) -> 14410 | AM35: =13425 -> 13425 | AW35: 630 | BO35: 355
B36: Total Spend | E36: =sum(E32:F33,E35) -> 462566.65 | G36: =sum(G32:H33,G35) -> 4536.9453 | I36: =sum(I32:J33,I35) -> 494.2968 | K36: =sum(K32:L33,K35) -> 9528.1719 | M36: =sum(M32:N33,M35) -> 3600.4318 | O36: =sum(O32:P33,O35) -> 21.754627 | Q36: =sum(Q32:R33,Q35) -> 1653.8976 | S36: =sum(S32:T33,S35) -> 4025.343 | U36: =sum(U32:V33,U35) -> 7819.3828 | W36: =sum(W32:X33,W35) -> 9616.5825 | Y36: =sum(Y32:Z33,Y35) -> 5180.1671 | AA36: =sum(AA32:AB33,AA35) -> 5786.1031 | AC36: =sum(AC32:AD33,AC35) -> 4150.5481 | AE36: =sum(AE32:AF33,AE35) -> 0 | AG36: =sum(AG32:AH33,AG35) -> 7502.0163 | AI36: =sum(AI32:AJ33,AI35) -> 3523.3489 | AK36: =sum(AK32:AL33,AK35) -> 25217.434 | AM36: =sum(AM32:AN33,AM35) -> 111174.71 | AO36: =sum(AO32:AP33,AO35) -> 11678.441 | AQ36: =sum(AQ32:AR33,AQ35) -> 18219.787 | AS36: =sum(AS32:AT33,AS35) -> 87421.72 | AU36: =sum(AU32:AV33,AU35) -> 21687.917 | AW36: =sum(AW32:AX33,AW35) -> 38619.175 | AY36: =sum(AY32:AZ33,AY35) -> 21756.565 | BA36: =sum(BA32:BB33,BA35) -> 38474.901 | BC36: =sum(BC32:BD33,BC35) -> 7233.3453 | BE36: =sum(BE32:BF33,BE35) -> 1774.2168 | BG36: =sum(BG32:BH33,BG35) -> 0 | BI36: =sum(BI32:BJ33,BI35) -> 11514.449 | BK36: =sum(BK32:BL33,BK35) -> 0 | BM36: =sum(BM32:BN33,BM35) -> 0 | BO36: =sum(BO32:BP33,BO35) -> 355
B37: Form Fills | E37: =if(isblank(B37),,if($E$36="--","--",sum(G37:BP37))) -> 285 | G37: 0 | I37: 1 | K37: 5 | M37: 1 | O37: 0 | Q37: 0 | S37: 3 | U37: 4 | W37: 1 | Y37: 2 | AA37: 4 | AC37: 0 | AE37: 0 | AG37: 0 | AI37: 0 | AK37: 1 | AM37: 79 | AO37: 7 | AQ37: 23 | AS37: 47 | AU37: 0 | AW37: 33 | AY37: 0 | BA37: 0 | BC37: 2 | BE37: 1 | BG37: 0 | BI37: 0 | BK37: 0 | BM37: 14 | BO37: 57
B38: Intro Held | E38: =if(isblank(B38),,if($E$36="--","--",sum(G38:BP38))) -> 134 | G38: 0 | I38: 1 | K38: 3 | M38: 0 | O38: 0 | Q38: 0 | S38: 1 | U38: 3 | W38: 0 | Y38: 2 | AA38: 2 | AC38: 0 | AE38: 0 | AG38: 0 | AI38: 0 | AK38: 0 | AM38: 36 | AO38: 1 | AQ38: 2 | AS38: 19 | AU38: 0 | AW38: 16 | AY38: 0 | BA38: 0 | BC38: 2 | BE38: 1 | BG38: 0 | BI38: 0 | BK38: 0 | BM38: 5 | BO38: 40
B39: Strat Call Held | E39: =if(isblank(B39),,if($E$36="--","--",sum(G39:BP39))) -> 45 | G39: 0 | I39: 0 | K39: 0 | M39: 0 | O39: 0 | Q39: 0 | S39: 0 | U39: 0 | W39: 3 | Y39: 0 | AA39: 0 | AC39: 0 | AE39: 0 | AG39: 0 | AI39: 0 | AK39: 0 | AM39: 3 | AO39: 1 | AQ39: 7 | AS39: 5 | AU39: 0 | AW39: 6 | AY39: 0 | BA39: 0 | BC39: 0 | BE39: 0 | BG39: 0 | BI39: 0 | BK39: 0 | BM39: 8 | BO39: 12
B40: Proposals | E40: =if(isblank(B40),,if($E$36="--","--",sum(G40:BP40))) -> 32 | G40: 0 | I40: 0 | K40: 0 | M40: 0 | O40: 0 | Q40: 0 | S40: 0 | U40: 0 | W40: 0 | Y40: 0 | AA40: 0 | AC40: 0 | AE40: 0 | AG40: 0 | AI40: 0 | AK40: 0 | AM40: 7 | AO40: 3 | AQ40: 0 | AS40: 7 | AU40: 0 | AW40: 0 | AY40: 0 | BA40: 0 | BC40: 0 | BE40: 0 | BG40: 0 | BI40: 0 | BK40: 0 | BM40: 0 | BO40: 15
E41: =if(isblank(B41),,if($E$36="--","--",sum(G41:BJ41))) | G41: 0 | I41: 0 | K41: 0 | M41: 0 | O41: 0 | Q41: 0 | S41: 0 | W41: 0 | Y41: 0 | AC41: 0 | AE41: 0 | AG41: 0 | AI41: 0 | AK41: 0 | AO41: 0 | AQ41: 0 | AU41: 0 | AY41: 0 | BA41: 0 | BC41: 0 | BE41: 0 | BG41: 0 | BI41: 0 | BK41: 0
B42: Customers | E42: =if(isblank(B42),,if($E$36="--","--",sum(G42:BP42))) -> 11 | G42: 0 | I42: 0 | K42: 0 | M42: 0 | O42: 0 | Q42: 0 | S42: 0 | U42: 0 | W42: 0 | Y42: 0 | AA42: 0 | AC42: 0 | AE42: 0 | AG42: 0 | AI42: 0 | AK42: 0 | AM42: 0 | AO42: 0 | AQ42: 0 | AS42: 0 | AU42: 0 | AW42: 3 | AY42: 0 | BA42: 0 | BC42: 0 | BE42: 0 | BG42: 0 | BI42: 0 | BK42: 0 | BM42: 3 | BO42: 5
B43: Channel-level AOV | E43: =if(X16="Yes",iferror(average(G43:BP43),""),X15) -> 5516.67 | AW43: 3041.67 | BM43: 3291.67 | BO43: 10216.67
B44: Total AOV | AW44: 60833.33 | BM44: 65833.33 | BO44: 122600
G45: =(G44*$AG$13)/(1-$AG$14) -> 0 | I45: =(I44*$AG$13)/(1-$AG$14) -> 0 | K45: =(K44*$AG$13)/(1-$AG$14) -> 0 | M45: =(M44*$AG$13)/(1-$AG$14) -> 0 | O45: =(O44*$AG$13)/(1-$AG$14) -> 0 | Q45: =(Q44*$AG$13)/(1-$AG$14) -> 0 | S45: =(S44*$AG$13)/(1-$AG$14) -> 0 | U45: =(U44*$AG$13)/(1-$AG$14) -> 0 | W45: =(W44*$AG$13)/(1-$AG$14) -> 0 | Y45: =(Y44*$AG$13)/(1-$AG$14) -> 0 | AA45: =(AA44*$AG$13)/(1-$AG$14) -> 0 | AC45: =(AC44*$AG$13)/(1-$AG$14) -> 0 | AE45: =(AE44*$AG$13)/(1-$AG$14) -> 0 | AG45: =(AG44*$AG$13)/(1-$AG$14) -> 0 | AI45: =(AI44*$AG$13)/(1-$AG$14) -> 0 | AK45: =(AK44*$AG$13)/(1-$AG$14) -> 0 | AM45: =(AM44*$AG$13)/(1-$AG$14) -> 0 | AO45: =(AO44*$AG$13)/(1-$AG$14) -> 0 | AQ45: =(AQ44*$AG$13)/(1-$AG$14) -> 0 | AS45: =(AS44*$AG$13)/(1-$AG$14) -> 0 | AU45: =(AU44*$AG$13)/(1-$AG$14) -> 0 | AW45: =(AW44*$AG$13)/(1-$AG$14) -> 54918.978 | AY45: =(AY44*$AG$13)/(1-$AG$14) -> 0 | BA45: =(BA44*$AG$13)/(1-$AG$14) -> 0 | BC45: =(BC44*$AG$13)/(1-$AG$14) -> 0 | BE45: =(BE44*$AG$13)/(1-$AG$14) -> 0 | BG45: =(BG44*$AG$13)/(1-$AG$14) -> 0 | BI45: =(BI44*$AG$13)/(1-$AG$14) -> 0 | BK45: =(BK44*$AG$13)/(1-$AG$14) -> 0 | BM45: =(BM44*$AG$13)/(1-$AG$14) -> 59432.867 | BO45: =(BO44*$AG$13)/(1-$AG$14) -> 110680.56
B46: Lifetime Value (LTV) | E46: =if(E36="--","--", if(X16="No",$X$17,iferror(average(G46:BP46),""))) -> 39720.024 | G46: =if($X$16="Yes",if(isblank(G36),"--",if(isblank($X$13),"Enter GM%",if(isblank($X$14),"Enter Lifespan",if(ISBLANK(G43),"Enter AOV",$X$13*$X$14*G43)))),if(isblank(G36),"--",$X$17)) -> Enter AOV | I46: =if($X$16="Yes",if(isblank(I36),"--",if(isblank($X$13),"Enter GM%",if(isblank($X$14),"Enter Lifespan",if(ISBLANK(I43),"Enter AOV",$X$13*$X$14*I43)))),if(isblank(I36),"--",$X$17)) -> Enter AOV | K46: =if($X$16="Yes",if(isblank(K36),"--",if(isblank($X$13),"Enter GM%",if(isblank($X$14),"Enter Lifespan",if(ISBLANK(K43),"Enter AOV",$X$13*$X$14*K43)))),if(isblank(K36),"--",$X$17)) -> Enter AOV | M46: =if($X$16="Yes",if(isblank(M36),"--",if(isblank($X$13),"Enter GM%",if(isblank($X$14),"Enter Lifespan",if(ISBLANK(M43),"Enter AOV",$X$13*$X$14*M43)))),if(isblank(M36),"--",$X$17)) -> Enter AOV | O46: =if($X$16="Yes",if(isblank(O36),"--",if(isblank($X$13),"Enter GM%",if(isblank($X$14),"Enter Lifespan",if(ISBLANK(O43),"Enter AOV",$X$13*$X$14*O43)))),if(isblank(O36),"--",$X$17)) -> Enter AOV | Q46: =if($X$16="Yes",if(isblank(Q36),"--",if(isblank($X$13),"Enter GM%",if(isblank($X$14),"Enter Lifespan",if(ISBLANK(Q43),"Enter AOV",$X$13*$X$14*Q43)))),if(isblank(Q36),"--",$X$17)) -> Enter AOV | S46: =if($X$16="Yes",if(isblank(S36),"--",if(isblank($X$13),"Enter GM%",if(isblank($X$14),"Enter Lifespan",if(ISBLANK(S43),"Enter AOV",$X$13*$X$14*S43)))),if(isblank(S36),"--",$X$17)) -> Enter AOV | U46: =if($X$16="Yes",if(isblank(U36),"--",if(isblank($X$13),"Enter GM%",if(isblank($X$14),"Enter Lifespan",if(ISBLANK(U43),"Enter AOV",$X$13*$X$14*U43)))),if(isblank(U36),"--",$X$17)) -> Enter AOV | W46: =if($X$16="Yes",if(isblank(W36),"--",if(isblank($X$13),"Enter GM%",if(isblank($X$14),"Enter Lifespan",if(ISBLANK(W43),"Enter AOV",$X$13*$X$14*W43)))),if(isblank(W36),"--",$X$17)) -> Enter AOV | Y46: =if($X$16="Yes",if(isblank(Y36),"--",if(isblank($X$13),"Enter GM%",if(isblank($X$14),"Enter Lifespan",if(ISBLANK(Y43),"Enter AOV",$X$13*$X$14*Y43)))),if(isblank(Y36),"--",$X$17)) -> Enter AOV | AA46: =if($X$16="Yes",if(isblank(AA36),"--",if(isblank($X$13),"Enter GM%",if(isblank($X$14),"Enter Lifespan",if(ISBLANK(AA43),"Enter AOV",$X$13*$X$14*AA43)))),if(isblank(AA36),"--",$X$17)) -> Enter AOV | AC46: =if($X$16="Yes",if(isblank(AC36),"--",if(isblank($X$13),"Enter GM%",if(isblank($X$14),"Enter Lifespan",if(ISBLANK(AC43),"Enter AOV",$X$13*$X$14*AC43)))),if(isblank(AC36),"--",$X$17)) -> Enter AOV | AE46: =if($X$16="Yes",if(isblank(AE36),"--",if(isblank($X$13),"Enter GM%",if(isblank($X$14),"Enter Lifespan",if(ISBLANK(AE43),"Enter AOV",$X$13*$X$14*AE43)))),if(isblank(AE36),"--",$X$17)) -> Enter AOV | AG46: =if($X$16="Yes",if(isblank(AG36),"--",if(isblank($X$13),"Enter GM%",if(isblank($X$14),"Enter Lifespan",if(ISBLANK(AG43),"Enter AOV",$X$13*$X$14*AG43)))),if(isblank(AG36),"--",$X$17)) -> Enter AOV | AI46: =if($X$16="Yes",if(isblank(AI36),"--",if(isblank($X$13),"Enter GM%",if(isblank($X$14),"Enter Lifespan",if(ISBLANK(AI43),"Enter AOV",$X$13*$X$14*AI43)))),if(isblank(AI36),"--",$X$17)) -> Enter AOV | AK46: =if($X$16="Yes",if(isblank(AK36),"--",if(isblank($X$13),"Enter GM%",if(isblank($X$14),"Enter Lifespan",if(ISBLANK(AK43),"Enter AOV",$X$13*$X$14*AK43)))),if(isblank(AK36),"--",$X$17)) -> Enter AOV | AM46: =if($X$16="Yes",if(isblank(AM36),"--",if(isblank($X$13),"Enter GM%",if(isblank($X$14),"Enter Lifespan",if(ISBLANK(AM43),"Enter AOV",$X$13*$X$14*AM43)))),if(isblank(AM36),"--",$X$17)) -> Enter AOV | AO46: =if($X$16="Yes",if(isblank(AO36),"--",if(isblank($X$13),"Enter GM%",if(isblank($X$14),"Enter Lifespan",if(ISBLANK(AO43),"Enter AOV",$X$13*$X$14*AO43)))),if(isblank(AO36),"--",$X$17)) -> Enter AOV | AQ46: =if($X$16="Yes",if(isblank(AQ36),"--",if(isblank($X$13),"Enter GM%",if(isblank($X$14),"Enter Lifespan",if(ISBLANK(AQ43),"Enter AOV",$X$13*$X$14*AQ43)))),if(isblank(AQ36),"--",$X$17)) -> Enter AOV | AS46: =if($X$16="Yes",if(isblank(AS36),"--",if(isblank($X$13),"Enter GM%",if(isblank($X$14),"Enter Lifespan",if(ISBLANK(AS43),"Enter AOV",$X$13*$X$14*AS43)))),if(isblank(AS36),"--",$X$17)) -> Enter AOV | AU46: =if($X$16="Yes",if(isblank(AU36),"--",if(isblank($X$13),"Enter GM%",if(isblank($X$14),"Enter Lifespan",if(ISBLANK(AU43),"Enter AOV",$X$13*$X$14*AU43)))),if(isblank(AU36),"--",$X$17)) -> Enter AOV | AW46: =if($X$16="Yes",if(isblank(AW36),"--",if(isblank($X$13),"Enter GM%",if(isblank($X$14),"Enter Lifespan",if(ISBLANK(AW43),"Enter AOV",$X$13*$X$14*AW43)))),if(isblank(AW36),"--",$X$17)) -> 21900.024 | AY46: =if($X$16="Yes",if(isblank(AY36),"--",if(isblank($X$13),"Enter GM%",if(isblank($X$14),"Enter Lifespan",if(ISBLANK(AY43),"Enter AOV",$X$13*$X$14*AY43)))),if(isblank(AY36),"--",$X$17)) -> Enter AOV | BA46: =if($X$16="Yes",if(isblank(BA36),"--",if(isblank($X$13),"Enter GM%",if(isblank($X$14),"Enter Lifespan",if(ISBLANK(BA43),"Enter AOV",$X$13*$X$14*BA43)))),if(isblank(BA36),"--",$X$17)) -> Enter AOV | BC46: =if($X$16="Yes",if(isblank(BC36),"--",if(isblank($X$13),"Enter GM%",if(isblank($X$14),"Enter Lifespan",if(ISBLANK(BC43),"Enter AOV",$X$13*$X$14*BC43)))),if(isblank(BC36),"--",$X$17)) -> Enter AOV | BE46: =if($X$16="Yes",if(isblank(BE36),"--",if(isblank($X$13),"Enter GM%",if(isblank($X$14),"Enter Lifespan",if(ISBLANK(BE43),"Enter AOV",$X$13*$X$14*BE43)))),if(isblank(BE36),"--",$X$17)) -> Enter AOV | BG46: =if($X$16="Yes",if(isblank(BG36),"--",if(isblank($X$13),"Enter GM%",if(isblank($X$14),"Enter Lifespan",if(ISBLANK(BG43),"Enter AOV",$X$13*$X$14*BG43)))),if(isblank(BG36),"--",$X$17)) -> Enter AOV | BI46: =if($X$16="Yes",if(isblank(BI36),"--",if(isblank($X$13),"Enter GM%",if(isblank($X$14),"Enter Lifespan",if(ISBLANK(BI43),"Enter AOV",$X$13*$X$14*BI43)))),if(isblank(BI36),"--",$X$17)) -> Enter AOV | BK46: =if($X$16="Yes",if(isblank(BK36),"--",if(isblank($X$13),"Enter GM%",if(isblank($X$14),"Enter Lifespan",if(ISBLANK(BK43),"Enter AOV",$X$13*$X$14*BK43)))),if(isblank(BK36),"--",$X$17)) -> Enter AOV | BM46: =if($X$16="Yes",if(isblank(BM36),"--",if(isblank($X$13),"Enter GM%",if(isblank($X$14),"Enter Lifespan",if(ISBLANK(BM43),"Enter AOV",$X$13*$X$14*BM43)))),if(isblank(BM36),"--",$X$17)) -> 23700.024 | BO46: =if($X$16="Yes",if(isblank(BO36),"--",if(isblank($X$13),"Enter GM%",if(isblank($X$14),"Enter Lifespan",if(ISBLANK(BO43),"Enter AOV",$X$13*$X$14*BO43)))),if(isblank(BO36),"--",$X$17)) -> 73560.024
B47: Total Est. Bookings | E47: =if(E36="--","--",sum(G47:BP47)) -> 504600.26 | G47: =if(isblank(G36),"--",if(or(isblank(G42),G42=0),"No Customers",if(isnumber(G46),G46*G42,"No LTV"))) -> No Customers | I47: =if(isblank(I36),"--",if(or(isblank(I42),I42=0),"No Customers",if(isnumber(I46),I46*I42,"No LTV"))) -> No Customers | K47: =if(isblank(K36),"--",if(or(isblank(K42),K42=0),"No Customers",if(isnumber(K46),K46*K42,"No LTV"))) -> No Customers | M47: =if(isblank(M36),"--",if(or(isblank(M42),M42=0),"No Customers",if(isnumber(M46),M46*M42,"No LTV"))) -> No Customers | O47: =if(isblank(O36),"--",if(or(isblank(O42),O42=0),"No Customers",if(isnumber(O46),O46*O42,"No LTV"))) -> No Customers | Q47: =if(isblank(Q36),"--",if(or(isblank(Q42),Q42=0),"No Customers",if(isnumber(Q46),Q46*Q42,"No LTV"))) -> No Customers | S47: =if(isblank(S36),"--",if(or(isblank(S42),S42=0),"No Customers",if(isnumber(S46),S46*S42,"No LTV"))) -> No Customers | U47: =if(isblank(U36),"--",if(or(isblank(U42),U42=0),"No Customers",if(isnumber(U46),U46*U42,"No LTV"))) -> No Customers | W47: =if(isblank(W36),"--",if(or(isblank(W42),W42=0),"No Customers",if(isnumber(W46),W46*W42,"No LTV"))) -> No Customers | Y47: =if(isblank(Y36),"--",if(or(isblank(Y42),Y42=0),"No Customers",if(isnumber(Y46),Y46*Y42,"No LTV"))) -> No Customers | AA47: =if(isblank(AA36),"--",if(or(isblank(AA42),AA42=0),"No Customers",if(isnumber(AA46),AA46*AA42,"No LTV"))) -> No Customers | AC47: =if(isblank(AC36),"--",if(or(isblank(AC42),AC42=0),"No Customers",if(isnumber(AC46),AC46*AC42,"No LTV"))) -> No Customers | AE47: =if(isblank(AE36),"--",if(or(isblank(AE42),AE42=0),"No Customers",if(isnumber(AE46),AE46*AE42,"No LTV"))) -> No Customers | AG47: =if(isblank(AG36),"--",if(or(isblank(AG42),AG42=0),"No Customers",if(isnumber(AG46),AG46*AG42,"No LTV"))) -> No Customers | AI47: =if(isblank(AI36),"--",if(or(isblank(AI42),AI42=0),"No Customers",if(isnumber(AI46),AI46*AI42,"No LTV"))) -> No Customers | AK47: =if(isblank(AK36),"--",if(or(isblank(AK42),AK42=0),"No Customers",if(isnumber(AK46),AK46*AK42,"No LTV"))) -> No Customers | AM47: =if(isblank(AM36),"--",if(or(isblank(AM42),AM42=0),"No Customers",if(isnumber(AM46),AM46*AM42,"No LTV"))) -> No Customers | AO47: =if(isblank(AO36),"--",if(or(isblank(AO42),AO42=0),"No Customers",if(isnumber(AO46),AO46*AO42,"No LTV"))) -> No Customers | AQ47: =if(isblank(AQ36),"--",if(or(isblank(AQ42),AQ42=0),"No Customers",if(isnumber(AQ46),AQ46*AQ42,"No LTV"))) -> No Customers | AS47: =if(isblank(AS36),"--",if(or(isblank(AS42),AS42=0),"No Customers",if(isnumber(AS46),AS46*AS42,"No LTV"))) -> No Customers | AU47: =if(isblank(AU36),"--",if(or(isblank(AU42),AU42=0),"No Customers",if(isnumber(AU46),AU46*AU42,"No LTV"))) -> No Customers | AW47: =if(isblank(AW36),"--",if(or(isblank(AW42),AW42=0),"No Customers",if(isnumber(AW46),AW46*AW42,"No LTV"))) -> 65700.072 | AY47: =if(isblank(AY36),"--",if(or(isblank(AY42),AY42=0),"No Customers",if(isnumber(AY46),AY46*AY42,"No LTV"))) -> No Customers | BA47: =if(isblank(BA36),"--",if(or(isblank(BA42),BA42=0),"No Customers",if(isnumber(BA46),BA46*BA42,"No LTV"))) -> No Customers | BC47: =if(isblank(BC36),"--",if(or(isblank(BC42),BC42=0),"No Customers",if(isnumber(BC46),BC46*BC42,"No LTV"))) -> No Customers | BE47: =if(isblank(BE36),"--",if(or(isblank(BE42),BE42=0),"No Customers",if(isnumber(BE46),BE46*BE42,"No LTV"))) -> No Customers | BG47: =if(isblank(BG36),"--",if(or(isblank(BG42),BG42=0),"No Customers",if(isnumber(BG46),BG46*BG42,"No LTV"))) -> No Customers | BI47: =if(isblank(BI36),"--",if(or(isblank(BI42),BI42=0),"No Customers",if(isnumber(BI46),BI46*BI42,"No LTV"))) -> No Customers | BK47: =if(isblank(BK36),"--",if(or(isblank(BK42),BK42=0),"No Customers",if(isnumber(BK46),BK46*BK42,"No LTV"))) -> No Customers | BM47: =if(isblank(BM36),"--",if(or(isblank(BM42),BM42=0),"No Customers",if(isnumber(BM46),BM46*BM42,"No LTV"))) -> 71100.072 | BO47: =if(isblank(BO36),"--",if(or(isblank(BO42),BO42=0),"No Customers",if(isnumber(BO46),BO46*BO42,"No LTV"))) -> 367800.12
B48: Net Return | E48: =if(E36="--","--",sum(G48:BP48)) -> 465626.09 | G48: =if(isblank(G36),"--",if(istext(G47),G47,G47-G36)) -> No Customers | I48: =if(isblank(I36),"--",if(istext(I47),I47,I47-I36)) -> No Customers | K48: =if(isblank(K36),"--",if(istext(K47),K47,K47-K36)) -> No Customers | M48: =if(isblank(M36),"--",if(istext(M47),M47,M47-M36)) -> No Customers | O48: =if(isblank(O36),"--",if(istext(O47),O47,O47-O36)) -> No Customers | Q48: =if(isblank(Q36),"--",if(istext(Q47),Q47,Q47-Q36)) -> No Customers | S48: =if(isblank(S36),"--",if(istext(S47),S47,S47-S36)) -> No Customers | U48: =if(isblank(U36),"--",if(istext(U47),U47,U47-U36)) -> No Customers | W48: =if(isblank(W36),"--",if(istext(W47),W47,W47-W36)) -> No Customers | Y48: =if(isblank(Y36),"--",if(istext(Y47),Y47,Y47-Y36)) -> No Customers | AA48: =if(isblank(AA36),"--",if(istext(AA47),AA47,AA47-AA36)) -> No Customers | AC48: =if(isblank(AC36),"--",if(istext(AC47),AC47,AC47-AC36)) -> No Customers | AE48: =if(isblank(AE36),"--",if(istext(AE47),AE47,AE47-AE36)) -> No Customers | AG48: =if(isblank(AG36),"--",if(istext(AG47),AG47,AG47-AG36)) -> No Customers | AI48: =if(isblank(AI36),"--",if(istext(AI47),AI47,AI47-AI36)) -> No Customers | AK48: =if(isblank(AK36),"--",if(istext(AK47),AK47,AK47-AK36)) -> No Customers | AM48: =if(isblank(AM36),"--",if(istext(AM47),AM47,AM47-AM36)) -> No Customers | AO48: =if(isblank(AO36),"--",if(istext(AO47),AO47,AO47-AO36)) -> No Customers | AQ48: =if(isblank(AQ36),"--",if(istext(AQ47),AQ47,AQ47-AQ36)) -> No Customers | AS48: =if(isblank(AS36),"--",if(istext(AS47),AS47,AS47-AS36)) -> No Customers | AU48: =if(isblank(AU36),"--",if(istext(AU47),AU47,AU47-AU36)) -> No Customers | AW48: =if(isblank(AW36),"--",if(istext(AW47),AW47,AW47-AW36)) -> 27080.897 | AY48: =if(isblank(AY36),"--",if(istext(AY47),AY47,AY47-AY36)) -> No Customers | BA48: =if(isblank(BA36),"--",if(istext(BA47),BA47,BA47-BA36)) -> No Customers | BC48: =if(isblank(BC36),"--",if(istext(BC47),BC47,BC47-BC36)) -> No Customers | BE48: =if(isblank(BE36),"--",if(istext(BE47),BE47,BE47-BE36)) -> No Customers | BG48: =if(isblank(BG36),"--",if(istext(BG47),BG47,BG47-BG36)) -> No Customers | BI48: =if(isblank(BI36),"--",if(istext(BI47),BI47,BI47-BI36)) -> No Customers | BK48: =if(isblank(BK36),"--",if(istext(BK47),BK47,BK47-BK36)) -> No Customers | BM48: =if(isblank(BM36),"--",if(istext(BM47),BM47,BM47-BM36)) -> 71100.072 | BO48: =if(isblank(BO36),"--",if(istext(BO47),BO47,BO47-BO36)) -> 367445.12
B49: Cost-per-Form Fill | E49: =iferror($E$36/E37,"--") -> 1623.0409 | G49: =iferror(G$36/G37,"--") -> -- | I49: =iferror(I$36/I37,"--") -> 494.2968 | K49: =iferror(K$36/K37,"--") -> 1905.6344 | M49: =iferror(M$36/M37,"--") -> 3600.4318 | O49: =iferror(O$36/O37,"--") -> -- | Q49: =iferror(Q$36/Q37,"--") -> -- | S49: =iferror(S$36/S37,"--") -> 1341.781 | U49: =iferror(U$36/U37,"--") -> 1954.8457 | W49: =iferror(W$36/W37,"--") -> 9616.5825 | Y49: =iferror(Y$36/Y37,"--") -> 2590.0835 | AA49: =iferror(AA$36/AA37,"--") -> 1446.5258 | AC49: =iferror(AC$36/AC37,"--") -> -- | AE49: =iferror(AE$36/AE37,"--") -> -- | AG49: =iferror(AG$36/AG37,"--") -> -- | AI49: =iferror(AI$36/AI37,"--") -> -- | AK49: =iferror(AK$36/AK37,"--") -> 25217.434 | AM49: =iferror(AM$36/AM37,"--") -> 1407.2748 | AO49: =iferror(AO$36/AO37,"--") -> 1668.3487 | AQ49: =iferror(AQ$36/AQ37,"--") -> 792.16465 | AS49: =iferror(AS$36/AS37,"--") -> 1860.0366 | AU49: =iferror(AU$36/AU37,"--") -> -- | AW49: =iferror(AW$36/AW37,"--") -> 1170.278 | AY49: =iferror(AY$36/AY37,"--") -> -- | BA49: =iferror(BA$36/BA37,"--") -> -- | BC49: =iferror(BC$36/BC37,"--") -> 3616.6727 | BE49: =iferror(BE$36/BE37,"--") -> 1774.2168 | BG49: =iferror(BG$36/BG37,"--") -> -- | BI49: =iferror(BI$36/BI37,"--") -> -- | BK49: =iferror(BK$36/BK37,"--") -> -- | BM49: =iferror(BM$36/BM37,"--") -> 0 | BO49: =iferror(BO$36/BO37,"--") -> 6.2280702
B50: Cost-per-Intro Held | E50: =iferror($E$36/E38,"--") -> 3451.9899 | G50: =iferror(G$36/G38,"--") -> -- | I50: =iferror(I$36/I38,"--") -> 494.2968 | K50: =iferror(K$36/K38,"--") -> 3176.0573 | M50: =iferror(M$36/M38,"--") -> -- | O50: =iferror(O$36/O38,"--") -> -- | Q50: =iferror(Q$36/Q38,"--") -> -- | S50: =iferror(S$36/S38,"--") -> 4025.343 | U50: =iferror(U$36/U38,"--") -> 2606.4609 | W50: =iferror(W$36/W38,"--") -> -- | Y50: =iferror(Y$36/Y38,"--") -> 2590.0835 | AA50: =iferror(AA$36/AA38,"--") -> 2893.0515 | AC50: =iferror(AC$36/AC38,"--") -> -- | AE50: =iferror(AE$36/AE38,"--") -> -- | AG50: =iferror(AG$36/AG38,"--") -> -- | AI50: =iferror(AI$36/AI38,"--") -> -- | AK50: =iferror(AK$36/AK38,"--") -> -- | AM50: =iferror(AM$36/AM38,"--") -> 3088.1864 | AO50: =iferror(AO$36/AO38,"--") -> 11678.441 | AQ50: =iferror(AQ$36/AQ38,"--") -> 9109.8935 | AS50: =iferror(AS$36/AS38,"--") -> 4601.1432 | AU50: =iferror(AU$36/AU38,"--") -> -- | AW50: =iferror(AW$36/AW38,"--") -> 2413.6984 | AY50: =iferror(AY$36/AY38,"--") -> -- | BA50: =iferror(BA$36/BA38,"--") -> -- | BC50: =iferror(BC$36/BC38,"--") -> 3616.6727 | BE50: =iferror(BE$36/BE38,"--") -> 1774.2168 | BG50: =iferror(BG$36/BG38,"--") -> -- | BI50: =iferror(BI$36/BI38,"--") -> -- | BK50: =iferror(BK$36/BK38,"--") -> -- | BM50: =iferror(BM$36/BM38,"--") -> 0 | BO50: =iferror(BO$36/BO38,"--") -> 8.875
B51: Cost-per-Strat Call Held | E51: =iferror($E$36/E39,"--") -> 10279.259 | G51: =iferror(G$36/G39,"--") -> -- | I51: =iferror(I$36/I39,"--") -> -- | K51: =iferror(K$36/K39,"--") -> -- | M51: =iferror(M$36/M39,"--") -> -- | O51: =iferror(O$36/O39,"--") -> -- | Q51: =iferror(Q$36/Q39,"--") -> -- | S51: =iferror(S$36/S39,"--") -> -- | U51: =iferror(U$36/U39,"--") -> -- | W51: =iferror(W$36/W39,"--") -> 3205.5275 | Y51: =iferror(Y$36/Y39,"--") -> -- | AA51: =iferror(AA$36/AA39,"--") -> -- | AC51: =iferror(AC$36/AC39,"--") -> -- | AE51: =iferror(AE$36/AE39,"--") -> -- | AG51: =iferror(AG$36/AG39,"--") -> -- | AI51: =iferror(AI$36/AI39,"--") -> -- | AK51: =iferror(AK$36/AK39,"--") -> -- | AM51: =iferror(AM$36/AM39,"--") -> 37058.236 | AO51: =iferror(AO$36/AO39,"--") -> 11678.441 | AQ51: =iferror(AQ$36/AQ39,"--") -> 2602.8267 | AS51: =iferror(AS$36/AS39,"--") -> 17484.344 | AU51: =iferror(AU$36/AU39,"--") -> -- | AW51: =iferror(AW$36/AW39,"--") -> 6436.5291 | AY51: =iferror(AY$36/AY39,"--") -> -- | BA51: =iferror(BA$36/BA39,"--") -> -- | BC51: =iferror(BC$36/BC39,"--") -> -- | BE51: =iferror(BE$36/BE39,"--") -> -- | BG51: =iferror(BG$36/BG39,"--") -> -- | BI51: =iferror(BI$36/BI39,"--") -> -- | BK51: =iferror(BK$36/BK39,"--") -> -- | BM51: =iferror(BM$36/BM39,"--") -> 0 | BO51: =iferror(BO$36/BO39,"--") -> 29.583333
B52: Cost-per-Proposal | E52: =iferror($E$36/E40,"--") -> 14455.208 | G52: =iferror(G$36/G40,"--") -> -- | I52: =iferror(I$36/I40,"--") -> -- | K52: =iferror(K$36/K40,"--") -> -- | M52: =iferror(M$36/M40,"--") -> -- | O52: =iferror(O$36/O40,"--") -> -- | Q52: =iferror(Q$36/Q40,"--") -> -- | S52: =iferror(S$36/S40,"--") -> -- | U52: =iferror(U$36/U40,"--") -> -- | W52: =iferror(W$36/W40,"--") -> -- | Y52: =iferror(Y$36/Y40,"--") -> -- | AA52: =iferror(AA$36/AA40,"--") -> -- | AC52: =iferror(AC$36/AC40,"--") -> -- | AE52: =iferror(AE$36/AE40,"--") -> -- | AG52: =iferror(AG$36/AG40,"--") -> -- | AI52: =iferror(AI$36/AI40,"--") -> -- | AK52: =iferror(AK$36/AK40,"--") -> -- | AM52: =iferror(AM$36/AM40,"--") -> 15882.101 | AO52: =iferror(AO$36/AO40,"--") -> 3892.8136 | AQ52: =iferror(AQ$36/AQ40,"--") -> -- | AS52: =iferror(AS$36/AS40,"--") -> 12488.817 | AU52: =iferror(AU$36/AU40,"--") -> -- | AW52: =iferror(AW$36/AW40,"--") -> -- | AY52: =iferror(AY$36/AY40,"--") -> -- | BA52: =iferror(BA$36/BA40,"--") -> -- | BC52: =iferror(BC$36/BC40,"--") -> -- | BE52: =iferror(BE$36/BE40,"--") -> -- | BG52: =iferror(BG$36/BG40,"--") -> -- | BI52: =iferror(BI$36/BI40,"--") -> -- | BK52: =iferror(BK$36/BK40,"--") -> -- | BM52: =iferror(BM$36/BM40,"--") -> -- | BO52: =iferror(BO$36/BO40,"--") -> 23.666667
B53: -- | E53: =iferror($E$36/E41,"--") -> -- | G53: =iferror(G$36/G41,"--") -> -- | I53: =iferror(I$36/I41,"--") -> -- | K53: =iferror(K$36/K41,"--") -> -- | M53: =iferror(M$36/M41,"--") -> -- | O53: =iferror(O$36/O41,"--") -> -- | Q53: =iferror(Q$36/Q41,"--") -> -- | S53: =iferror(S$36/S41,"--") -> -- | U53: =iferror(U$36/U41,"--") -> -- | W53: =iferror(W$36/W41,"--") -> -- | Y53: =iferror(Y$36/Y41,"--") -> -- | AA53: =iferror(AA$36/AA41,"--") -> -- | AC53: =iferror(AC$36/AC41,"--") -> -- | AE53: =iferror(AE$36/AE41,"--") -> -- | AG53: =iferror(AG$36/AG41,"--") -> -- | AI53: =iferror(AI$36/AI41,"--") -> -- | AK53: =iferror(AK$36/AK41,"--") -> -- | AM53: =iferror(AM$36/AM41,"--") -> -- | AO53: =iferror(AO$36/AO41,"--") -> -- | AQ53: =iferror(AQ$36/AQ41,"--") -> -- | AS53: =iferror(AS$36/AS41,"--") -> -- | AU53: =iferror(AU$36/AU41,"--") -> -- | AW53: =iferror(AW$36/AW41,"--") -> -- | AY53: =iferror(AY$36/AY41,"--") -> -- | BA53: =iferror(BA$36/BA41,"--") -> -- | BC53: =iferror(BC$36/BC41,"--") -> -- | BE53: =iferror(BE$36/BE41,"--") -> -- | BG53: =iferror(BG$36/BG41,"--") -> -- | BI53: =iferror(BI$36/BI41,"--") -> -- | BK53: =iferror(BK$36/BK41,"--") -> -- | BM53: =iferror(BM$36/BM41,"--") -> -- | BO53: =iferror(BO$36/BO41,"--") -> --
B54: Cost-per-Customer | E54: =iferror($E$36/E42,"--") -> 42051.514 | G54: =iferror(G$36/G42,"--") -> -- | I54: =iferror(I$36/I42,"--") -> -- | K54: =iferror(K$36/K42,"--") -> -- | M54: =iferror(M$36/M42,"--") -> -- | O54: =iferror(O$36/O42,"--") -> -- | Q54: =iferror(Q$36/Q42,"--") -> -- | S54: =iferror(S$36/S42,"--") -> -- | U54: =iferror(U$36/U42,"--") -> -- | W54: =iferror(W$36/W42,"--") -> -- | Y54: =iferror(Y$36/Y42,"--") -> -- | AA54: =iferror(AA$36/AA42,"--") -> -- | AC54: =iferror(AC$36/AC42,"--") -> -- | AE54: =iferror(AE$36/AE42,"--") -> -- | AG54: =iferror(AG$36/AG42,"--") -> -- | AI54: =iferror(AI$36/AI42,"--") -> -- | AK54: =iferror(AK$36/AK42,"--") -> -- | AM54: =iferror(AM$36/AM42,"--") -> -- | AO54: =iferror(AO$36/AO42,"--") -> -- | AQ54: =iferror(AQ$36/AQ42,"--") -> -- | AS54: =iferror(AS$36/AS42,"--") -> -- | AU54: =iferror(AU$36/AU42,"--") -> -- | AW54: =iferror(AW$36/AW42,"--") -> 12873.058 | AY54: =iferror(AY$36/AY42,"--") -> -- | BA54: =iferror(BA$36/BA42,"--") -> -- | BC54: =iferror(BC$36/BC42,"--") -> -- | BE54: =iferror(BE$36/BE42,"--") -> -- | BG54: =iferror(BG$36/BG42,"--") -> -- | BI54: =iferror(BI$36/BI42,"--") -> -- | BK54: =iferror(BK$36/BK42,"--") -> -- | BM54: =iferror(BM$36/BM42,"--") -> 0 | BO54: =iferror(BO$36/BO42,"--") -> 71
B55: Form Fill > Intro Held | E55: =iferror(if(match(B37,$B$37:$B$41,0)=Counta($B$37:$B$41),$E$42/E37,E38/E37),"--") -> 0.47017544 | G55: =iferror(if(match($B$37,$B$37:$B$41,0)=Counta($B$37:$B$41),G42/G37,G38/G37),"--") -> -- | I55: =iferror(if(match($B$37,$B$37:$B$41,0)=Counta($B$37:$B$41),I42/I37,I38/I37),"--") -> 1 | K55: =iferror(if(match($B$37,$B$37:$B$41,0)=Counta($B$37:$B$41),K42/K37,K38/K37),"--") -> 0.6 | M55: =iferror(if(match($B$37,$B$37:$B$41,0)=Counta($B$37:$B$41),M42/M37,M38/M37),"--") -> 0 | O55: =iferror(if(match($B$37,$B$37:$B$41,0)=Counta($B$37:$B$41),O42/O37,O38/O37),"--") -> -- | Q55: =iferror(if(match($B$37,$B$37:$B$41,0)=Counta($B$37:$B$41),Q42/Q37,Q38/Q37),"--") -> -- | S55: =iferror(if(match($B$37,$B$37:$B$41,0)=Counta($B$37:$B$41),S42/S37,S38/S37),"--") -> 0.33333333 | U55: =iferror(if(match($B$37,$B$37:$B$41,0)=Counta($B$37:$B$41),U42/U37,U38/U37),"--") -> 0.75 | W55: =iferror(if(match($B$37,$B$37:$B$41,0)=Counta($B$37:$B$41),W42/W37,W38/W37),"--") -> 0 | Y55: =iferror(if(match($B$37,$B$37:$B$41,0)=Counta($B$37:$B$41),Y42/Y37,Y38/Y37),"--") -> 1 | AA55: =iferror(if(match($B$37,$B$37:$B$41,0)=Counta($B$37:$B$41),AA42/AA37,AA38/AA37),"--") -> 0.5 | AC55: =iferror(if(match($B$37,$B$37:$B$41,0)=Counta($B$37:$B$41),AC42/AC37,AC38/AC37),"--") -> -- | AE55: =iferror(if(match($B$37,$B$37:$B$41,0)=Counta($B$37:$B$41),AE42/AE37,AE38/AE37),"--") -> -- | AG55: =iferror(if(match($B$37,$B$37:$B$41,0)=Counta($B$37:$B$41),AG42/AG37,AG38/AG37),"--") -> -- | AI55: =iferror(if(match($B$37,$B$37:$B$41,0)=Counta($B$37:$B$41),AI42/AI37,AI38/AI37),"--") -> -- | AK55: =iferror(if(match($B$37,$B$37:$B$41,0)=Counta($B$37:$B$41),AK42/AK37,AK38/AK37),"--") -> 0 | AM55: =iferror(if(match($B$37,$B$37:$B$41,0)=Counta($B$37:$B$41),AM42/AM37,AM38/AM37),"--") -> 0.4556962 | AO55: =iferror(if(match($B$37,$B$37:$B$41,0)=Counta($B$37:$B$41),AO42/AO37,AO38/AO37),"--") -> 0.14285714 | AQ55: =iferror(if(match($B$37,$B$37:$B$41,0)=Counta($B$37:$B$41),AQ42/AQ37,AQ38/AQ37),"--") -> 0.086956522 | AS55: =iferror(if(match($B$37,$B$37:$B$41,0)=Counta($B$37:$B$41),AS42/AS37,AS38/AS37),"--") -> 0.40425532 | AU55: =iferror(if(match($B$37,$B$37:$B$41,0)=Counta($B$37:$B$41),AU42/AU37,AU38/AU37),"--") -> -- | AW55: =iferror(if(match($B$37,$B$37:$B$41,0)=Counta($B$37:$B$41),AW42/AW37,AW38/AW37),"--") -> 0.48484848 | AY55: =iferror(if(match($B$37,$B$37:$B$41,0)=Counta($B$37:$B$41),AY42/AY37,AY38/AY37),"--") -> -- | BA55: =iferror(if(match($B$37,$B$37:$B$41,0)=Counta($B$37:$B$41),BA42/BA37,BA38/BA37),"--") -> -- | BC55: =iferror(if(match($B$37,$B$37:$B$41,0)=Counta($B$37:$B$41),BC42/BC37,BC38/BC37),"--") -> 1 | BE55: =iferror(if(match($B$37,$B$37:$B$41,0)=Counta($B$37:$B$41),BE42/BE37,BE38/BE37),"--") -> 1 | BG55: =iferror(if(match($B$37,$B$37:$B$41,0)=Counta($B$37:$B$41),BG42/BG37,BG38/BG37),"--") -> -- | BI55: =iferror(if(match($B$37,$B$37:$B$41,0)=Counta($B$37:$B$41),BI42/BI37,BI38/BI37),"--") -> -- | BK55: =iferror(if(match($B$37,$B$37:$B$41,0)=Counta($B$37:$B$41),BK42/BK37,BK38/BK37),"--") -> -- | BM55: =iferror(if(match($B$37,$B$37:$B$41,0)=Counta($B$37:$B$41),BM42/BM37,BM38/BM37),"--") -> 0.35714286 | BO55: =iferror(if(match($B$37,$B$37:$B$41,0)=Counta($B$37:$B$41),BO42/BO37,BO38/BO37),"--") -> 0.70175439
B56: Intro Held > Strat Call Held | E56: =iferror(if(match(B38,$B$37:$B$41,0)=Counta($B$37:$B$41),$E$42/E38,E39/E38),"--") -> 0.3358209 | G56: =iferror(if(match($B$38,$B$37:$B$41,0)=Counta($B$37:$B$41),G42/G38,G39/G38),"--") -> -- | I56: =iferror(if(match($B$38,$B$37:$B$41,0)=Counta($B$37:$B$41),I42/I38,I39/I38),"--") -> 0 | K56: =iferror(if(match($B$38,$B$37:$B$41,0)=Counta($B$37:$B$41),K42/K38,K39/K38),"--") -> 0 | M56: =iferror(if(match($B$38,$B$37:$B$41,0)=Counta($B$37:$B$41),M42/M38,M39/M38),"--") -> -- | O56: =iferror(if(match($B$38,$B$37:$B$41,0)=Counta($B$37:$B$41),O42/O38,O39/O38),"--") -> -- | Q56: =iferror(if(match($B$38,$B$37:$B$41,0)=Counta($B$37:$B$41),Q42/Q38,Q39/Q38),"--") -> -- | S56: =iferror(if(match($B$38,$B$37:$B$41,0)=Counta($B$37:$B$41),S42/S38,S39/S38),"--") -> 0 | U56: =iferror(if(match($B$38,$B$37:$B$41,0)=Counta($B$37:$B$41),U42/U38,U39/U38),"--") -> 0 | W56: =iferror(if(match($B$38,$B$37:$B$41,0)=Counta($B$37:$B$41),W42/W38,W39/W38),"--") -> -- | Y56: =iferror(if(match($B$38,$B$37:$B$41,0)=Counta($B$37:$B$41),Y42/Y38,Y39/Y38),"--") -> 0 | AA56: =iferror(if(match($B$38,$B$37:$B$41,0)=Counta($B$37:$B$41),AA42/AA38,AA39/AA38),"--") -> 0 | AC56: =iferror(if(match($B$38,$B$37:$B$41,0)=Counta($B$37:$B$41),AC42/AC38,AC39/AC38),"--") -> -- | AE56: =iferror(if(match($B$38,$B$37:$B$41,0)=Counta($B$37:$B$41),AE42/AE38,AE39/AE38),"--") -> -- | AG56: =iferror(if(match($B$38,$B$37:$B$41,0)=Counta($B$37:$B$41),AG42/AG38,AG39/AG38),"--") -> -- | AI56: =iferror(if(match($B$38,$B$37:$B$41,0)=Counta($B$37:$B$41),AI42/AI38,AI39/AI38),"--") -> -- | AK56: =iferror(if(match($B$38,$B$37:$B$41,0)=Counta($B$37:$B$41),AK42/AK38,AK39/AK38),"--") -> -- | AM56: =iferror(if(match($B$38,$B$37:$B$41,0)=Counta($B$37:$B$41),AM42/AM38,AM39/AM38),"--") -> 0.083333333 | AO56: =iferror(if(match($B$38,$B$37:$B$41,0)=Counta($B$37:$B$41),AO42/AO38,AO39/AO38),"--") -> 1 | AQ56: =iferror(if(match($B$38,$B$37:$B$41,0)=Counta($B$37:$B$41),AQ42/AQ38,AQ39/AQ38),"--") -> 3.5 | AS56: =iferror(if(match($B$38,$B$37:$B$41,0)=Counta($B$37:$B$41),AS42/AS38,AS39/AS38),"--") -> 0.26315789 | AU56: =iferror(if(match($B$38,$B$37:$B$41,0)=Counta($B$37:$B$41),AU42/AU38,AU39/AU38),"--") -> -- | AW56: =iferror(if(match($B$38,$B$37:$B$41,0)=Counta($B$37:$B$41),AW42/AW38,AW39/AW38),"--") -> 0.375 | AY56: =iferror(if(match($B$38,$B$37:$B$41,0)=Counta($B$37:$B$41),AY42/AY38,AY39/AY38),"--") -> -- | BA56: =iferror(if(match($B$38,$B$37:$B$41,0)=Counta($B$37:$B$41),BA42/BA38,BA39/BA38),"--") -> -- | BC56: =iferror(if(match($B$38,$B$37:$B$41,0)=Counta($B$37:$B$41),BC42/BC38,BC39/BC38),"--") -> 0 | BE56: =iferror(if(match($B$38,$B$37:$B$41,0)=Counta($B$37:$B$41),BE42/BE38,BE39/BE38),"--") -> 0 | BG56: =iferror(if(match($B$38,$B$37:$B$41,0)=Counta($B$37:$B$41),BG42/BG38,BG39/BG38),"--") -> -- | BI56: =iferror(if(match($B$38,$B$37:$B$41,0)=Counta($B$37:$B$41),BI42/BI38,BI39/BI38),"--") -> -- | BK56: =iferror(if(match($B$38,$B$37:$B$41,0)=Counta($B$37:$B$41),BK42/BK38,BK39/BK38),"--") -> -- | BM56: =iferror(if(match($B$38,$B$37:$B$41,0)=Counta($B$37:$B$41),BM42/BM38,BM39/BM38),"--") -> 1.6 | BO56: =iferror(if(match($B$38,$B$37:$B$41,0)=Counta($B$37:$B$41),BO42/BO38,BO39/BO38),"--") -> 0.3
B57: Strat Call Held > Proposal | E57: =iferror(if(match(B39,$B$37:$B$41,0)=Counta($B$37:$B$41),$E$42/E39,E40/E39),"--") -> 0.71111111 | G57: =iferror(if(match($B$39,$B$37:$B$41,0)=Counta($B$37:$B$41),G42/G39,G40/G39),"--") -> -- | I57: =iferror(if(match($B$39,$B$37:$B$41,0)=Counta($B$37:$B$41),I42/I39,I40/I39),"--") -> -- | K57: =iferror(if(match($B$39,$B$37:$B$41,0)=Counta($B$37:$B$41),K42/K39,K40/K39),"--") -> -- | M57: =iferror(if(match($B$39,$B$37:$B$41,0)=Counta($B$37:$B$41),M42/M39,M40/M39),"--") -> -- | O57: =iferror(if(match($B$39,$B$37:$B$41,0)=Counta($B$37:$B$41),O42/O39,O40/O39),"--") -> -- | Q57: =iferror(if(match($B$39,$B$37:$B$41,0)=Counta($B$37:$B$41),Q42/Q39,Q40/Q39),"--") -> -- | S57: =iferror(if(match($B$39,$B$37:$B$41,0)=Counta($B$37:$B$41),S42/S39,S40/S39),"--") -> -- | U57: =iferror(if(match($B$39,$B$37:$B$41,0)=Counta($B$37:$B$41),U42/U39,U40/U39),"--") -> -- | W57: =iferror(if(match($B$39,$B$37:$B$41,0)=Counta($B$37:$B$41),W42/W39,W40/W39),"--") -> 0 | Y57: =iferror(if(match($B$39,$B$37:$B$41,0)=Counta($B$37:$B$41),Y42/Y39,Y40/Y39),"--") -> -- | AA57: =iferror(if(match($B$39,$B$37:$B$41,0)=Counta($B$37:$B$41),AA42/AA39,AA40/AA39),"--") -> -- | AC57: =iferror(if(match($B$39,$B$37:$B$41,0)=Counta($B$37:$B$41),AC42/AC39,AC40/AC39),"--") -> -- | AE57: =iferror(if(match($B$39,$B$37:$B$41,0)=Counta($B$37:$B$41),AE42/AE39,AE40/AE39),"--") -> -- | AG57: =iferror(if(match($B$39,$B$37:$B$41,0)=Counta($B$37:$B$41),AG42/AG39,AG40/AG39),"--") -> -- | AI57: =iferror(if(match($B$39,$B$37:$B$41,0)=Counta($B$37:$B$41),AI42/AI39,AI40/AI39),"--") -> -- | AK57: =iferror(if(match($B$39,$B$37:$B$41,0)=Counta($B$37:$B$41),AK42/AK39,AK40/AK39),"--") -> -- | AM57: =iferror(if(match($B$39,$B$37:$B$41,0)=Counta($B$37:$B$41),AM42/AM39,AM40/AM39),"--") -> 2.3333333 | AO57: =iferror(if(match($B$39,$B$37:$B$41,0)=Counta($B$37:$B$41),AO42/AO39,AO40/AO39),"--") -> 3 | AQ57: =iferror(if(match($B$39,$B$37:$B$41,0)=Counta($B$37:$B$41),AQ42/AQ39,AQ40/AQ39),"--") -> 0 | AS57: =iferror(if(match($B$39,$B$37:$B$41,0)=Counta($B$37:$B$41),AS42/AS39,AS40/AS39),"--") -> 1.4 | AU57: =iferror(if(match($B$39,$B$37:$B$41,0)=Counta($B$37:$B$41),AU42/AU39,AU40/AU39),"--") -> -- | AW57: =iferror(if(match($B$39,$B$37:$B$41,0)=Counta($B$37:$B$41),AW42/AW39,AW40/AW39),"--") -> 0 | AY57: =iferror(if(match($B$39,$B$37:$B$41,0)=Counta($B$37:$B$41),AY42/AY39,AY40/AY39),"--") -> -- | BA57: =iferror(if(match($B$39,$B$37:$B$41,0)=Counta($B$37:$B$41),BA42/BA39,BA40/BA39),"--") -> -- | BC57: =iferror(if(match($B$39,$B$37:$B$41,0)=Counta($B$37:$B$41),BC42/BC39,BC40/BC39),"--") -> -- | BE57: =iferror(if(match($B$39,$B$37:$B$41,0)=Counta($B$37:$B$41),BE42/BE39,BE40/BE39),"--") -> -- | BG57: =iferror(if(match($B$39,$B$37:$B$41,0)=Counta($B$37:$B$41),BG42/BG39,BG40/BG39),"--") -> -- | BI57: =iferror(if(match($B$39,$B$37:$B$41,0)=Counta($B$37:$B$41),BI42/BI39,BI40/BI39),"--") -> -- | BK57: =iferror(if(match($B$39,$B$37:$B$41,0)=Counta($B$37:$B$41),BK42/BK39,BK40/BK39),"--") -> -- | BM57: =iferror(if(match($B$39,$B$37:$B$41,0)=Counta($B$37:$B$41),BM42/BM39,BM40/BM39),"--") -> 0 | BO57: =iferror(if(match($B$39,$B$37:$B$41,0)=Counta($B$37:$B$41),BO42/BO39,BO40/BO39),"--") -> 1.25
B58: Proposal > Customer | E58: =iferror(if(match(B40,$B$37:$B$41,0)=Counta($B$37:$B$41),$E$42/E40,E41/E40),"--") -> 0.34375 | G58: =iferror(if(match($B$40,$B$37:$B$41,0)=Counta($B$37:$B$41),G42/G40,G41/G40),"--") -> -- | I58: =iferror(if(match($B$40,$B$37:$B$41,0)=Counta($B$37:$B$41),I42/I40,I41/I40),"--") -> -- | K58: =iferror(if(match($B$40,$B$37:$B$41,0)=Counta($B$37:$B$41),K42/K40,K41/K40),"--") -> -- | M58: =iferror(if(match($B$40,$B$37:$B$41,0)=Counta($B$37:$B$41),M42/M40,M41/M40),"--") -> -- | O58: =iferror(if(match($B$40,$B$37:$B$41,0)=Counta($B$37:$B$41),O42/O40,O41/O40),"--") -> -- | Q58: =iferror(if(match($B$40,$B$37:$B$41,0)=Counta($B$37:$B$41),Q42/Q40,Q41/Q40),"--") -> -- | S58: =iferror(if(match($B$40,$B$37:$B$41,0)=Counta($B$37:$B$41),S42/S40,S41/S40),"--") -> -- | U58: =iferror(if(match($B$40,$B$37:$B$41,0)=Counta($B$37:$B$41),U42/U40,U41/U40),"--") -> -- | W58: =iferror(if(match($B$40,$B$37:$B$41,0)=Counta($B$37:$B$41),W42/W40,W41/W40),"--") -> -- | Y58: =iferror(if(match($B$40,$B$37:$B$41,0)=Counta($B$37:$B$41),Y42/Y40,Y41/Y40),"--") -> -- | AA58: =iferror(if(match($B$40,$B$37:$B$41,0)=Counta($B$37:$B$41),AA42/AA40,AA41/AA40),"--") -> -- | AC58: =iferror(if(match($B$40,$B$37:$B$41,0)=Counta($B$37:$B$41),AC42/AC40,AC41/AC40),"--") -> -- | AE58: =iferror(if(match($B$40,$B$37:$B$41,0)=Counta($B$37:$B$41),AE42/AE40,AE41/AE40),"--") -> -- | AG58: =iferror(if(match($B$40,$B$37:$B$41,0)=Counta($B$37:$B$41),AG42/AG40,AG41/AG40),"--") -> -- | AI58: =iferror(if(match($B$40,$B$37:$B$41,0)=Counta($B$37:$B$41),AI42/AI40,AI41/AI40),"--") -> -- | AK58: =iferror(if(match($B$40,$B$37:$B$41,0)=Counta($B$37:$B$41),AK42/AK40,AK41/AK40),"--") -> -- | AM58: =iferror(if(match($B$40,$B$37:$B$41,0)=Counta($B$37:$B$41),AM42/AM40,AM41/AM40),"--") -> 0 | AO58: =iferror(if(match($B$40,$B$37:$B$41,0)=Counta($B$37:$B$41),AO42/AO40,AO41/AO40),"--") -> 0 | AQ58: =iferror(if(match($B$40,$B$37:$B$41,0)=Counta($B$37:$B$41),AQ42/AQ40,AQ41/AQ40),"--") -> -- | AS58: =iferror(if(match($B$40,$B$37:$B$41,0)=Counta($B$37:$B$41),AS42/AS40,AS41/AS40),"--") -> 0 | AU58: =iferror(if(match($B$40,$B$37:$B$41,0)=Counta($B$37:$B$41),AU42/AU40,AU41/AU40),"--") -> -- | AW58: =iferror(if(match($B$40,$B$37:$B$41,0)=Counta($B$37:$B$41),AW42/AW40,AW41/AW40),"--") -> -- | AY58: =iferror(if(match($B$40,$B$37:$B$41,0)=Counta($B$37:$B$41),AY42/AY40,AY41/AY40),"--") -> -- | BA58: =iferror(if(match($B$40,$B$37:$B$41,0)=Counta($B$37:$B$41),BA42/BA40,BA41/BA40),"--") -> -- | BC58: =iferror(if(match($B$40,$B$37:$B$41,0)=Counta($B$37:$B$41),BC42/BC40,BC41/BC40),"--") -> -- | BE58: =iferror(if(match($B$40,$B$37:$B$41,0)=Counta($B$37:$B$41),BE42/BE40,BE41/BE40),"--") -> -- | BG58: =iferror(if(match($B$40,$B$37:$B$41,0)=Counta($B$37:$B$41),BG42/BG40,BG41/BG40),"--") -> -- | BI58: =iferror(if(match($B$40,$B$37:$B$41,0)=Counta($B$37:$B$41),BI42/BI40,BI41/BI40),"--") -> -- | BK58: =iferror(if(match($B$40,$B$37:$B$41,0)=Counta($B$37:$B$41),BK42/BK40,BK41/BK40),"--") -> -- | BM58: =iferror(if(match($B$40,$B$37:$B$41,0)=Counta($B$37:$B$41),BM42/BM40,BM41/BM40),"--") -> -- | BO58: =iferror(if(match($B$40,$B$37:$B$41,0)=Counta($B$37:$B$41),BO42/BO40,BO41/BO40),"--") -> 0.33333333
B59: -- | E59: =iferror(if(match(B41,$B$37:$B$41,0)=Counta($B$37:$B$41),$E$42/E41,E42/E41),"--") -> -- | G59: =iferror(if(match($B$41,$B$37:$B$41,0)=Counta($B$37:$B$41),G42/G41,G42/G41),"--") -> -- | I59: =iferror(if(match($B$41,$B$37:$B$41,0)=Counta($B$37:$B$41),I42/I41,I42/I41),"--") -> -- | K59: =iferror(if(match($B$41,$B$37:$B$41,0)=Counta($B$37:$B$41),K42/K41,K42/K41),"--") -> -- | M59: =iferror(if(match($B$41,$B$37:$B$41,0)=Counta($B$37:$B$41),M42/M41,M42/M41),"--") -> -- | O59: =iferror(if(match($B$41,$B$37:$B$41,0)=Counta($B$37:$B$41),O42/O41,O42/O41),"--") -> -- | Q59: =iferror(if(match($B$41,$B$37:$B$41,0)=Counta($B$37:$B$41),Q42/Q41,Q42/Q41),"--") -> -- | S59: =iferror(if(match($B$41,$B$37:$B$41,0)=Counta($B$37:$B$41),S42/S41,S42/S41),"--") -> -- | U59: =iferror(if(match($B$41,$B$37:$B$41,0)=Counta($B$37:$B$41),U42/U41,U42/U41),"--") -> -- | W59: =iferror(if(match($B$41,$B$37:$B$41,0)=Counta($B$37:$B$41),W42/W41,W42/W41),"--") -> -- | Y59: =iferror(if(match($B$41,$B$37:$B$41,0)=Counta($B$37:$B$41),Y42/Y41,Y42/Y41),"--") -> -- | AA59: =iferror(if(match($B$41,$B$37:$B$41,0)=Counta($B$37:$B$41),AA42/AA41,AA42/AA41),"--") -> -- | AC59: =iferror(if(match($B$41,$B$37:$B$41,0)=Counta($B$37:$B$41),AC42/AC41,AC42/AC41),"--") -> -- | AE59: =iferror(if(match($B$41,$B$37:$B$41,0)=Counta($B$37:$B$41),AE42/AE41,AE42/AE41),"--") -> -- | AG59: =iferror(if(match($B$41,$B$37:$B$41,0)=Counta($B$37:$B$41),AG42/AG41,AG42/AG41),"--") -> -- | AI59: =iferror(if(match($B$41,$B$37:$B$41,0)=Counta($B$37:$B$41),AI42/AI41,AI42/AI41),"--") -> -- | AK59: =iferror(if(match($B$41,$B$37:$B$41,0)=Counta($B$37:$B$41),AK42/AK41,AK42/AK41),"--") -> -- | AM59: =iferror(if(match($B$41,$B$37:$B$41,0)=Counta($B$37:$B$41),AM42/AM41,AM42/AM41),"--") -> -- | AO59: =iferror(if(match($B$41,$B$37:$B$41,0)=Counta($B$37:$B$41),AO42/AO41,AO42/AO41),"--") -> -- | AQ59: =iferror(if(match($B$41,$B$37:$B$41,0)=Counta($B$37:$B$41),AQ42/AQ41,AQ42/AQ41),"--") -> -- | AS59: =iferror(if(match($B$41,$B$37:$B$41,0)=Counta($B$37:$B$41),AS42/AS41,AS42/AS41),"--") -> -- | AU59: =iferror(if(match($B$41,$B$37:$B$41,0)=Counta($B$37:$B$41),AU42/AU41,AU42/AU41),"--") -> -- | AW59: =iferror(if(match($B$41,$B$37:$B$41,0)=Counta($B$37:$B$41),AW42/AW41,AW42/AW41),"--") -> -- | AY59: =iferror(if(match($B$41,$B$37:$B$41,0)=Counta($B$37:$B$41),AY42/AY41,AY42/AY41),"--") -> -- | BA59: =iferror(if(match($B$41,$B$37:$B$41,0)=Counta($B$37:$B$41),BA42/BA41,BA42/BA41),"--") -> -- | BC59: =iferror(if(match($B$41,$B$37:$B$41,0)=Counta($B$37:$B$41),BC42/BC41,BC42/BC41),"--") -> -- | BE59: =iferror(if(match($B$41,$B$37:$B$41,0)=Counta($B$37:$B$41),BE42/BE41,BE42/BE41),"--") -> -- | BG59: =iferror(if(match($B$41,$B$37:$B$41,0)=Counta($B$37:$B$41),BG42/BG41,BG42/BG41),"--") -> -- | BI59: =iferror(if(match($B$41,$B$37:$B$41,0)=Counta($B$37:$B$41),BI42/BI41,BI42/BI41),"--") -> -- | BK59: =iferror(if(match($B$41,$B$37:$B$41,0)=Counta($B$37:$B$41),BK42/BK41,BK42/BK41),"--") -> -- | BM59: =iferror(if(match($B$41,$B$37:$B$41,0)=Counta($B$37:$B$41),BM42/BM41,BM42/BM41),"--") -> -- | BO59: =iferror(if(match($B$41,$B$37:$B$41,0)=Counta($B$37:$B$41),BO42/BO41,BO42/BO41),"--") -> --
